Workbook
Name NativeTimeline_Dia: #N/A
Name NativeTimeline_Dia1: #N/A
Name NativeTimeline_Dia11: #N/A
Name NativeTimeline_Dia111: #N/A
Name NativeTimeline_Dia2: #N/A
Name NativeTimeline_Dia21: #N/A

Sheet PROVISÃO 2026
C2: AGROPECUÁRIA ARAMBURU
B6: Rótulos de Linha | C6: JANEIRO | D6: FEVEREIRO | E6: MARÇO | F6: ABRIL | G6: MAIO | H6: JUNHO | I6: JULHO | J6: AGOSTO | K6: SETEMBRO | L6: OUTUBRO | M6: NOVEMBRO | N6: DEZEMBRO | O6: Total Geral
B7: 1.1 – Saldo Inicial | C7: 383789.58 | O7: 383789.58
B8: 1.2 – Receita de Arrendamento de Terras | C8: 960000 | E8: 1793031.1 | I8: 760234.22 | O8: 3513265.3
B9: 1.8 – Resgate de Aplicações | C9: 179865.44 | D9: 47205.93 | E9: 15920.67 | F9: 4768 | G9: 4768 | H9: 0 | I9: 0 | J9: 0 | K9: 0 | L9: 0 | M9: 0 | N9: 0 | O9: 252528.04
B10: 1.9 – Outros Recebimentos | C10: 1878 | O10: 1878
B11: 2.1 – Despesas Administrativas | C11: -33968.09 | D11: -18402.09 | E11: -6971.07 | F11: -51971.07 | G11: -198707 | H11: -6971.07 | I11: -53515.29 | J11: -7249.07 | K11: -126971.07 | L11: -61971.07 | M11: -9258.07 | N11: -9258.07 | O11: -585213.03
B12: 2.2 – Despesas com Pessoal | C12: -8126.78 | D12: -7926.78 | E12: -7926.78 | F12: -7926.78 | G12: -7926.78 | H12: -7926.78 | I12: -7926.78 | J12: -7926.78 | K12: -13893.45 | L12: -3436.36 | M12: -10426.78 | N12: -11923.14 | O12: -103293.97
B13: 2.3 – Operação da Propriedade | C13: -18852.23 | D13: -19016.93 | E13: -19016.93 | F13: -19016.93 | G13: -19016.93 | H13: -19016.93 | I13: -18892.73 | J13: -318738.93 | K13: -19016.93 | L13: -9016.93 | M13: -19016.93 | N13: -19016.93 | O13: -517636.26
B14: 2.4 – Serviços Terceirizados | C14: -70 | D14: -70 | E14: -70 | F14: -70 | G14: -70 | H14: -70 | I14: -70 | J14: -70 | K14: -70 | L14: -70 | M14: -70 | N14: -70 | O14: -840
B15: 2.5 – Financeiras e Bancárias | C15: -334.75 | D15: -334.75 | E15: -334.75 | F15: -334.75 | G15: -334.75 | H15: -156.5 | I15: -156.5 | J15: -156.5 | K15: -156.5 | L15: -156.5 | M15: -156.5 | N15: -156.5 | O15: -2769.25
B16: 2.6 – Investimentos em Capital | C16: -100000 | F16: -383638.43 | O16: -483638.43
B17: 2.7 – Investimentos em Imobilizado Operacional | C17: -179030.89 | D17: -47205.93 | E17: -15920.67 | F17: -4768 | G17: -4768 | O17: -251693.49
B18: 2.8 – Distribuição de Lucro / Saídas Pessoais | C18: -110898.43 | D18: -95882.15 | E18: -731538.86 | F18: -91092.05 | G18: -83595.44 | H18: -97547.8 | I18: -77110.04 | J18: -184529.18 | K18: -128066.17 | L18: -152528.31 | M18: -128154.04 | N18: -142702.46 | O18: -2023644.9
B19: 2.9 – Outras Saídas | C19: -1878 | O19: -1878
B20: Total Geral | C20: 1072373.8 | D20: -141632.7 | E20: 1027172.7 | F20: -554050.01 | G20: -309650.9 | H20: -131689.08 | I20: 602562.88 | J20: -518670.46 | K20: -288174.12 | L20: -227179.17 | M20: -167082.32 | N20: -183127.1 | O20: 180853.55
C23: DISTRIBUIÇÃO DE LUCRO
B27: Rótulos de Linha | C27: JANEIRO | D27: FEVEREIRO | E27: MARÇO | F27: ABRIL | G27: MAIO | H27: JUNHO | I27: JULHO | J27: AGOSTO | K27: SETEMBRO | L27: OUTUBRO | M27: NOVEMBRO | N27: DEZEMBRO | O27: Total Geral
B28: Ana Beatriz Ponte Fragelli | E28: 557991.07 | O28: 557991.07
B29: 1.6 - Contratos de Venda | E29: 557991.07 | O29: 557991.07
B30: Repasse Venda Soja 24/25 | E30: 557991.07 | O30: 557991.07
B31: Claudio Luiz Resta Fragelli | C31: 62771.64 | D31: 33169.7 | E31: 74147.2 | F31: 39418.96 | G31: 36267.34 | H31: 39719.7 | I31: 35781.94 | J31: 70290.84 | K31: 42355.33 | L31: 48717.47 | M31: 33185.7 | N31: 43019.7 | O31: 558845.52
B32: 1.1 - Imóvel | C32: 39559.35 | D32: 15616.54 | E32: 15616.54 | F32: 15616.54 | G32: 15616.54 | H32: 15616.54 | I32: 15616.54 | J32: 15616.54 | K32: 15616.54 | L32: 15616.54 | M32: 15616.54 | N32: 15616.54 | O32: 211341.29
B33: Reforma Programada | C33: 2000 | D33: 2000 | E33: 2000 | F33: 2000 | G33: 2000 | H33: 2000 | I33: 2000 | J33: 2000 | K33: 2000 | L33: 2000 | M33: 2000 | N33: 2000 | O33: 24000
B34: Parcelamento (Residência SC) | C34: 13616.54 | D34: 13616.54 | E34: 13616.54 | F34: 13616.54 | G34: 13616.54 | H34: 13616.54 | I34: 13616.54 | J34: 13616.54 | K34: 13616.54 | L34: 13616.54 | M34: 13616.54 | N34: 13616.54 | O34: 163398.48
B35: IPTU (Casa Vila Inventário) | C35: 1507.96 | O35: 1507.96
B36: IPTU (Forest House) | C36: 5102.87 | O36: 5102.87
B37: IPTU (R. Margina Humberlina Lima 80) | C37: 2280.61 | O37: 2280.61
B38: IPTU (R. Margina Humberlina Lima 90) | C38: 2287.21 | O38: 2287.21
B39: IPTU (Atmosphera) | C39: 10476.95 | O39: 10476.95
B40: IPTU (R. Appa 201) | C40: 2287.21 | O40: 2287.21
B41: 1.3 - Renda Mensal/Qualidade de Vida | C41: 4565.99 | D41: 4118.25 | E41: 48845.75 | F41: 4118.25 | G41: 4118.25 | H41: 14218.25 | I41: 4118.25 | J41: 40745.75 | K41: 12218.25 | L41: 21118.25 | M41: 4118.25 | N41: 14218.25 | O41: 176521.74
B42: Distribuição Fixa | C42: 3105 | D42: 3105 | E42: 3105 | F42: 3105 | G42: 3105 | H42: 3105 | I42: 3105 | J42: 3105 | K42: 3105 | L42: 3105 | M42: 3105 | N42: 3105 | O42: 37260
B43: Custos Emergenciais | C43: 300 | D43: 300 | E43: 300 | F43: 300 | G43: 300 | H43: 300 | I43: 300 | J43: 300 | K43: 300 | L43: 300 | M43: 300 | N43: 300 | O43: 3600
B44: Medicamentos | C44: 713.25 | D44: 713.25 | E44: 713.25 | F44: 713.25 | G44: 713.25 | H44: 713.25 | I44: 713.25 | J44: 713.25 | K44: 713.25 | L44: 713.25 | M44: 713.25 | N44: 713.25 | O44: 8559
B45: Tratamento Dentário | E45: 500 | H45: 2500 | K45: 500 | N45: 2500 | O45: 6000
B46: Troca de Celular | C46: 447.74 | O46: 447.74
B47: Viagem Internacional | E47: 36627.5 | J47: 36627.5 | O47: 73255
B48: Viagem Trimestral | E48: 7600 | H48: 7600 | K48: 7600 | N48: 7600 | O48: 30400
B49: Viagem Final de Ano | L49: 17000 | O49: 17000
B50: 1.4 - Despesas Pessoais | C50: 7624.21 | D50: 692.66 | E50: 692.66 | F50: 10691.92 | G50: 7540.3 | H50: 892.66 | I50: 692.66 | J50: 931.02 | K50: 992.66 | L50: 692.66 | M50: 1198.66 | N50: 692.66 | O50: 33334.73
B51: Manutenção Conta Bradesco | C51: 150 | D51: 150 | E51: 150 | F51: 150 | G51: 150 | H51: 150 | I51: 150 | J51: 150 | K51: 150 | L51: 150 | M51: 150 | N51: 150 | O51: 1800
B52: Vivo Família Móvel | C52: 542.66 | D52: 542.66 | E52: 542.66 | F52: 542.66 | G52: 542.66 | H52: 542.66 | I52: 542.66 | J52: 542.66 | K52: 542.66 | L52: 542.66 | M52: 542.66 | N52: 542.66 | O52: 6511.92
B53: Troca de Pneus | C53: 3200 | O53: 3200
B54: Seguro Veículo | F54: 7969.26 | O54: 7969.26
B55: Revisão Veículo | F55: 2030 | O55: 2030
B56: IPVA - Triton Sport (SLZ-8B58) | C56: 3731.55 | O56: 3731.55
B57: Renovação OFC Certificado Digital | H57: 200 | O57: 200
B58: Cempar - Manutenção Anual Jazigo | M58: 506 | O58: 506
B59: IRPF 2026 | G59: 6847.64 | O59: 6847.64
B60: Licenciamento 2026 (Placas SLZ-8B58) da Triton Sport | J60: 238.36 | O60: 238.36
B61: ITR 2026 - Estância Ivone | K61: 300 | O61: 300
B62: 1.5 - Fazenda Aramburu | C62: 11022.09 | D62: 12742.25 | E62: 8992.25 | F62: 8992.25 | G62: 8992.25 | H62: 8992.25 | I62: 15354.49 | J62: 12997.53 | K62: 13527.88 | L62: 11290.02 | M62: 12252.25 | N62: 12492.25 | O62: 137647.76
B63: Energisa (Fazenda Aramburu) | C63: 860.91 | D63: 860.91 | E63: 860.91 | F63: 860.91 | G63: 860.91 | H63: 860.91 | I63: 860.91 | J63: 860.91 | K63: 860.91 | L63: 860.91 | M63: 860.91 | N63: 860.91 | O63: 10330.92
B64: FGTS Folha de Pgto | D64: 410 | E64: 410 | F64: 410 | G64: 410 | H64: 410 | I64: 410 | J64: 410 | K64: 410 | L64: 410 | M64: 410 | N64: 410 | O64: 4510
B65: INSS Folha de Pgto | C65: 466.34 | D65: 466.34 | E65: 466.34 | F65: 466.34 | G65: 466.34 | H65: 466.34 | I65: 466.34 | J65: 466.34 | K65: 466.34 | L65: 466.34 | M65: 466.34 | N65: 466.34 | O65: 5596.08
B66: IPVA - Triton L200 (NRY-0578) | C66: 1753.35 | O66: 1753.35
B67: Serviços Advocatícios Ação Civil Pública nº 0900021-98.2020.8.12.0014 | D67: 3750 | O67: 3750
B68: Folha de Pgto - Amadeu Fava Junior | C68: 2297.77 | D68: 2300 | E68: 2300 | F68: 2300 | G68: 2300 | H68: 2300 | I68: 2300 | J68: 2300 | K68: 2300 | L68: 2300 | M68: 2300 | N68: 2300 | O68: 27597.77
B69: Folha de Pgto - Cristiane da Silva Freire | C69: 1469.15 | D69: 1405 | E69: 1405 | F69: 1405 | G69: 1405 | H69: 1405 | I69: 1405 | J69: 1405 | K69: 1405 | L69: 1405 | M69: 1405 | N69: 1405 | O69: 16924.15
B70: Pluxee Multibenefícios - Amadeu Fava Junior | C70: 450 | D70: 450 | E70: 450 | F70: 450 | G70: 450 | H70: 450 | I70: 450 | J70: 450 | K70: 450 | L70: 450 | M70: 450 | N70: 450 | O70: 5400
B71: Pluxee Multibenefícios - Cristiane da Silva Freire | C71: 350 | D71: 350 | E71: 350 | F71: 350 | G71: 350 | H71: 350 | I71: 350 | J71: 350 | K71: 350 | L71: 350 | M71: 350 | N71: 350 | O71: 4200
B72: Pluxee Multibenefícios - Peres Siqueira | C72: 450 | D72: 450 | E72: 450 | F72: 450 | G72: 450 | H72: 450 | I72: 450 | J72: 450 | K72: 450 | L72: 450 | M72: 450 | N72: 450 | O72: 5400
B73: Folha de Pgto - Peres Siqueira | C73: 2297.77 | D73: 2300 | E73: 2300 | F73: 2300 | G73: 2300 | H73: 2300 | I73: 2300 | J73: 2300 | K73: 2300 | L73: 2300 | M73: 2300 | N73: 2300 | O73: 27597.77
B74: Férias - Amadeu Fava Junior | I74: 3017.63 | O74: 3017.63
B75: Férias - Cristiane da Silva Freire | I75: 1864.61 | O75: 1864.61
B76: Renovação Documentos SST (PCMSO, LTCAT e LIT) | I76: 1480 | O76: 1480
B77: Férias (venda por fora) - Amadeu Fava Junior | J77: 2297.77 | O77: 2297.77
B78: Férias (venda por fora) - Cristiane da Silva Freire | J78: 1469.15 | O78: 1469.15
B79: Licenciamento 2026 (Placas NRY-0578) da L200 | J79: 238.36 | O79: 238.36
B80: Anuidade do Sindicato Rural de Maracaju de 2026 | K80: 1518 | O80: 1518
B81: Férias - Peres Siqueira | K81: 3017.63 | O81: 3017.63
B82: Férias (venda por fora) - Peres Siqueira | L82: 2297.77 | O82: 2297.77
B83: Folha de Pgto_1ª Parc. 13/2026 - Amadeu Fava Junior | M83: 1250 | O83: 1250
B84: Folha de Pgto_1ª Parc. 13/2026 - Cristiane da Silva Freire | M84: 760 | O84: 760
B85: Folha de Pgto_1ª Parc. 13/2026 - Peres Siqueira | M85: 1250 | O85: 1250
B86: Folha de Pgto_2ª Parc. 13/2026 - Amadeu Fava Junior | N86: 1100 | O86: 1100
B87: Folha de Pgto_2ª Parc. 13/2026 - Cristiane da Silva Freire | N87: 650 | O87: 650
B88: Folha de Pgto_2ª Parc. 13/2026 - Peres Siqueira | N88: 1100 | O88: 1100
B89: INSS 13/2026 | N89: 650 | O89: 650
B90: FGTS 12/2025 e 13º Folha de Pgto | C90: 626.8 | O90: 626.8
B91: Isamelia Ponte Fragelli | C91: 23190.62 | D91: 22392.12 | E91: 76580.26 | F91: 18852.76 | G91: 24507.77 | H91: 28607.77 | I91: 18507.77 | J91: 91135.27 | K91: 62607.77 | L91: 71507.77 | M91: 55665.27 | N91: 71579.69 | O91: 565134.84
B92: 1.1 - Imóvel | C92: 3453.93 | D92: 3854.99 | E92: 3854.99 | F92: 3854.99 | G92: 3510 | H92: 3510 | I92: 3510 | J92: 3510 | K92: 3510 | L92: 3510 | M92: 3510 | N92: 3510 | O92: 43098.9
B93: Águas Guariroba (Forest House CG) | C93: 1100 | D93: 1100 | E93: 1100 | F93: 1100 | G93: 1100 | H93: 1100 | I93: 1100 | J93: 1100 | K93: 1100 | L93: 1100 | M93: 1100 | N93: 1100 | O93: 13200
B94: Condomínio (Forest House CG) | C94: 1100 | D94: 1444.99 | E94: 1444.99 | F94: 1444.99 | G94: 1100 | H94: 1100 | I94: 1100 | J94: 1100 | K94: 1100 | L94: 1100 | M94: 1100 | N94: 1100 | O94: 14234.97
B95: Energisa (Forest House CG) | C95: 633.93 | D95: 700 | E95: 700 | F95: 700 | G95: 700 | H95: 700 | I95: 700 | J95: 700 | K95: 700 | L95: 700 | M95: 700 | N95: 700 | O95: 8333.93
B96: Piscineiro (Forest House CG) | C96: 220 | D96: 210 | E96: 210 | F96: 210 | G96: 210 | H96: 210 | I96: 210 | J96: 210 | K96: 210 | L96: 210 | M96: 210 | N96: 210 | O96: 2530
B97: Jardineiro (Forest House CG) | C97: 400 | D97: 400 | E97: 400 | F97: 400 | G97: 400 | H97: 400 | I97: 400 | J97: 400 | K97: 400 | L97: 400 | M97: 400 | N97: 400 | O97: 4800
B98: 1.2 - Família | C98: 3504.84 | D98: 6483.79 | E98: 2944.43 | F98: 2944.43 | G98: 2944.43 | H98: 2944.43 | I98: 2944.43 | J98: 2944.43 | K98: 2944.43 | L98: 2944.43 | M98: 4101.93 | N98: 3916.35 | O98: 41562.35
B99: FGTS - Célia Regina de Amorim Apontes | C99: 778.22 | D99: 735 | E99: 735 | F99: 735 | G99: 735 | H99: 735 | I99: 735 | J99: 735 | K99: 735 | L99: 735 | M99: 735 | N99: 735 | O99: 8863.22
B100: Folha de Pgto - Célia Regina de Amorim Apontes | C100: 2129.42 | D100: 2000.43 | E100: 2000.43 | F100: 2000.43 | G100: 2000.43 | H100: 2000.43 | I100: 2000.43 | J100: 2000.43 | K100: 2000.43 | L100: 2000.43 | M100: 2000.43 | N100: 2000.43 | O100: 24134.15
B101: Vale Transporte - Célia Regina de Amorim Apontes | C101: 207.9 | D101: 209 | E101: 209 | F101: 209 | G101: 209 | H101: 209 | I101: 209 | J101: 209 | K101: 209 | L101: 209 | M101: 209 | N101: 209 | O101: 2506.9
B102: Férias - Célia Regina de Amorim Apontes | D102: 3539.36 | O102: 3539.36
B103: FGTS 13/2025 - Célia Regina de Amorim Apontes | C103: 389.3 | O103: 389.3
B104: Folha de Pgto_1ª Parc. 13/2026 - Célia Regina de Amorim Apontes | M104: 1157.5 | O104: 1157.5
B105: Folha de Pgto_2ª Parc. 13/2026 - Célia Regina de Amorim Apontes | N105: 971.92 | O105: 971.92
B106: 1.3 - Renda Mensal/Qualidade de Vida | C106: 11550 | D106: 11550 | E106: 56277.5 | F106: 11550 | G106: 17550 | H106: 21650 | I106: 11550 | J106: 84177.5 | K106: 55650 | L106: 64550 | M106: 47550 | N106: 63650 | O106: 457255
B107: Distribuição Fixa | C107: 11000 | D107: 11000 | E107: 11000 | F107: 11000 | G107: 11000 | H107: 11000 | I107: 11000 | J107: 11000 | K107: 11000 | L107: 11000 | M107: 11000 | N107: 11000 | O107: 132000
B108: Custos Emergenciais | C108: 330 | D108: 330 | E108: 330 | F108: 330 | G108: 330 | H108: 330 | I108: 330 | J108: 330 | K108: 330 | L108: 330 | M108: 330 | N108: 330 | O108: 3960
B109: Medicamentos | C109: 220 | D109: 220 | E109: 220 | F109: 220 | G109: 220 | H109: 220 | I109: 220 | J109: 220 | K109: 220 | L109: 220 | M109: 220 | N109: 220 | O109: 2640
...

Sheet Dados Bancários
B3: ANA BEATRIZ
B5: DADOS BANCÁRIOS
B7: 1.04 - Despesas Pessoais | C7: Conta Bancária (Pgto) | D7: Validação | E7: Observação
B8: Casan Águas e Saneamento (Residência SC) | C8: Nubank 0101 C/C 6254033-3 | D8: ( ) Sim ( ) Não
B9: Claro Internet (Residência SC) | C9: Nubank 0101 C/C 6254033-3 | D9: ( ) Sim ( ) Não
B10: Dedetização (Residência SC) | C10: Nubank 0101 C/C 6254033-3 | D10: ( ) Sim ( ) Não
B11: IPTU (Residência SC) | C11: Nubank 0101 C/C 6254033-3 | D11: ( ) Sim ( ) Não
B12: Jardineiro (Residência SC) | C12: Nubank 0101 C/C 6254033-3 | D12: ( ) Sim ( ) Não
B13: Limpeza Caixa de Gordura (Residência SC) | C13: Nubank 0101 C/C 6254033-3 | D13: ( ) Sim ( ) Não
B14: Limpeza Mensal (Residência SC) | C14: Nubank 0101 C/C 6254033-3 | D14: ( ) Sim ( ) Não
B15: Reforma Programada (Residência SC) | C15: Nubank 0101 C/C 6254033-3 | D15: ( ) Sim ( ) Não
B16: Taxa de Coleta Residual (Residência SC) | C16: Nubank 0101 C/C 6254033-3 | D16: ( ) Sim ( ) Não
B18: 1.06 - Contratos de Venda | C18: Conta Bancária (Pgto) | D18: Validação | E18: Observação
B19: Repasse Venda Soja 23/24 | C19: Inter 0001 C/C 12284789-0 | D19: ( ) Sim ( ) Não
B20: Repasse Venda Milho 24/24 | C20: Inter 0001 C/C 12284789-0 | D20: ( ) Sim ( ) Não
B21: Repasse Venda Soja 24/25 | C21: Inter 0001 C/C 12284789-0 | D21: ( ) Sim ( ) Não
B24: CLÁUDIO LUIZ
B26: DADOS BANCÁRIOS
B28: 1.01 - Imóvel | C28: Conta Bancária (Pgto) | D28: Validação | E28: Observação
B29: C.E.R IPTU | C29: Bradesco 3489 C/C 3154-2 | D29: ( ) Sim ( ) Não
B30: C.E.R Taxa Lixo | C30: Bradesco 3489 C/C 3154-2 | D30: ( ) Sim ( ) Não
B31: IPTU (Apto 01 Marechal Rondon) | C31: Bradesco 3489 C/C 3154-2 | D31: ( ) Sim ( ) Não
B32: IPTU (Casa Barão) | C32: Bradesco 3489 C/C 3154-2 | D32: ( ) Sim ( ) Não
B33: IPTU (Casa Fundos Marechal Rondon) | C33: Bradesco 3489 C/C 3154-2 | D33: ( ) Sim ( ) Não
B34: IPTU (Casa Vila Inventário) | C34: Bradesco 3489 C/C 3154-2 | D34: ( ) Sim ( ) Não
B35: IPTU (Forest House) | C35: Bradesco 3489 C/C 3154-2 | D35: ( ) Sim ( ) Não
B36: IPTU (R. Margina Humberlina Lima 80) | C36: Bradesco 3489 C/C 3154-2 | D36: ( ) Sim ( ) Não
B37: IPTU (R. Margina Humberlina Lima 90) | C37: Bradesco 3489 C/C 3154-2 | D37: ( ) Sim ( ) Não
B38: IPTU (Sala 01 Marechal Rondon) | C38: Bradesco 3489 C/C 3154-2 | D38: ( ) Sim ( ) Não
B39: ITR Estância Ivone | C39: Bradesco 3489 C/C 3154-2 | D39: ( ) Sim ( ) Não
B40: Parcelamento (Residência SC) | C40: Bradesco 3489 C/C 3154-2 | D40: ( ) Sim ( ) Não
... B42: Usucapião | C42: Bradesco 3489 C/C 3154-2 | D42: ( ) Sim ( ) Não
B43: 1.03 - Renda Mensal/Qualidade de Vida | C43: Conta Bancária (Pgto) | D43: Validação | E43: Observação
B44: Custos Emergenciais | C44: Bradesco 1375 C/C 242867-9 | D44: ( ) Sim ( ) Não
B45: Distribuição Fixa | C45: Bradesco 1375 C/C 242867-9 | D45: ( ) Sim ( ) Não
B46: Medicamento | C46: Bradesco 1375 C/C 242867-9 | D46: ( ) Sim ( ) Não
B47: Tratamento Dentário | C47: Bradesco 1375 C/C 242867-9 | D47: ( ) Sim ( ) Não
B48: Vacina | C48: Bradesco 1375 C/C 242867-9 | D48: ( ) Sim ( ) Não
B49: Troca de Celular | C49: B. Brasil cfragelli7@gmail.com | D49: ( ) Sim ( ) Não
B50: Viagem Final de Ano | C50: B. Brasil cfragelli7@gmail.com | D50: ( ) Sim ( ) Não
B51: Viagem Internacional | C51: B. Brasil cfragelli7@gmail.com | D51: ( ) Sim ( ) Não
B52: Viagem Trimestral | C52: B. Brasil cfragelli7@gmail.com | D52: ( ) Sim ( ) Não
B53: 1.04 - Despesas Pessoais | C53: Conta Bancária (Pgto) | D53: Validação | E53: Observação
B54: Manutenção Conta Bradesco | C54: Bradesco 1375 C/C 242867-9 | D54: ( ) Sim ( ) Não
B55: IPVA | C55: Bradesco 3489 C/C 3154-2 | D55: ( ) Sim ( ) Não
B56: IRPF | C56: Bradesco 3489 C/C 3154-2 | D56: ( ) Sim ( ) Não
B57: Revisão Veículo | C57: Bradesco 3489 C/C 3154-2 | D57: ( ) Sim ( ) Não
B58: Seguro Veículo | C58: Bradesco 3489 C/C 3154-2 | D58: ( ) Sim ( ) Não
B59: Troca de Pneus | C59: Bradesco 3489 C/C 3154-2 | D59: ( ) Sim ( ) Não
B60: Vivo Família Móvel | C60: Bradesco 3489 C/C 3154-2 | D60: ( ) Sim ( ) Não
B61: 1.05 - Fazenda Aramburu | C61: Conta Bancária (Pgto) | D61: Validação | E61: Observação
B62: 1ª Parc. 13º - Cintia Daniela Rodrigues Ricalde | C62: Bradesco 3489 C/C 3154-2 | D62: ( ) Sim ( ) Não
B63: 1ª Parc. 13º - Fernando Guilherme Ledesma Bronel | C63: Bradesco 3489 C/C 3154-2 | D63: ( ) Sim ( ) Não
B64: 2ª Parc. 13º - Cintia Daniela Rodrigues Ricalde | C64: Bradesco 3489 C/C 3154-2 | D64: ( ) Sim ( ) Não
B65: 2ª Parc. 13º - Fernando Guilherme Ledesma Bronel | C65: Bradesco 3489 C/C 3154-2 | D65: ( ) Sim ( ) Não
B66: Energisa (Fazenda Aramburu) | C66: Bradesco 3489 C/C 3154-2 | D66: ( ) Sim ( ) Não
B67: Férias - Cintia Daniela Rodrigues Ricalde | C67: Bradesco 3489 C/C 3154-2 | D67: ( ) Sim ( ) Não
B68: Férias - Fernando Guilherme Ledesma Bronel | C68: Bradesco 3489 C/C 3154-2 | D68: ( ) Sim ( ) Não
B69: FGTS 13º | C69: Bradesco 3489 C/C 3154-2 | D69: ( ) Sim ( ) Não
B70: FGTS Folha de Pgto | C70: Bradesco 3489 C/C 3154-2 | D70: ( ) Sim ( ) Não
B71: Folha de Pgto - Cintia Daniela Rodrigues Ricalde | C71: Bradesco 3489 C/C 3154-2 | D71: ( ) Sim ( ) Não
B72: Folha de Pgto - Fernando Guilherme Ledesma Bronel | C72: Bradesco 3489 C/C 3154-2 | D72: ( ) Sim ( ) Não
B73: INSS 13º | C73: Bradesco 3489 C/C 3154-2 | D73: ( ) Sim ( ) Não
... B76: Pluxee Alimentação - Fernando Guilherme Ledesma Bronel | C76: Bradesco 3489 C/C 3154-2 | D76: ( ) Sim ( ) Não
B80: ISAMÉLIA FRAGELLI
B82: DADOS BANCÁRIOS
B84: 1.01 - Imóvel | C84: Conta Bancária (Pgto) | D84: Validação | E84: Observação
B85: Águas Guariroba (Forest House CG) | C85: Bradesco 3489 C/C 35858-4 | D85: ( ) Sim ( ) Não
B86: Condomínio (Forest House CG) | C86: Bradesco 3489 C/C 35858-4 | D86: ( ) Sim ( ) Não
B87: Energisa (Forest House CG) | C87: Bradesco 3489 C/C 35858-4 | D87: ( ) Sim ( ) Não
B88: Piscineiro (Forest House CG) | C88: Bradesco 3489 C/C 35858-4 | D88: ( ) Sim ( ) Não
B89: Jardineiro (Forest House CG) | C89: Bradesco 3489 C/C 35858-4 | D89: ( ) Sim ( ) Não
B90: IPTU (Forest House CG) | C90: Bradesco 3489 C/C 35858-4 | D90: ( ) Sim ( ) Não
B91: Manutenção (Forest House CG) | C91: Bradesco 3489 C/C 35858-4 | D91: ( ) Sim ( ) Não
B92: 1.02 - Família | C92: Conta Bancária (Pgto) | D92: Validação | E92: Observação
B93: Vale Transporte - Célia Regina de Amorim Pontes | C93: Bradesco 3489 C/C 35858-4 | D93: ( ) Sim ( ) Não
B94: Folha de Pgto - Célia Regina de Amorim Pontes | C94: Bradesco 3489 C/C 35858-4 | D94: ( ) Sim ( ) Não
B95: FGTS - Célia Regina de Amorim Pontes | C95: Bradesco 3489 C/C 35858-4 | D95: ( ) Sim ( ) Não
B96: INSS 13º | C96: Bradesco 3489 C/C 35858-4 | D96: ( ) Sim ( ) Não
B97: 1ª Parc. 13º - Célia Regina de Amorim Pontes | C97: Bradesco 3489 C/C 35858-4 | D97: ( ) Sim ( ) Não
B98: 2ª Parc. 13º - Célia Regina de Amorim Pontes | C98: Bradesco 3489 C/C 35858-4 | D98: ( ) Sim ( ) Não
B99: Férias - Célia Regina de Amorim Pontes | C99: Bradesco 3489 C/C 35858-4 | D99: ( ) Sim ( ) Não
B100: 1.03 - Renda Mensal/Qualidade de Vida | C100: Conta Bancária (Pgto) | D100: Validação | E100: Observação
B101: Distribuição Fixa | C101: Nubank isafragelli@gmail.com | D101: ( ) Sim ( ) Não
B102: Custos Emergenciais | C102: Nubank isafragelli@gmail.com | D102: ( ) Sim ( ) Não
B103: Medicamentos | C103: Nubank isafragelli@gmail.com | D103: ( ) Sim ( ) Não
B104: Tratamento Dentário | C104: Nubank isafragelli@gmail.com | D104: ( ) Sim ( ) Não
B105: Estética | C105: Nubank isafragelli@gmail.com | D105: ( ) Sim ( ) Não
B106: Zélia Alves Ponte | C106: Bradesco 3489 C/C 35858-4 | D106: ( ) Sim ( ) Não
B107: Viagem Internacional | C107: Inter 001 C/C 28333196-0 | D107: ( ) Sim ( ) Não
B108: Viagem Trimestral | C108: Inter 001 C/C 28333196-0 | D108: ( ) Sim ( ) Não
B109: Viagem Final de Ano | C109: Inter 001 C/C 28333196-0 | D109: ( ) Sim ( ) Não
B110: 1.04 - Despesas Pessoais | C110: Conta Bancária (Pgto) | D110: Validação | E110: Observação
B111: Vivo TV + Internet | C111: Bradesco 3489 C/C 35858-4 | D111: ( ) Sim ( ) Não
B112: IPVA | C112: Bradesco 3489 C/C 35858-4 | D112: ( ) Sim ( ) Não
B113: IRPF | C113: Bradesco 3489 C/C 35858-4 | D113: ( ) Sim ( ) Não
B114: Seguro Veículo | C114: Bradesco 3489 C/C 35858-4 | D114: ( ) Sim ( ) Não
B115: Revisão Veículo | C115: Bradesco 3489 C/C 35858-4 | D115: ( ) Sim ( ) Não
B120: PEDRO HENRIQUE
B122: DADOS BANCÁRIOS
...

Sheet Classificação Financeira
B2: Classificações Financeiras - Agropecuária Aramburu Ltda
B5: Código | C5: Classificação | E5: Conta Contábil | G5: Conta Contábil + Centro de Custo | I5: Tipo de Despesa | K5: Forma de Pgto | M5: Conta Bancária | O5: Status
E7: Natureza da conta ou plano de contas, representa a finalidade da movimentação financeira, ou seja, o que está sendo pago ou recebido. | G7: Representa onde o recurso foi usado ou gerado, ou seja, qual unidade, fazenda, setor ou atividade originou aquela receita ou despesa.
B8: 1 – ENTRADAS | K8: Boleto | M8: Banco Cora (0001) | O8: Saldo inicial
B9: 1.1 | C9: Saldo Inicial | I9: Despesas Fixas | K9: Cartão de Débito | M9: Cooperativa Sicredi (0902) | O9: Recebido
B10: 1.1.1 | C10: Banco Cora | E10: 1 – ENTRADAS | G10: 1.1 SALDO INICIAL | I10: Despesas Variáveis | K10: Cartão de Crédito | M10: Cooperativa Sicredi (0913)
B11: 1.1.2 | C11: Cooperativa Sicredi | E11: 1.1 – Saldo Inicial | G11: 1.1.1 – Banco Cora | I11: Despesas Eventuais | K11: Débito Automático | M11: Banco Inter (0001-9) | O11: Pago
E12: 1.2 – Receita de Arrendamento de Terras | G12: 1.1.2 – Cooperativa Sicredi | I12: Despesas Periódicas | K12: Guia | O12: Repassado
B13: 1.2 | C13: Receita de Arrendamento de Terras | E13: 1.3 – Receita com Venda de Subprodutos | I13: - | K13: Pix | O13: Aplicado
B14: 1.2.1 | C14: Venda de Soja | E14: 1.4 – Receita com Venda de Animais | G14: 1.2 RECEITA DE ARRENDAMENTO DE TERRAS | K14: Transferência | O14: Resgatado
B15: 1.2.2 | C15: Venda de Milho | E15: 1.5 – Juros e Rendimentos de Aplicações | G15: 1.2.1 – Venda de Soja | K15: -
E16: 1.6 – Estorno de Pagamentos | G16: 1.2.2 – Venda de Milho | O16: A receber
B17: 1.3 | C17: Receita com Venda de Subprodutos | E17: 1.7 – Reembolsos Recebidos | O17: A pagar
B18: 1.3.1 | C18: Diversos | E18: 1.8 – Resgate de Aplicações | G18: 1.3 RECEITA COM VENDA DE SUBPRODUTOS | O18: A repassar
E19: 1.9 – Outros Recebimentos | G19: 1.3.1 – Diversos | O19: A aplicar
B20: 1.4 | C20: Receita com Venda de Animais | O20: A resgatar
B21: 1.4.1 | C21: Diversos | E21: 2 – SAÍDAS | G21: 1.4 RECEITA COM VENDA DE ANIMAIS
E22: 2.1 – Despesas Administrativas | G22: 1.4.1 – Diversos | O22: Provisionado
B23: 1.5 | C23: Juros e Rendimentos de Aplicações | E23: 2.2 – Despesas com Pessoal | O23: Aplicação
B24: 1.5.1 | C24: Cooperativa Sicredi | E24: 2.3 – Operação da Propriedade | G24: 1.5 JUROS E RENDIMENTOS DE APLICAÇÕES | O24: Resgate
B25: 1.5.2 | C25: Banco XP | E25: 2.4 – Serviços Terceirizados | G25: 1.5.1 – Cooperativa Sicredi | O25: Provisionado DV
E26: 2.5 – Financeiras e Bancárias | G26: 1.5.2 – Banco XP | O26: Provisionado DL
B27: 1.6 | C27: Estorno de Pagamentos | E27: 2.6 – Investimentos em Capital
B28: 1.6.1 | C28: Diversos | E28: 2.7 – Investimentos em Imobilizado Operacional | G28: 1.6 ESTORNO DE PAGAMENTOS
E29: 2.8 – Distribuição de Lucro / Saídas Pessoais | G29: 1.6.1 – Diversos
B30: 1.7 | C30: Reembolsos Recebidos | E30: 2.9 – Outras Saídas
B31: 1.7.1 | C31: Diversos | G31: 1.7 REEMBOLSO RECEBIDOS
G32: 1.7.1 – Diversos
B33: 1.8 | C33: Resgate de Aplicações
B34: 1.8.1 | C34: Cooperativa Sicredi | G34: 1.8 RESGATE DE APLICAÇÕES
B35: 1.8.2 | C35: Banco XP | G35: 1.8.1 – Cooperativa Sicredi
G36: 1.8.2 – Banco XP
B37: 1.9 | C37: Outros Recebimentos
B38: 1.9.1 | C38: Diversos | G38: 1.9 OUTROS RECEBIMENTOS
G39: 1.9.1 – Diversos
B40: 2 – SAÍDAS
B41: 2.1 | C41: Despesas Administrativa | G41: 2.1 DESPESAS ADMINISTRATIVAS
B42: 2.1.1 | C42: Honorários Contábeis | G42: 2.1.1 – Honorários Contábeis
B43: 2.1.2 | C43: Honorários Jurídicos | G43: 2.1.2 – Honorários Jurídicos
B44: 2.1.3 | C44: Despesas com Aluguel | G44: 2.1.3 – Despesas com Aluguel
B45: 2.1.4 | C45: Software Rural | G45: 2.1.4 – Software Rural
B46: 2.1.5 | C46: Licenciamento e Regularização Ambiental | G46: 2.1.5 – Licenciamento e Regularização Ambiental
B47: 2.1.6 | C47: Taxas e Impostos (ITR, INCRA, etc.) | G47: 2.1.6 – Taxas e Impostos (ITR, INCRA, etc.)
B48: 2.1.7 | C48: Material de Escritório | G48: 2.1.7 – Material de Escritório
B49: 2.1.8 | C49: Despesas Gerais | G49: 2.1.8 – Despesas Gerais
B51: 2.2 | C51: Despesas com Pessoal | G51: 2.2 DESPESAS COM PESSOAL
B52: 2.2.1 | C52: Salários e Remunerações | G52: 2.2.1 – Salários e Remunerações
B53: 2.2.2 | C53: Encargos Sociais (INSS, FGTS, etc.) | G53: 2.2.2 – Encargos Sociais (INSS, FGTS, etc.)
... B102: 2.9.3 | C102: Outras Despesas Não Classificadas | G102: 2.9.3 – Outras Despesas Não Classificadas

Sheet Saldo Disponível
E9: CONTA CORRENTE | J9: C/C 0902 MJU | N9: C/C 0913 CGR | R9: INVEST | V9: INVEST EVOLUTIVO | Z9: CONTA CORRENTE | AD9: XP
E10: =SUMIFS(Aramburu_Mensal!$O$6:$O$1098,Aramburu_Mensal!$M$6:$M$1098,"Banco Cora (0001)",Aramburu_Mensal!$N$6:$N$1098,"saldo inicial")+SUMIFS(Aramburu_Mensal!$O$6:$O$1098,Aramburu_Mensal!$M$6:$M$1098,"Banco Cora (0001)",Aramburu_Mensal!$N$6:$N$1098,"pago")+SUMIFS(Aramburu_Mensal!$O$6:$O$1098,Aramburu_Mensal!$M$6:$M$1098,"Banco Cora (0001)",Aramburu_Mensal!$N$6:$N$1098,"Recebido")+SUMIFS(Aramburu_Mensal!$O$6:$O$1098,Aramburu_Mensal!$M$6:$M$1098,"Banco Cora (0001)",Aramburu_Mensal!$N$6:$N$1098,"Aplicado")+SUMIFS(Aramburu_Mensal!$O$6:$O$1098,Aramburu_Mensal!$M$6:$M$1098,"Banco Cora (0001)",Aramburu_Mensal!$N$6:$N$1098,"Resgatado")+SUMIFS(Aramburu_Mensal!$O$6:$O$1098,Aramburu_Mensal!$M$6:$M$1098,"Banco Cora (0001)",Aramburu_Mensal!$N$6:$N$1098,"Repassado") -> 1324843.3 | J10: =SUMIFS(Aramburu_Mensal!$O$6:$O$1098,Aramburu_Mensal!$M$6:$M$1098,"Cooperativa Sicredi (0902)",Aramburu_Mensal!$N$6:$N$1098,"saldo inicial")+SUMIFS(Aramburu_Mensal!$O$6:$O$1098,Aramburu_Mensal!$M$6:$M$1098,"Cooperativa Sicredi (0902)",Aramburu_Mensal!$N$6:$N$1098,"pago")+SUMIFS(Aramburu_Mensal!$O$6:$O$1098,Aramburu_Mensal!$M$6:$M$1098,"Cooperativa Sicredi (0902)",Aramburu_Mensal!$N$6:$N$1098,"Recebido")+SUMIFS(Aramburu_Mensal!$O$6:$O$1098,Aramburu_Mensal!$M$6:$M$1098,"Cooperativa Sicredi (0902)",Aramburu_Mensal!$N$6:$N$1098,"Aplicado")+SUMIFS(Aramburu_Mensal!$O$6:$O$1098,Aramburu_Mensal!$M$6:$M$1098,"Cooperativa Sicredi (0902)",Aramburu_Mensal!$N$6:$N$1098,"Resgatado")+SUMIFS(Aramburu_Mensal!$O$6:$O$1098,Aramburu_Mensal!$M$6:$M$1098,"Cooperativa Sicredi (0902)",Aramburu_Mensal!$N$6:$N$1098,"Repassado") -> -2.910383e-11 | N10: =SUMIFS(Aramburu_Mensal!$O$6:$O$1098,Aramburu_Mensal!$M$6:$M$1098,"Cooperativa Sicredi (0913)",Aramburu_Mensal!$N$6:$N$1098,"saldo inicial")+SUMIFS(Aramburu_Mensal!$O$6:$O$1098,Aramburu_Mensal!$M$6:$M$1098,"Cooperativa Sicredi (0913)",Aramburu_Mensal!$N$6:$N$1098,"pago")+SUMIFS(Aramburu_Mensal!$O$6:$O$1098,Aramburu_Mensal!$M$6:$M$1098,"Cooperativa Sicredi (0913)",Aramburu_Mensal!$N$6:$N$1098,"Recebido")+SUMIFS(Aramburu_Mensal!$O$6:$O$1098,Aramburu_Mensal!$M$6:$M$1098,"Cooperativa Sicredi (0913)",Aramburu_Mensal!$N$6:$N$1098,"Aplicado")+SUMIFS(Aramburu_Mensal!$O$6:$O$1098,Aramburu_Mensal!$M$6:$M$1098,"Cooperativa Sicredi (0913)",Aramburu_Mensal!$N$6:$N$1098,"Resgatado")+SUMIFS(Aramburu_Mensal!$O$6:$O$1098,Aramburu_Mensal!$M$6:$M$1098,"Cooperativa Sicredi (0913)",Aramburu_Mensal!$N$6:$N$1098,"Repassado") -> 1350.06 | R10: 187799.81 | V10: 132103.34 | Z10: 1000 | AD10: =1899472.09 -> 1899472.1
F15: JANEIRO | H15: FEVEREIRO | J15: MARÇO | L15: ABRIL | N15: MAIO | P15: JUNHO | R15: JULHO | T15: AGOSTO | V15: SETEMBRO | X15: OUTUBRO | Z15: NOVEMBRO | AB15: DEZEMBRO | AD15: TOTAL | AH15: FLUXO DE CAIXA 2026
D17: Saldo Inicial CORA (0001): | F17: =SUMIFS(Aramburu_Mensal!$O$6:$O$981,Aramburu_Mensal!$N$6:$N$981,"Saldo Inicial",Aramburu_Mensal!$M$6:$M$981,"Banco Cora (0001)") -> 383184.43 | H17: =F33 -> 1086493.1 | J17: =H33 -> 965011.08 | L17: =J33 -> 2274703.7 | N17: =L33 -> 1324843.3 | P17: =N33 -> 1052395.8 | R17: =P33 -> 917304.16 | T17: =R33 -> 1517793.9 | V17: =T33 -> 997050.36 | X17: =V33 -> 708271.3 | Z17: =X33 -> 479027.1 | AB17: =Z33 -> 308873.67
D18: Saldo Inicial SICREDI (0902): | F18: =SUMIFS(Aramburu_Mensal!$O$6:$O$981,Aramburu_Mensal!$N$6:$N$981,"Saldo Inicial",Aramburu_Mensal!$M$6:$M$981,"Cooperativa Sicredi (0902)") -> 51.15 | H18: =F34 -> 832.25 | J18: =H34 -> 713.35 | L18: =J34 -> 0 | N18: =L34 -> 0 | P18: =N34 -> 0 | R18: =P34 -> 0 | T18: =R34 -> 0 | V18: =T34 -> 0 | X18: =V34 -> 0 | Z18: =X34 -> 0 | AB18: =Z34 -> 0 | AH18: =AD21 -> 5078214.9 | AI18: Movimentações de Entradas
D19: Saldo Inicial SICREDI (0913): | F19: =SUMIFS(Aramburu_Mensal!$O$6:$O$981,Aramburu_Mensal!$N$6:$N$981,"Saldo Inicial",Aramburu_Mensal!$M$6:$M$981,"Cooperativa Sicredi (0913)") -> 100 | H19: =F35 -> 1819.56 | J19: =H35 -> 1663.06 | L19: =J35 -> 1506.56 | N19: =L35 -> 1350.06 | P19: =N35 -> 1181.06 | R19: =P35 -> 1012.07 | T19: =R35 -> 843.07 | V19: =T35 -> 674.07 | X19: =V35 -> 505.07 | Z19: =X35 -> 336.07 | AB19: =Z35 -> 167.07 | AH19: =AD26 -> -4953509.6 | AI19: Movimentações de Saídas
AH20: =SUM(AH18:AH19) -> 124705.34 | AI20: Saldo Final em Conta | 2025
D21: Entradas | E21: + | F21: =SUM(F22:F25) -> 2005604.9 | H21: =SUM(H23:H25) -> 86796.07 | J21: =SUM(J23:J25) -> 1902403.8 | L21: =SUM(L22:L25) -> 137968.85 | N21: =SUM(N22:N25) -> 129339.39 | P21: =SUM(P22:P25) -> 20446.87 | R21: =SUM(R22:R25) -> 775333.16 | T21: =SUM(T22:T25) -> 6060.12 | V21: =SUM(V22:V25) -> 6060.12 | X21: =SUM(X22:X25) -> 5913.37 | Z21: =SUM(Z22:Z25) -> 2288.37 | AB21: =SUM(AB22:AB25) -> 0 | AD21: =SUM(F21,H21,J21,L21,N21,P21,R21,T21,V21,X21,Z21,AB21) -> 5078214.9
D22: Saldo 2025 | F22: =SUMPRODUCT((Aramburu_Mensal!$C$6:$C$1098="janeiro")*(Aramburu_Mensal!$N$6:$N$1098="saldo inicial")*(Aramburu_Mensal!$O$6:$O$1098)) -> 383335.58 | H22: 0 | J22: 0 | L22: 0 | N22: 0 | P22: 0 | R22: 0 | T22: 0 | V22: 0 | X22: 0 | Z22: 0 | AB22: 0 | AD22: =SUM(F22:AC22) -> 383335.58
D23: Vendas | F23: =SUMPRODUCT((Aramburu_Mensal!$C$6:$C$1098="Janeiro")*(Aramburu_Mensal!$D$6:$D$1098="1.2 – Receita de Arrendamento de Terras")*((Aramburu_Mensal!$N$6:$N$1098="A receber")+(Aramburu_Mensal!$N$6:$N$1098="Recebido"))*(Aramburu_Mensal!$O$6:$O$1098)) -> 960000 | H23: =SUMPRODUCT((Aramburu_Mensal!$C$6:$C$1098="Fevereiro")*(Aramburu_Mensal!$D$6:$D$1098="1.2 – Receita de Arrendamento de Terras")*((Aramburu_Mensal!$N$6:$N$1098="A receber")+(Aramburu_Mensal!$N$6:$N$1098="Recebido"))*(Aramburu_Mensal!$O$6:$O$1098)) -> 0 | J23: =SUMPRODUCT((Aramburu_Mensal!$C$6:$C$1098="Março")*(Aramburu_Mensal!$D$6:$D$1098="1.2 – Receita de Arrendamento de Terras")*((Aramburu_Mensal!$N$6:$N$1098="A receber")+(Aramburu_Mensal!$N$6:$N$1098="Recebido"))*(Aramburu_Mensal!$O$6:$O$1098)) -> 1793031.1 | L23: =SUMPRODUCT((Aramburu_Mensal!$C$6:$C$1098="Abril")*(Aramburu_Mensal!$D$6:$D$1098="1.2 – Receita de Arrendamento de Terras")*((Aramburu_Mensal!$N$6:$N$1098="A receber")+(Aramburu_Mensal!$N$6:$N$1098="Recebido"))*(Aramburu_Mensal!$O$6:$O$1098)) -> 0 | N23: =SUMPRODUCT((Aramburu_Mensal!$C$6:$C$1098="Maio")*(Aramburu_Mensal!$D$6:$D$1098="1.2 – Receita de Arrendamento de Terras")*((Aramburu_Mensal!$N$6:$N$1098="A receber")+(Aramburu_Mensal!$N$6:$N$1098="Recebido"))*(Aramburu_Mensal!$O$6:$O$1098)) -> 0 | P23: =SUMPRODUCT((Aramburu_Mensal!$C$6:$C$1098="Junho")*(Aramburu_Mensal!$D$6:$D$1098="1.2 – Receita de Arrendamento de Terras")*((Aramburu_Mensal!$N$6:$N$1098="A receber")+(Aramburu_Mensal!$N$6:$N$1098="Recebido"))*(Aramburu_Mensal!$O$6:$O$1098)) -> 0 | R23: =SUMPRODUCT((Aramburu_Mensal!$C$6:$C$1098="Julho")*(Aramburu_Mensal!$D$6:$D$1098="1.2 – Receita de Arrendamento de Terras")*((Aramburu_Mensal!$N$6:$N$1098="A receber")+(Aramburu_Mensal!$N$6:$N$1098="Recebido"))*(Aramburu_Mensal!$O$6:$O$1098)) -> 760234.22 | T23: =SUMPRODUCT((Aramburu_Mensal!$C$6:$C$1098="Agosto")*(Aramburu_Mensal!$D$6:$D$1098="1.2 – Receita de Arrendamento de Terras")*((Aramburu_Mensal!$N$6:$N$1098="A receber")+(Aramburu_Mensal!$N$6:$N$1098="Recebido"))*(Aramburu_Mensal!$O$6:$O$1098)) -> 0 | V23: =SUMPRODUCT((Aramburu_Mensal!$C$6:$C$1098="Setembro")*(Aramburu_Mensal!$D$6:$D$1098="1.2 – Receita de Arrendamento de Terras")*((Aramburu_Mensal!$N$6:$N$1098="A receber")+(Aramburu_Mensal!$N$6:$N$1098="Recebido"))*(Aramburu_Mensal!$O$6:$O$1098)) -> 0 | X23: =SUMPRODUCT((Aramburu_Mensal!$C$6:$C$1098="Outubro")*(Aramburu_Mensal!$D$6:$D$1098="1.2 – Receita de Arrendamento de Terras")*((Aramburu_Mensal!$N$6:$N$1098="A receber")+(Aramburu_Mensal!$N$6:$N$1098="Recebido"))*(Aramburu_Mensal!$O$6:$O$1098)) -> 0 | Z23: =SUMPRODUCT((Aramburu_Mensal!$C$6:$C$1098="Novembro")*(Aramburu_Mensal!$D$6:$D$1098="1.2 – Receita de Arrendamento de Terras")*((Aramburu_Mensal!$N$6:$N$1098="A receber")+(Aramburu_Mensal!$N$6:$N$1098="Recebido"))*(Aramburu_Mensal!$O$6:$O$1098)) -> 0 | AB23: =SUMPRODUCT((Aramburu_Mensal!$C$6:$C$1098="Dezembro")*(Aramburu_Mensal!$D$6:$D$1098="1.2 – Receita de Arrendamento de Terras")*((Aramburu_Mensal!$N$6:$N$1098="A receber")+(Aramburu_Mensal!$N$6:$N$1098="Recebido"))*(Aramburu_Mensal!$O$6:$O$1098)) -> 0 | AD23: =SUM(F23:AC23) -> 3513265.3
D24: Investimentos (Resgate) | F24: =SUMPRODUCT((Aramburu_Mensal!$C$6:$C$1098="Janeiro")*((Aramburu_Mensal!$N$6:$N$1098="Resgate")+(Aramburu_Mensal!$N$6:$N$1098="A resgatar")+(Aramburu_Mensal!$N$6:$N$1098="Resgatado"))*(Aramburu_Mensal!$O$6:$O$1098)) -> 135614.8 | H24: =SUMPRODUCT((Aramburu_Mensal!$C$6:$C$1098="Fevereiro")*((Aramburu_Mensal!$N$6:$N$1098="Resgate")+(Aramburu_Mensal!$N$6:$N$1098="A resgatar")+(Aramburu_Mensal!$N$6:$N$1098="Resgatado"))*(Aramburu_Mensal!$O$6:$O$1098)) -> 86701.51 | J24: =SUMPRODUCT((Aramburu_Mensal!$C$6:$C$1098="Março")*((Aramburu_Mensal!$N$6:$N$1098="Resgate")+(Aramburu_Mensal!$N$6:$N$1098="A resgatar")+(Aramburu_Mensal!$N$6:$N$1098="Resgatado"))*(Aramburu_Mensal!$O$6:$O$1098)) -> 88899.32 | L24: =SUMPRODUCT((Aramburu_Mensal!$C$6:$C$1098="Abril")*((Aramburu_Mensal!$N$6:$N$1098="Resgate")+(Aramburu_Mensal!$N$6:$N$1098="A resgatar")+(Aramburu_Mensal!$N$6:$N$1098="Resgatado"))*(Aramburu_Mensal!$O$6:$O$1098)) -> 86068.75 | N24: =SUMPRODUCT((Aramburu_Mensal!$C$6:$C$1098="Maio")*((Aramburu_Mensal!$N$6:$N$1098="Resgate")+(Aramburu_Mensal!$N$6:$N$1098="A resgatar")+(Aramburu_Mensal!$N$6:$N$1098="Resgatado"))*(Aramburu_Mensal!$O$6:$O$1098)) -> 129339.39 | P24: =SUMPRODUCT((Aramburu_Mensal!$C$6:$C$1098="Junho")*((Aramburu_Mensal!$N$6:$N$1098="Resgate")+(Aramburu_Mensal!$N$6:$N$1098="A resgatar")+(Aramburu_Mensal!$N$6:$N$1098="Resgatado"))*(Aramburu_Mensal!$O$6:$O$1098)) -> 20446.87 | R24: =SUMPRODUCT((Aramburu_Mensal!$C$6:$C$1098="Julho")*((Aramburu_Mensal!$N$6:$N$1098="Resgate")+(Aramburu_Mensal!$N$6:$N$1098="A resgatar")+(Aramburu_Mensal!$N$6:$N$1098="Resgatado"))*(Aramburu_Mensal!$O$6:$O$1098)) -> 15098.94 | T24: =SUMPRODUCT((Aramburu_Mensal!$C$6:$C$1098="Agosto")*((Aramburu_Mensal!$N$6:$N$1098="Resgate")+(Aramburu_Mensal!$N$6:$N$1098="A resgatar")+(Aramburu_Mensal!$N$6:$N$1098="Resgatado"))*(Aramburu_Mensal!$O$6:$O$1098)) -> 6060.12 | V24: =SUMPRODUCT((Aramburu_Mensal!$C$6:$C$1098="Setembro")*((Aramburu_Mensal!$N$6:$N$1098="Resgate")+(Aramburu_Mensal!$N$6:$N$1098="A resgatar")+(Aramburu_Mensal!$N$6:$N$1098="Resgatado"))*(Aramburu_Mensal!$O$6:$O$1098)) -> 6060.12 | X24: =SUMPRODUCT((Aramburu_Mensal!$C$6:$C$1098="Outubro")*((Aramburu_Mensal!$N$6:$N$1098="Resgate")+(Aramburu_Mensal!$N$6:$N$1098="A resgatar")+(Aramburu_Mensal!$N$6:$N$1098="Resgatado"))*(Aramburu_Mensal!$O$6:$O$1098)) -> 5913.37 | Z24: =SUMPRODUCT((Aramburu_Mensal!$C$6:$C$1098="Novembro")*((Aramburu_Mensal!$N$6:$N$1098="Resgate")+(Aramburu_Mensal!$N$6:$N$1098="A resgatar")+(Aramburu_Mensal!$N$6:$N$1098="Resgatado"))*(Aramburu_Mensal!$O$6:$O$1098)) -> 2288.37 | AB24: =SUMPRODUCT((Aramburu_Mensal!$C$6:$C$1098="Dezembro")*((Aramburu_Mensal!$N$6:$N$1098="Resgate")+(Aramburu_Mensal!$N$6:$N$1098="A resgatar")+(Aramburu_Mensal!$N$6:$N$1098="Resgatado"))*(Aramburu_Mensal!$O$6:$O$1098)) -> 0 | AD24: =SUM(F24:AC24) -> 582491.56
D25: Outros Entradas | F25: =(SUMPRODUCT((Aramburu_Mensal!$C$6:$C$1098="Janeiro")*((Aramburu_Mensal!$N$6:$N$1098="A receber")+(Aramburu_Mensal!$N$6:$N$1098="Recebido"))*(Aramburu_Mensal!$O$6:$O$1098))-F23) -> 526654.48 | H25: =(SUMPRODUCT((Aramburu_Mensal!$C$6:$C$1098="Fevereiro")*((Aramburu_Mensal!$N$6:$N$1098="A receber")+(Aramburu_Mensal!$N$6:$N$1098="Recebido"))*(Aramburu_Mensal!$O$6:$O$1098))-H23) -> 94.56 | J25: =(SUMPRODUCT((Aramburu_Mensal!$C$6:$C$1098="Março")*((Aramburu_Mensal!$N$6:$N$1098="A receber")+(Aramburu_Mensal!$N$6:$N$1098="Recebido"))*(Aramburu_Mensal!$O$6:$O$1098))-J23) -> 20473.37 | L25: =(SUMPRODUCT((Aramburu_Mensal!$C$6:$C$1098="Abril")*((Aramburu_Mensal!$N$6:$N$1098="A receber")+(Aramburu_Mensal!$N$6:$N$1098="Recebido"))*(Aramburu_Mensal!$O$6:$O$1098))-L23) -> 51900.1 | N25: =(SUMPRODUCT((Aramburu_Mensal!$C$6:$C$1098="Maio")*((Aramburu_Mensal!$N$6:$N$1098="A receber")+(Aramburu_Mensal!$N$6:$N$1098="Recebido"))*(Aramburu_Mensal!$O$6:$O$1098))-N23) -> 0 | P25: =(SUMPRODUCT((Aramburu_Mensal!$C$6:$C$1098="Junho")*((Aramburu_Mensal!$N$6:$N$1098="A receber")+(Aramburu_Mensal!$N$6:$N$1098="Recebido"))*(Aramburu_Mensal!$O$6:$O$1098))-P23) -> 0 | R25: =(SUMPRODUCT((Aramburu_Mensal!$C$6:$C$1098="Julho")*((Aramburu_Mensal!$N$6:$N$1098="A receber")+(Aramburu_Mensal!$N$6:$N$1098="Recebido"))*(Aramburu_Mensal!$O$6:$O$1098))-R23) -> 0 | T25: =(SUMPRODUCT((Aramburu_Mensal!$C$6:$C$1098="Agosto")*((Aramburu_Mensal!$N$6:$N$1098="A receber")+(Aramburu_Mensal!$N$6:$N$1098="Recebido"))*(Aramburu_Mensal!$O$6:$O$1098))-T23) -> 0 | V25: =(SUMPRODUCT((Aramburu_Mensal!$C$6:$C$1098="Setembro")*((Aramburu_Mensal!$N$6:$N$1098="A receber")+(Aramburu_Mensal!$N$6:$N$1098="Recebido"))*(Aramburu_Mensal!$O$6:$O$1098))-V23) -> 0 | X25: =(SUMPRODUCT((Aramburu_Mensal!$C$6:$C$1098="Outubro")*((Aramburu_Mensal!$N$6:$N$1098="A receber")+(Aramburu_Mensal!$N$6:$N$1098="Recebido"))*(Aramburu_Mensal!$O$6:$O$1098))-X23) -> 0 | Z25: =(SUMPRODUCT((Aramburu_Mensal!$C$6:$C$1098="Novembro")*((Aramburu_Mensal!$N$6:$N$1098="A receber")+(Aramburu_Mensal!$N$6:$N$1098="Recebido"))*(Aramburu_Mensal!$O$6:$O$1098))-Z23) -> 0 | AB25: =(SUMPRODUCT((Aramburu_Mensal!$C$6:$C$1098="Dezembro")*((Aramburu_Mensal!$N$6:$N$1098="A receber")+(Aramburu_Mensal!$N$6:$N$1098="Recebido"))*(Aramburu_Mensal!$O$6:$O$1098))-AB23) -> 0 | AD25: =SUM(F25:AC25) -> 599122.51 | AH25: SALDOS 2026
D26: Saídas | E26: - | F26: =SUM(F27:F30) -> -916459.96 | H26: =SUM(H27:H30) -> -208553.48 | J26: =SUM(J27:J30) -> -593581.03 | L26: =SUM(L27:L30) -> -1087985.7 | N26: =SUM(N27:N30) -> -401955.86 | P26: =SUM(P27:P30) -> -155707.54 | R26: =SUM(R27:R30) -> -175012.39 | T26: =SUM(T27:T30) -> -526972.69 | V26: =SUM(V27:V30) -> -295008.18 | X26: =SUM(X27:X30) -> -235326.57 | Z26: =SUM(Z27:Z30) -> -172610.8 | AB26: =SUM(AB27:AB30) -> -184335.4 | AD26: =SUM(F26:AC26) -> -4953509.6
D27: Despesas Aramburu | F27: =SUMPRODUCT((Aramburu_Mensal!$C$6:$C$1098="janeiro")*((Aramburu_Mensal!$N$6:$N$1098="provisionado")+(Aramburu_Mensal!$N$6:$N$1098="a pagar")+(Aramburu_Mensal!$N$6:$N$1098="Pago")+(Aramburu_Mensal!$N$6:$N$1098="Provisionado DV"))*(Aramburu_Mensal!$O$6:$O$1098))-F30 -> -195848.44 | H27: =SUMPRODUCT((Aramburu_Mensal!$C$6:$C$1098="fevereiro")*((Aramburu_Mensal!$N$6:$N$1098="provisionado")+(Aramburu_Mensal!$N$6:$N$1098="a pagar")+(Aramburu_Mensal!$N$6:$N$1098="Pago")+(Aramburu_Mensal!$N$6:$N$1098="Provisionado DV"))*(Aramburu_Mensal!$O$6:$O$1098))-H30 -> -123484.94 | J27: =SUMPRODUCT((Aramburu_Mensal!$C$6:$C$1098="março")*((Aramburu_Mensal!$N$6:$N$1098="provisionado")+(Aramburu_Mensal!$N$6:$N$1098="a pagar")+(Aramburu_Mensal!$N$6:$N$1098="Pago")+(Aramburu_Mensal!$N$6:$N$1098="Provisionado DV"))*(Aramburu_Mensal!$O$6:$O$1098))-J30 -> -123078.9 | L27: =SUMPRODUCT((Aramburu_Mensal!$C$6:$C$1098="abril")*((Aramburu_Mensal!$N$6:$N$1098="provisionado")+(Aramburu_Mensal!$N$6:$N$1098="a pagar")+(Aramburu_Mensal!$N$6:$N$1098="Pago")+(Aramburu_Mensal!$N$6:$N$1098="Provisionado DV"))*(Aramburu_Mensal!$O$6:$O$1098))-L30 -> -222950.61 | N27: =SUMPRODUCT((Aramburu_Mensal!$C$6:$C$1098="maio")*((Aramburu_Mensal!$N$6:$N$1098="provisionado")+(Aramburu_Mensal!$N$6:$N$1098="a pagar")+(Aramburu_Mensal!$N$6:$N$1098="Pago")+(Aramburu_Mensal!$N$6:$N$1098="Provisionado DV"))*(Aramburu_Mensal!$O$6:$O$1098))-N30 -> -374284.45 | P27: =SUMPRODUCT((Aramburu_Mensal!$C$6:$C$1098="junho")*((Aramburu_Mensal!$N$6:$N$1098="provisionado")+(Aramburu_Mensal!$N$6:$N$1098="a pagar")+(Aramburu_Mensal!$N$6:$N$1098="Pago")+(Aramburu_Mensal!$N$6:$N$1098="Provisionado DV"))*(Aramburu_Mensal!$O$6:$O$1098))-P30 -> -62542.55 | R27: =SUMPRODUCT((Aramburu_Mensal!$C$6:$C$1098="julho")*((Aramburu_Mensal!$N$6:$N$1098="provisionado")+(Aramburu_Mensal!$N$6:$N$1098="a pagar")+(Aramburu_Mensal!$N$6:$N$1098="Pago")+(Aramburu_Mensal!$N$6:$N$1098="Provisionado DV"))*(Aramburu_Mensal!$O$6:$O$1098))-R30 -> -103614.65 | T27: =SUMPRODUCT((Aramburu_Mensal!$C$6:$C$1098="agosto")*((Aramburu_Mensal!$N$6:$N$1098="provisionado")+(Aramburu_Mensal!$N$6:$N$1098="a pagar")+(Aramburu_Mensal!$N$6:$N$1098="Pago")+(Aramburu_Mensal!$N$6:$N$1098="Provisionado DV"))*(Aramburu_Mensal!$O$6:$O$1098))-T30 -> -349438.55 | V27: =SUMPRODUCT((Aramburu_Mensal!$C$6:$C$1098="setembro")*((Aramburu_Mensal!$N$6:$N$1098="provisionado")+(Aramburu_Mensal!$N$6:$N$1098="a pagar")+(Aramburu_Mensal!$N$6:$N$1098="Pago")+(Aramburu_Mensal!$N$6:$N$1098="Provisionado DV"))*(Aramburu_Mensal!$O$6:$O$1098))-V30 -> -173937.05 | X27: =SUMPRODUCT((Aramburu_Mensal!$C$6:$C$1098="outubro")*((Aramburu_Mensal!$N$6:$N$1098="provisionado")+(Aramburu_Mensal!$N$6:$N$1098="a pagar")+(Aramburu_Mensal!$N$6:$N$1098="Pago")+(Aramburu_Mensal!$N$6:$N$1098="Provisionado DV"))*(Aramburu_Mensal!$O$6:$O$1098))-X30 -> -89793.3 | Z27: =SUMPRODUCT((Aramburu_Mensal!$C$6:$C$1098="novembro")*((Aramburu_Mensal!$N$6:$N$1098="provisionado")+(Aramburu_Mensal!$N$6:$N$1098="a pagar")+(Aramburu_Mensal!$N$6:$N$1098="Pago")+(Aramburu_Mensal!$N$6:$N$1098="Provisionado DV"))*(Aramburu_Mensal!$O$6:$O$1098))-Z30 -> -50609.3 | AB27: =SUMPRODUCT((Aramburu_Mensal!$C$6:$C$1098="dezembro")*((Aramburu_Mensal!$N$6:$N$1098="provisionado")+(Aramburu_Mensal!$N$6:$N$1098="a pagar")+(Aramburu_Mensal!$N$6:$N$1098="Pago")+(Aramburu_Mensal!$N$6:$N$1098="Provisionado DV"))*(Aramburu_Mensal!$O$6:$O$1098))-AB30 -> -49648.47 | AD27: =SUM(F27:AC27) -> -1919231.2
D28: Distribuição de Lucro | F28: =SUMPRODUCT((Aramburu_Mensal!$C$6:$C$1098="janeiro")*((Aramburu_Mensal!$N$6:$N$1098="provisionado dl")+(Aramburu_Mensal!$N$6:$N$1098="a repassar")+(Aramburu_Mensal!$N$6:$N$1098="repassado"))*(Aramburu_Mensal!$O$6:$O$1098)) -> -93957.02 | H28: =SUMPRODUCT((Aramburu_Mensal!$C$6:$C$1098="fevereiro")*((Aramburu_Mensal!$N$6:$N$1098="provisionado dl")+(Aramburu_Mensal!$N$6:$N$1098="a repassar")+(Aramburu_Mensal!$N$6:$N$1098="repassado"))*(Aramburu_Mensal!$O$6:$O$1098)) -> -84973.98 | J28: =SUMPRODUCT((Aramburu_Mensal!$C$6:$C$1098="março")*((Aramburu_Mensal!$N$6:$N$1098="provisionado dl")+(Aramburu_Mensal!$N$6:$N$1098="a repassar")+(Aramburu_Mensal!$N$6:$N$1098="repassado"))*(Aramburu_Mensal!$O$6:$O$1098)) -> -436231.06 | L28: =SUMPRODUCT((Aramburu_Mensal!$C$6:$C$1098="abril")*((Aramburu_Mensal!$N$6:$N$1098="provisionado dl")+(Aramburu_Mensal!$N$6:$N$1098="a repassar")+(Aramburu_Mensal!$N$6:$N$1098="repassado"))*(Aramburu_Mensal!$O$6:$O$1098)) -> -429950.56 | N28: =SUMPRODUCT((Aramburu_Mensal!$C$6:$C$1098="maio")*((Aramburu_Mensal!$N$6:$N$1098="provisionado dl")+(Aramburu_Mensal!$N$6:$N$1098="a repassar")+(Aramburu_Mensal!$N$6:$N$1098="repassado"))*(Aramburu_Mensal!$O$6:$O$1098)) -> -27671.41 | P28: =SUMPRODUCT((Aramburu_Mensal!$C$6:$C$1098="junho")*((Aramburu_Mensal!$N$6:$N$1098="provisionado dl")+(Aramburu_Mensal!$N$6:$N$1098="a repassar")+(Aramburu_Mensal!$N$6:$N$1098="repassado"))*(Aramburu_Mensal!$O$6:$O$1098)) -> -93164.99 | R28: =SUMPRODUCT((Aramburu_Mensal!$C$6:$C$1098="julho")*((Aramburu_Mensal!$N$6:$N$1098="provisionado dl")+(Aramburu_Mensal!$N$6:$N$1098="a repassar")+(Aramburu_Mensal!$N$6:$N$1098="repassado"))*(Aramburu_Mensal!$O$6:$O$1098)) -> -71397.74 | T28: =SUMPRODUCT((Aramburu_Mensal!$C$6:$C$1098="agosto")*((Aramburu_Mensal!$N$6:$N$1098="provisionado dl")+(Aramburu_Mensal!$N$6:$N$1098="a repassar")+(Aramburu_Mensal!$N$6:$N$1098="repassado"))*(Aramburu_Mensal!$O$6:$O$1098)) -> -177534.14 | V28: =SUMPRODUCT((Aramburu_Mensal!$C$6:$C$1098="setembro")*((Aramburu_Mensal!$N$6:$N$1098="provisionado dl")+(Aramburu_Mensal!$N$6:$N$1098="a repassar")+(Aramburu_Mensal!$N$6:$N$1098="repassado"))*(Aramburu_Mensal!$O$6:$O$1098)) -> -121071.13 | X28: =SUMPRODUCT((Aramburu_Mensal!$C$6:$C$1098="outubro")*((Aramburu_Mensal!$N$6:$N$1098="provisionado dl")+(Aramburu_Mensal!$N$6:$N$1098="a repassar")+(Aramburu_Mensal!$N$6:$N$1098="repassado"))*(Aramburu_Mensal!$O$6:$O$1098)) -> -145533.27 | Z28: =SUMPRODUCT((Aramburu_Mensal!$C$6:$C$1098="novembro")*((Aramburu_Mensal!$N$6:$N$1098="provisionado dl")+(Aramburu_Mensal!$N$6:$N$1098="a repassar")+(Aramburu_Mensal!$N$6:$N$1098="repassado"))*(Aramburu_Mensal!$O$6:$O$1098)) -> -122001.5 | AB28: =SUMPRODUCT((Aramburu_Mensal!$C$6:$C$1098="dezembro")*((Aramburu_Mensal!$N$6:$N$1098="provisionado dl")+(Aramburu_Mensal!$N$6:$N$1098="a repassar")+(Aramburu_Mensal!$N$6:$N$1098="repassado"))*(Aramburu_Mensal!$O$6:$O$1098)) -> -134686.93 | AD28: =SUM(F28:AC28) -> -1938173.7 | AH28: =AH20 -> 124705.34
D29: Investimentos (Aplicação) | F29: =SUMPRODUCT((Aramburu_Mensal!$C$6:$C$1098="janeiro")*((Aramburu_Mensal!$N$6:$N$1098="A aplicar")+(Aramburu_Mensal!$N$6:$N$1098="Aplicado")+(Aramburu_Mensal!$N$6:$N$1098="Aplicação"))*(Aramburu_Mensal!$O$6:$O$1098)) -> -400573.8 | H29: =SUMPRODUCT((Aramburu_Mensal!$C$6:$C$1098="fevereiro")*((Aramburu_Mensal!$N$6:$N$1098="A aplicar")+(Aramburu_Mensal!$N$6:$N$1098="Aplicado")+(Aramburu_Mensal!$N$6:$N$1098="Aplicação"))*(Aramburu_Mensal!$O$6:$O$1098)) -> 0 | J29: =SUMPRODUCT((Aramburu_Mensal!$C$6:$C$1098="março")*((Aramburu_Mensal!$N$6:$N$1098="A aplicar")+(Aramburu_Mensal!$N$6:$N$1098="Aplicado")+(Aramburu_Mensal!$N$6:$N$1098="Aplicação"))*(Aramburu_Mensal!$O$6:$O$1098)) -> -20140.28 | L29: =SUMPRODUCT((Aramburu_Mensal!$C$6:$C$1098="abril")*((Aramburu_Mensal!$N$6:$N$1098="A aplicar")+(Aramburu_Mensal!$N$6:$N$1098="Aplicado")+(Aramburu_Mensal!$N$6:$N$1098="Aplicação"))*(Aramburu_Mensal!$O$6:$O$1098)) -> -383184.43 | N29: =SUMPRODUCT((Aramburu_Mensal!$C$6:$C$1098="maio")*((Aramburu_Mensal!$N$6:$N$1098="A aplicar")+(Aramburu_Mensal!$N$6:$N$1098="Aplicado")+(Aramburu_Mensal!$N$6:$N$1098="Aplicação"))*(Aramburu_Mensal!$O$6:$O$1098)) -> 0 | P29: =SUMPRODUCT((Aramburu_Mensal!$C$6:$C$1098="junho")*((Aramburu_Mensal!$N$6:$N$1098="A aplicar")+(Aramburu_Mensal!$N$6:$N$1098="Aplicado")+(Aramburu_Mensal!$N$6:$N$1098="Aplicação"))*(Aramburu_Mensal!$O$6:$O$1098)) -> 0 | R29: =SUMPRODUCT((Aramburu_Mensal!$C$6:$C$1098="julho")*((Aramburu_Mensal!$N$6:$N$1098="A aplicar")+(Aramburu_Mensal!$N$6:$N$1098="Aplicado")+(Aramburu_Mensal!$N$6:$N$1098="Aplicação"))*(Aramburu_Mensal!$O$6:$O$1098)) -> 0 | T29: =SUMPRODUCT((Aramburu_Mensal!$C$6:$C$1098="agosto")*((Aramburu_Mensal!$N$6:$N$1098="A aplicar")+(Aramburu_Mensal!$N$6:$N$1098="Aplicado")+(Aramburu_Mensal!$N$6:$N$1098="Aplicação"))*(Aramburu_Mensal!$O$6:$O$1098)) -> 0 | V29: =SUMPRODUCT((Aramburu_Mensal!$C$6:$C$1098="setembro")*((Aramburu_Mensal!$N$6:$N$1098="A aplicar")+(Aramburu_Mensal!$N$6:$N$1098="Aplicado")+(Aramburu_Mensal!$N$6:$N$1098="Aplicação"))*(Aramburu_Mensal!$O$6:$O$1098)) -> 0 | X29: =SUMPRODUCT((Aramburu_Mensal!$C$6:$C$1098="outubro")*((Aramburu_Mensal!$N$6:$N$1098="A aplicar")+(Aramburu_Mensal!$N$6:$N$1098="Aplicado")+(Aramburu_Mensal!$N$6:$N$1098="Aplicação"))*(Aramburu_Mensal!$O$6:$O$1098)) -> 0 | Z29: =SUMPRODUCT((Aramburu_Mensal!$C$6:$C$1098="novembro")*((Aramburu_Mensal!$N$6:$N$1098="A aplicar")+(Aramburu_Mensal!$N$6:$N$1098="Aplicado")+(Aramburu_Mensal!$N$6:$N$1098="Aplicação"))*(Aramburu_Mensal!$O$6:$O$1098)) -> 0 | AB29: =SUMPRODUCT((Aramburu_Mensal!$C$6:$C$1098="dezembro")*((Aramburu_Mensal!$N$6:$N$1098="A aplicar")+(Aramburu_Mensal!$N$6:$N$1098="Aplicado")+(Aramburu_Mensal!$N$6:$N$1098="Aplicação"))*(Aramburu_Mensal!$O$6:$O$1098)) -> 0 | AD29: =SUM(F29:AC29) -> -803898.51
D30: Outras Saídas | F30: =SUMPRODUCT((Aramburu_Mensal!$C$6:$C$1098="janeiro")*(Aramburu_Mensal!$D$6:$D$1098="2.9 – Outras Saídas")*((Aramburu_Mensal!$N$6:$N$1098="provisionado")+(Aramburu_Mensal!$N$6:$N$1098="a pagar")+(Aramburu_Mensal!$N$6:$N$1098="Pago")+(Aramburu_Mensal!$N$6:$N$1098="Provisionado DV"))*(Aramburu_Mensal!$O$6:$O$1098)) -> -226080.7 | H30: =SUMPRODUCT((Aramburu_Mensal!$C$6:$C$1098="fevereiro")*(Aramburu_Mensal!$D$6:$D$1098="2.9 – Outras Saídas")*((Aramburu_Mensal!$N$6:$N$1098="provisionado")+(Aramburu_Mensal!$N$6:$N$1098="a pagar")+(Aramburu_Mensal!$N$6:$N$1098="Pago")+(Aramburu_Mensal!$N$6:$N$1098="Provisionado DV"))*(Aramburu_Mensal!$O$6:$O$1098)) -> -94.56 | J30: =SUMPRODUCT((Aramburu_Mensal!$C$6:$C$1098="março")*(Aramburu_Mensal!$D$6:$D$1098="2.9 – Outras Saídas")*((Aramburu_Mensal!$N$6:$N$1098="provisionado")+(Aramburu_Mensal!$N$6:$N$1098="a pagar")+(Aramburu_Mensal!$N$6:$N$1098="Pago")+(Aramburu_Mensal!$N$6:$N$1098="Provisionado DV"))*(Aramburu_Mensal!$O$6:$O$1098)) -> -14130.79 | L30: =SUMPRODUCT((Aramburu_Mensal!$C$6:$C$1098="abril")*(Aramburu_Mensal!$D$6:$D$1098="2.9 – Outras Saídas")*((Aramburu_Mensal!$N$6:$N$1098="provisionado")+(Aramburu_Mensal!$N$6:$N$1098="a pagar")+(Aramburu_Mensal!$N$6:$N$1098="Pago")+(Aramburu_Mensal!$N$6:$N$1098="Provisionado DV"))*(Aramburu_Mensal!$O$6:$O$1098)) -> -51900.1 | N30: =SUMPRODUCT((Aramburu_Mensal!$C$6:$C$1098="maio")*(Aramburu_Mensal!$D$6:$D$1098="2.9 – Outras Saídas")*((Aramburu_Mensal!$N$6:$N$1098="provisionado")+(Aramburu_Mensal!$N$6:$N$1098="a pagar")+(Aramburu_Mensal!$N$6:$N$1098="Pago")+(Aramburu_Mensal!$N$6:$N$1098="Provisionado DV"))*(Aramburu_Mensal!$O$6:$O$1098)) -> 0 | P30: =SUMPRODUCT((Aramburu_Mensal!$C$6:$C$1098="junho")*(Aramburu_Mensal!$D$6:$D$1098="2.9 – Outras Saídas")*((Aramburu_Mensal!$N$6:$N$1098="provisionado")+(Aramburu_Mensal!$N$6:$N$1098="a pagar")+(Aramburu_Mensal!$N$6:$N$1098="Pago")+(Aramburu_Mensal!$N$6:$N$1098="Provisionado DV"))*(Aramburu_Mensal!$O$6:$O$1098)) -> 0 | R30: =SUMPRODUCT((Aramburu_Mensal!$C$6:$C$1098="julho")*(Aramburu_Mensal!$D$6:$D$1098="2.9 – Outras Saídas")*((Aramburu_Mensal!$N$6:$N$1098="provisionado")+(Aramburu_Mensal!$N$6:$N$1098="a pagar")+(Aramburu_Mensal!$N$6:$N$1098="Pago")+(Aramburu_Mensal!$N$6:$N$1098="Provisionado DV"))*(Aramburu_Mensal!$O$6:$O$1098)) -> 0 | T30: =SUMPRODUCT((Aramburu_Mensal!$C$6:$C$1098="agosto")*(Aramburu_Mensal!$D$6:$D$1098="2.9 – Outras Saídas")*((Aramburu_Mensal!$N$6:$N$1098="provisionado")+(Aramburu_Mensal!$N$6:$N$1098="a pagar")+(Aramburu_Mensal!$N$6:$N$1098="Pago")+(Aramburu_Mensal!$N$6:$N$1098="Provisionado DV"))*(Aramburu_Mensal!$O$6:$O$1098)) -> 0 | V30: =SUMPRODUCT((Aramburu_Mensal!$C$6:$C$1098="setembro")*(Aramburu_Mensal!$D$6:$D$1098="2.9 – Outras Saídas")*((Aramburu_Mensal!$N$6:$N$1098="provisionado")+(Aramburu_Mensal!$N$6:$N$1098="a pagar")+(Aramburu_Mensal!$N$6:$N$1098="Pago")+(Aramburu_Mensal!$N$6:$N$1098="Provisionado DV"))*(Aramburu_Mensal!$O$6:$O$1098)) -> 0 | X30: =SUMPRODUCT((Aramburu_Mensal!$C$6:$C$1098="outubro")*(Aramburu_Mensal!$D$6:$D$1098="2.9 – Outras Saídas")*((Aramburu_Mensal!$N$6:$N$1098="provisionado")+(Aramburu_Mensal!$N$6:$N$1098="a pagar")+(Aramburu_Mensal!$N$6:$N$1098="Pago")+(Aramburu_Mensal!$N$6:$N$1098="Provisionado DV"))*(Aramburu_Mensal!$O$6:$O$1098)) -> 0 | Z30: =SUMPRODUCT((Aramburu_Mensal!$C$6:$C$1098="novembro")*(Aramburu_Mensal!$D$6:$D$1098="2.9 – Outras Saídas")*((Aramburu_Mensal!$N$6:$N$1098="provisionado")+(Aramburu_Mensal!$N$6:$N$1098="a pagar")+(Aramburu_Mensal!$N$6:$N$1098="Pago")+(Aramburu_Mensal!$N$6:$N$1098="Provisionado DV"))*(Aramburu_Mensal!$O$6:$O$1098)) -> 0 | AB30: =SUMPRODUCT((Aramburu_Mensal!$C$6:$C$1098="dezembro")*(Aramburu_Mensal!$D$6:$D$1098="2.9 – Outras Saídas")*((Aramburu_Mensal!$N$6:$N$1098="provisionado")+(Aramburu_Mensal!$N$6:$N$1098="a pagar")+(Aramburu_Mensal!$N$6:$N$1098="Pago")+(Aramburu_Mensal!$N$6:$N$1098="Provisionado DV"))*(Aramburu_Mensal!$O$6:$O$1098)) -> 0 | AD30: =SUM(F30:AC30) -> -292206.15 | AH30: =L45 -> -10614.41
D31: Saldo Final | E31: = | F31: =SUM(F21+F26) -> 1089144.9 | H31: =SUM(H21+H26) -> -121757.41 | J31: =SUM(J21+J26) -> 1308822.7 | L31: =SUM(L21+L26) -> -950016.85 | N31: =SUM(N21+N26) -> -272616.47 | P31: =SUM(P21+P26) -> -135260.67 | R31: =SUM(R21+R26) -> 600320.77 | T31: =SUM(T21+T26) -> -520912.57 | V31: =SUM(V21+V26) -> -288948.06 | X31: =SUM(X21+X26) -> -229413.2 | Z31: =SUM(Z21+Z26) -> -170322.43 | AB31: =SUM(AB21+AB26) -> -184335.4 | AD31: =SUM(AD21+AD26) -> 124705.34
D33: Saldo Final CORA (0001): | F33: =SUMPRODUCT((Aramburu_Mensal!$C$6:$C$1098="janeiro")*(Aramburu_Mensal!$M$6:$M$1098="Banco Cora (0001)")*((Aramburu_Mensal!$N$6:$N$1098="saldo inicial")+(Aramburu_Mensal!$N$6:$N$1098="pago")+(Aramburu_Mensal!$N$6:$N$1098="Recebido")+(Aramburu_Mensal!$N$6:$N$1098="Aplicação")+(Aramburu_Mensal!$N$6:$N$1098="Resgate")+(Aramburu_Mensal!$N$6:$N$1098="Repassado")+(Aramburu_Mensal!$N$6:$N$1098="Provisionado")+(Aramburu_Mensal!$N$6:$N$1098="Provisionado DV")+(Aramburu_Mensal!$N$6:$N$1098="A pagar")+(Aramburu_Mensal!$N$6:$N$1098="Provisionado DL")+(Aramburu_Mensal!$N$6:$N$1098="A repassar")+(Aramburu_Mensal!$N$6:$N$1098="A aplicar")+(Aramburu_Mensal!$N$6:$N$1098="A receber")+(Aramburu_Mensal!$N$6:$N$1098="A resgatar")+(Aramburu_Mensal!$N$6:$N$1098="Aplicado")+(Aramburu_Mensal!$N$6:$N$1098="Resgatado")),Aramburu_Mensal!$O$6:$O$1098) -> 1086493.1 | H33: =F33+SUMPRODUCT((Aramburu_Mensal!$C$6:$C$1098="fevereiro")*(Aramburu_Mensal!$M$6:$M$1098="Banco Cora (0001)")*((Aramburu_Mensal!$N$6:$N$1098="saldo inicial")+(Aramburu_Mensal!$N$6:$N$1098="pago")+(Aramburu_Mensal!$N$6:$N$1098="Recebido")+(Aramburu_Mensal!$N$6:$N$1098="Aplicação")+(Aramburu_Mensal!$N$6:$N$1098="Resgate")+(Aramburu_Mensal!$N$6:$N$1098="Repassado")+(Aramburu_Mensal!$N$6:$N$1098="Provisionado")+(Aramburu_Mensal!$N$6:$N$1098="Provisionado DV")+(Aramburu_Mensal!$N$6:$N$1098="A pagar")+(Aramburu_Mensal!$N$6:$N$1098="Provisionado DL")+(Aramburu_Mensal!$N$6:$N$1098="A repassar")+(Aramburu_Mensal!$N$6:$N$1098="A aplicar")+(Aramburu_Mensal!$N$6:$N$1098="A receber")+(Aramburu_Mensal!$N$6:$N$1098="A resgatar")+(Aramburu_Mensal!$N$6:$N$1098="Aplicado")+(Aramburu_Mensal!$N$6:$N$1098="Resgatado")),Aramburu_Mensal!$O$6:$O$1098) -> 965011.08 | J33: =H33+SUMPRODUCT((Aramburu_Mensal!$C$6:$C$1098="março")*(Aramburu_Mensal!$M$6:$M$1098="Banco Cora (0001)")*((Aramburu_Mensal!$N$6:$N$1098="saldo inicial")+(Aramburu_Mensal!$N$6:$N$1098="pago")+(Aramburu_Mensal!$N$6:$N$1098="Recebido")+(Aramburu_Mensal!$N$6:$N$1098="Aplicação")+(Aramburu_Mensal!$N$6:$N$1098="Resgate")+(Aramburu_Mensal!$N$6:$N$1098="Repassado")+(Aramburu_Mensal!$N$6:$N$1098="Provisionado")+(Aramburu_Mensal!$N$6:$N$1098="Provisionado DV")+(Aramburu_Mensal!$N$6:$N$1098="A pagar")+(Aramburu_Mensal!$N$6:$N$1098="Provisionado DL")+(Aramburu_Mensal!$N$6:$N$1098="A repassar")+(Aramburu_Mensal!$N$6:$N$1098="A aplicar")+(Aramburu_Mensal!$N$6:$N$1098="A receber")+(Aramburu_Mensal!$N$6:$N$1098="A resgatar")+(Aramburu_Mensal!$N$6:$N$1098="Aplicado")+(Aramburu_Mensal!$N$6:$N$1098="Resgatado")),Aramburu_Mensal!$O$6:$O$1098) -> 2274703.7 | L33: =J33+SUMPRODUCT((Aramburu_Mensal!$C$6:$C$1098="abril")*(Aramburu_Mensal!$M$6:$M$1098="Banco Cora (0001)")*((Aramburu_Mensal!$N$6:$N$1098="saldo inicial")+(Aramburu_Mensal!$N$6:$N$1098="pago")+(Aramburu_Mensal!$N$6:$N$1098="Recebido")+(Aramburu_Mensal!$N$6:$N$1098="Aplicação")+(Aramburu_Mensal!$N$6:$N$1098="Resgate")+(Aramburu_Mensal!$N$6:$N$1098="Repassado")+(Aramburu_Mensal!$N$6:$N$1098="Provisionado")+(Aramburu_Mensal!$N$6:$N$1098="Provisionado DV")+(Aramburu_Mensal!$N$6:$N$1098="A pagar")+(Aramburu_Mensal!$N$6:$N$1098="Provisionado DL")+(Aramburu_Mensal!$N$6:$N$1098="A repassar")+(Aramburu_Mensal!$N$6:$N$1098="A aplicar")+(Aramburu_Mensal!$N$6:$N$1098="A receber")+(Aramburu_Mensal!$N$6:$N$1098="A resgatar")+(Aramburu_Mensal!$N$6:$N$1098="Aplicado")+(Aramburu_Mensal!$N$6:$N$1098="Resgatado")),Aramburu_Mensal!$O$6:$O$1098) -> 1324843.3 | N33: =L33+SUMPRODUCT((Aramburu_Mensal!$C$6:$C$1098="maio")*(Aramburu_Mensal!$M$6:$M$1098="Banco Cora (0001)")*((Aramburu_Mensal!$N$6:$N$1098="saldo inicial")+(Aramburu_Mensal!$N$6:$N$1098="pago")+(Aramburu_Mensal!$N$6:$N$1098="Recebido")+(Aramburu_Mensal!$N$6:$N$1098="Aplicação")+(Aramburu_Mensal!$N$6:$N$1098="Resgate")+(Aramburu_Mensal!$N$6:$N$1098="Repassado")+(Aramburu_Mensal!$N$6:$N$1098="Provisionado")+(Aramburu_Mensal!$N$6:$N$1098="Provisionado DV")+(Aramburu_Mensal!$N$6:$N$1098="A pagar")+(Aramburu_Mensal!$N$6:$N$1098="Provisionado DL")+(Aramburu_Mensal!$N$6:$N$1098="A repassar")+(Aramburu_Mensal!$N$6:$N$1098="A aplicar")+(Aramburu_Mensal!$N$6:$N$1098="A receber")+(Aramburu_Mensal!$N$6:$N$1098="A resgatar")+(Aramburu_Mensal!$N$6:$N$1098="Aplicado")+(Aramburu_Mensal!$N$6:$N$1098="Resgatado")),Aramburu_Mensal!$O$6:$O$1098) -> 1052395.8 | P33: =N33+SUMPRODUCT((Aramburu_Mensal!$C$6:$C$1098="junho")*(Aramburu_Mensal!$M$6:$M$1098="Banco Cora (0001)")*((Aramburu_Mensal!$N$6:$N$1098="saldo inicial")+(Aramburu_Mensal!$N$6:$N$1098="pago")+(Aramburu_Mensal!$N$6:$N$1098="Recebido")+(Aramburu_Mensal!$N$6:$N$1098="Aplicação")+(Aramburu_Mensal!$N$6:$N$1098="Resgate")+(Aramburu_Mensal!$N$6:$N$1098="Repassado")+(Aramburu_Mensal!$N$6:$N$1098="Provisionado")+(Aramburu_Mensal!$N$6:$N$1098="Provisionado DV")+(Aramburu_Mensal!$N$6:$N$1098="A pagar")+(Aramburu_Mensal!$N$6:$N$1098="Provisionado DL")+(Aramburu_Mensal!$N$6:$N$1098="A repassar")+(Aramburu_Mensal!$N$6:$N$1098="A aplicar")+(Aramburu_Mensal!$N$6:$N$1098="A receber")+(Aramburu_Mensal!$N$6:$N$1098="A resgatar")+(Aramburu_Mensal!$N$6:$N$1098="Aplicado")+(Aramburu_Mensal!$N$6:$N$1098="Resgatado")),Aramburu_Mensal!$O$6:$O$1098) -> 917304.16 | R33: =P33+SUMPRODUCT((Aramburu_Mensal!$C$6:$C$1098="julho")*(Aramburu_Mensal!$M$6:$M$1098="Banco Cora (0001)")*((Aramburu_Mensal!$N$6:$N$1098="saldo inicial")+(Aramburu_Mensal!$N$6:$N$1098="pago")+(Aramburu_Mensal!$N$6:$N$1098="Recebido")+(Aramburu_Mensal!$N$6:$N$1098="Aplicação")+(Aramburu_Mensal!$N$6:$N$1098="Resgate")+(Aramburu_Mensal!$N$6:$N$1098="Repassado")+(Aramburu_Mensal!$N$6:$N$1098="Provisionado")+(Aramburu_Mensal!$N$6:$N$1098="Provisionado DV")+(Aramburu_Mensal!$N$6:$N$1098="A pagar")+(Aramburu_Mensal!$N$6:$N$1098="Provisionado DL")+(Aramburu_Mensal!$N$6:$N$1098="A repassar")+(Aramburu_Mensal!$N$6:$N$1098="A aplicar")+(Aramburu_Mensal!$N$6:$N$1098="A receber")+(Aramburu_Mensal!$N$6:$N$1098="A resgatar")+(Aramburu_Mensal!$N$6:$N$1098="Aplicado")+(Aramburu_Mensal!$N$6:$N$1098="Resgatado")),Aramburu_Mensal!$O$6:$O$1098) -> 1517793.9 | T33: =R33+SUMPRODUCT((Aramburu_Mensal!$C$6:$C$1098="agosto")*(Aramburu_Mensal!$M$6:$M$1098="Banco Cora (0001)")*((Aramburu_Mensal!$N$6:$N$1098="saldo inicial")+(Aramburu_Mensal!$N$6:$N$1098="pago")+(Aramburu_Mensal!$N$6:$N$1098="Recebido")+(Aramburu_Mensal!$N$6:$N$1098="Aplicação")+(Aramburu_Mensal!$N$6:$N$1098="Resgate")+(Aramburu_Mensal!$N$6:$N$1098="Repassado")+(Aramburu_Mensal!$N$6:$N$1098="Provisionado")+(Aramburu_Mensal!$N$6:$N$1098="Provisionado DV")+(Aramburu_Mensal!$N$6:$N$1098="A pagar")+(Aramburu_Mensal!$N$6:$N$1098="Provisionado DL")+(Aramburu_Mensal!$N$6:$N$1098="A repassar")+(Aramburu_Mensal!$N$6:$N$1098="A aplicar")+(Aramburu_Mensal!$N$6:$N$1098="A receber")+(Aramburu_Mensal!$N$6:$N$1098="A resgatar")+(Aramburu_Mensal!$N$6:$N$1098="Aplicado")+(Aramburu_Mensal!$N$6:$N$1098="Resgatado")),Aramburu_Mensal!$O$6:$O$1098) -> 997050.36 | V33: =T33+SUMPRODUCT((Aramburu_Mensal!$C$6:$C$1098="setembro")*(Aramburu_Mensal!$M$6:$M$1098="Banco Cora (0001)")*((Aramburu_Mensal!$N$6:$N$1098="saldo inicial")+(Aramburu_Mensal!$N$6:$N$1098="pago")+(Aramburu_Mensal!$N$6:$N$1098="Recebido")+(Aramburu_Mensal!$N$6:$N$1098="Aplicação")+(Aramburu_Mensal!$N$6:$N$1098="Resgate")+(Aramburu_Mensal!$N$6:$N$1098="Repassado")+(Aramburu_Mensal!$N$6:$N$1098="Provisionado")+(Aramburu_Mensal!$N$6:$N$1098="Provisionado DV")+(Aramburu_Mensal!$N$6:$N$1098="A pagar")+(Aramburu_Mensal!$N$6:$N$1098="Provisionado DL")+(Aramburu_Mensal!$N$6:$N$1098="A repassar")+(Aramburu_Mensal!$N$6:$N$1098="A aplicar")+(Aramburu_Mensal!$N$6:$N$1098="A receber")+(Aramburu_Mensal!$N$6:$N$1098="A resgatar")+(Aramburu_Mensal!$N$6:$N$1098="Aplicado")+(Aramburu_Mensal!$N$6:$N$1098="Resgatado")),Aramburu_Mensal!$O$6:$O$1098) -> 708271.3 | X33: =V33+SUMPRODUCT((Aramburu_Mensal!$C$6:$C$1098="outubro")*(Aramburu_Mensal!$M$6:$M$1098="Banco Cora (0001)")*((Aramburu_Mensal!$N$6:$N$1098="saldo inicial")+(Aramburu_Mensal!$N$6:$N$1098="pago")+(Aramburu_Mensal!$N$6:$N$1098="Recebido")+(Aramburu_Mensal!$N$6:$N$1098="Aplicação")+(Aramburu_Mensal!$N$6:$N$1098="Resgate")+(Aramburu_Mensal!$N$6:$N$1098="Repassado")+(Aramburu_Mensal!$N$6:$N$1098="Provisionado")+(Aramburu_Mensal!$N$6:$N$1098="Provisionado DV")+(Aramburu_Mensal!$N$6:$N$1098="A pagar")+(Aramburu_Mensal!$N$6:$N$1098="Provisionado DL")+(Aramburu_Mensal!$N$6:$N$1098="A repassar")+(Aramburu_Mensal!$N$6:$N$1098="A aplicar")+(Aramburu_Mensal!$N$6:$N$1098="A receber")+(Aramburu_Mensal!$N$6:$N$1098="A resgatar")+(Aramburu_Mensal!$N$6:$N$1098="Aplicado")+(Aramburu_Mensal!$N$6:$N$1098="Resgatado")),Aramburu_Mensal!$O$6:$O$1098) -> 479027.1 | Z33: =X33+SUMPRODUCT((Aramburu_Mensal!$C$6:$C$1098="novembro")*(Aramburu_Mensal!$M$6:$M$1098="Banco Cora (0001)")*((Aramburu_Mensal!$N$6:$N$1098="saldo inicial")+(Aramburu_Mensal!$N$6:$N$1098="pago")+(Aramburu_Mensal!$N$6:$N$1098="Recebido")+(Aramburu_Mensal!$N$6:$N$1098="Aplicação")+(Aramburu_Mensal!$N$6:$N$1098="Resgate")+(Aramburu_Mensal!$N$6:$N$1098="Repassado")+(Aramburu_Mensal!$N$6:$N$1098="Provisionado")+(Aramburu_Mensal!$N$6:$N$1098="Provisionado DV")+(Aramburu_Mensal!$N$6:$N$1098="A pagar")+(Aramburu_Mensal!$N$6:$N$1098="Provisionado DL")+(Aramburu_Mensal!$N$6:$N$1098="A repassar")+(Aramburu_Mensal!$N$6:$N$1098="A aplicar")+(Aramburu_Mensal!$N$6:$N$1098="A receber")+(Aramburu_Mensal!$N$6:$N$1098="A resgatar")+(Aramburu_Mensal!$N$6:$N$1098="Aplicado")+(Aramburu_Mensal!$N$6:$N$1098="Resgatado")),Aramburu_Mensal!$O$6:$O$1098) -> 308873.67 | AB33: =Z33+SUMPRODUCT((Aramburu_Mensal!$C$6:$C$1098="dezembro")*(Aramburu_Mensal!$M$6:$M$1098="Banco Cora (0001)")*((Aramburu_Mensal!$N$6:$N$1098="saldo inicial")+(Aramburu_Mensal!$N$6:$N$1098="pago")+(Aramburu_Mensal!$N$6:$N$1098="Recebido")+(Aramburu_Mensal!$N$6:$N$1098="Aplicação")+(Aramburu_Mensal!$N$6:$N$1098="Resgate")+(Aramburu_Mensal!$N$6:$N$1098="Repassado")+(Aramburu_Mensal!$N$6:$N$1098="Provisionado")+(Aramburu_Mensal!$N$6:$N$1098="Provisionado DV")+(Aramburu_Mensal!$N$6:$N$1098="A pagar")+(Aramburu_Mensal!$N$6:$N$1098="Provisionado DL")+(Aramburu_Mensal!$N$6:$N$1098="A repassar")+(Aramburu_Mensal!$N$6:$N$1098="A aplicar")+(Aramburu_Mensal!$N$6:$N$1098="A receber")+(Aramburu_Mensal!$N$6:$N$1098="A resgatar")+(Aramburu_Mensal!$N$6:$N$1098="Aplicado")+(Aramburu_Mensal!$N$6:$N$1098="Resgatado")),Aramburu_Mensal!$O$6:$O$1098) -> 124707.27
D34: Saldo Final SICREDI (0902): | F34: =ROUND(SUMPRODUCT((Aramburu_Mensal!$C$6:$C$1098="janeiro")*(Aramburu_Mensal!$M$6:$M$1098="Cooperativa Sicredi (0902)")*((Aramburu_Mensal!$N$6:$N$1098="saldo inicial")+(Aramburu_Mensal!$N$6:$N$1098="pago")+(Aramburu_Mensal!$N$6:$N$1098="Recebido")+(Aramburu_Mensal!$N$6:$N$1098="Aplicação")+(Aramburu_Mensal!$N$6:$N$1098="Resgate")+(Aramburu_Mensal!$N$6:$N$1098="Repassado")+(Aramburu_Mensal!$N$6:$N$1098="Provisionado")+(Aramburu_Mensal!$N$6:$N$1098="Provisionado DV")+(Aramburu_Mensal!$N$6:$N$1098="A pagar")+(Aramburu_Mensal!$N$6:$N$1098="Provisionado DL")+(Aramburu_Mensal!$N$6:$N$1098="A repassar")+(Aramburu_Mensal!$N$6:$N$1098="A aplicar")+(Aramburu_Mensal!$N$6:$N$1098="A receber")+(Aramburu_Mensal!$N$6:$N$1098="A resgatar")+(Aramburu_Mensal!$N$6:$N$1098="Aplicado")+(Aramburu_Mensal!$N$6:$N$1098="Resgatado")),Aramburu_Mensal!$O$6:$O$1098),2) -> 832.25 | H34: =ROUND(F34+SUMPRODUCT((Aramburu_Mensal!$C$6:$C$1098="fevereiro")*(Aramburu_Mensal!$M$6:$M$1098="Cooperativa Sicredi (0902)")*((Aramburu_Mensal!$N$6:$N$1098="saldo inicial")+(Aramburu_Mensal!$N$6:$N$1098="pago")+(Aramburu_Mensal!$N$6:$N$1098="Recebido")+(Aramburu_Mensal!$N$6:$N$1098="Aplicação")+(Aramburu_Mensal!$N$6:$N$1098="Resgate")+(Aramburu_Mensal!$N$6:$N$1098="Repassado")+(Aramburu_Mensal!$N$6:$N$1098="Provisionado")+(Aramburu_Mensal!$N$6:$N$1098="Provisionado DV")+(Aramburu_Mensal!$N$6:$N$1098="A pagar")+(Aramburu_Mensal!$N$6:$N$1098="Provisionado DL")+(Aramburu_Mensal!$N$6:$N$1098="A repassar")+(Aramburu_Mensal!$N$6:$N$1098="A aplicar")+(Aramburu_Mensal!$N$6:$N$1098="A receber")+(Aramburu_Mensal!$N$6:$N$1098="A resgatar")+(Aramburu_Mensal!$N$6:$N$1098="Aplicado")+(Aramburu_Mensal!$N$6:$N$1098="Resgatado")),Aramburu_Mensal!$O$6:$O$1098),2) -> 713.35 | J34: =ROUND(H34+SUMPRODUCT((Aramburu_Mensal!$C$6:$C$1098="março")*(Aramburu_Mensal!$M$6:$M$1098="Cooperativa Sicredi (0902)")*((Aramburu_Mensal!$N$6:$N$1098="saldo inicial")+(Aramburu_Mensal!$N$6:$N$1098="pago")+(Aramburu_Mensal!$N$6:$N$1098="Recebido")+(Aramburu_Mensal!$N$6:$N$1098="Aplicação")+(Aramburu_Mensal!$N$6:$N$1098="Resgate")+(Aramburu_Mensal!$N$6:$N$1098="Repassado")+(Aramburu_Mensal!$N$6:$N$1098="Provisionado")+(Aramburu_Mensal!$N$6:$N$1098="Provisionado DV")+(Aramburu_Mensal!$N$6:$N$1098="A pagar")+(Aramburu_Mensal!$N$6:$N$1098="Provisionado DL")+(Aramburu_Mensal!$N$6:$N$1098="A repassar")+(Aramburu_Mensal!$N$6:$N$1098="A aplicar")+(Aramburu_Mensal!$N$6:$N$1098="A receber")+(Aramburu_Mensal!$N$6:$N$1098="A resgatar")+(Aramburu_Mensal!$N$6:$N$1098="Aplicado")+(Aramburu_Mensal!$N$6:$N$1098="Resgatado")),Aramburu_Mensal!$O$6:$O$1098),2) -> 0 | L34: =ROUND(J34+SUMPRODUCT((Aramburu_Mensal!$C$6:$C$1098="abril")*(Aramburu_Mensal!$M$6:$M$1098="Cooperativa Sicredi (0902)")*((Aramburu_Mensal!$N$6:$N$1098="saldo inicial")+(Aramburu_Mensal!$N$6:$N$1098="pago")+(Aramburu_Mensal!$N$6:$N$1098="Recebido")+(Aramburu_Mensal!$N$6:$N$1098="Aplicação")+(Aramburu_Mensal!$N$6:$N$1098="Resgate")+(Aramburu_Mensal!$N$6:$N$1098="Repassado")+(Aramburu_Mensal!$N$6:$N$1098="Provisionado")+(Aramburu_Mensal!$N$6:$N$1098="Provisionado DV")+(Aramburu_Mensal!$N$6:$N$1098="A pagar")+(Aramburu_Mensal!$N$6:$N$1098="Provisionado DL")+(Aramburu_Mensal!$N$6:$N$1098="A repassar")+(Aramburu_Mensal!$N$6:$N$1098="A aplicar")+(Aramburu_Mensal!$N$6:$N$1098="A receber")+(Aramburu_Mensal!$N$6:$N$1098="A resgatar")+(Aramburu_Mensal!$N$6:$N$1098="Aplicado")+(Aramburu_Mensal!$N$6:$N$1098="Resgatado")),Aramburu_Mensal!$O$6:$O$1098),2) -> 0 | N34: =ROUND(L34+SUMPRODUCT((Aramburu_Mensal!$C$6:$C$1098="maio")*(Aramburu_Mensal!$M$6:$M$1098="Cooperativa Sicredi (0902)")*((Aramburu_Mensal!$N$6:$N$1098="saldo inicial")+(Aramburu_Mensal!$N$6:$N$1098="pago")+(Aramburu_Mensal!$N$6:$N$1098="Recebido")+(Aramburu_Mensal!$N$6:$N$1098="Aplicação")+(Aramburu_Mensal!$N$6:$N$1098="Resgate")+(Aramburu_Mensal!$N$6:$N$1098="Repassado")+(Aramburu_Mensal!$N$6:$N$1098="Provisionado")+(Aramburu_Mensal!$N$6:$N$1098="Provisionado DV")+(Aramburu_Mensal!$N$6:$N$1098="A pagar")+(Aramburu_Mensal!$N$6:$N$1098="Provisionado DL")+(Aramburu_Mensal!$N$6:$N$1098="A repassar")+(Aramburu_Mensal!$N$6:$N$1098="A aplicar")+(Aramburu_Mensal!$N$6:$N$1098="A receber")+(Aramburu_Mensal!$N$6:$N$1098="A resgatar")+(Aramburu_Mensal!$N$6:$N$1098="Aplicado")+(Aramburu_Mensal!$N$6:$N$1098="Resgatado")),Aramburu_Mensal!$O$6:$O$1098),2) -> 0 | P34: =ROUND(N34++SUMPRODUCT((Aramburu_Mensal!$C$6:$C$1098="junho")*(Aramburu_Mensal!$M$6:$M$1098="Cooperativa Sicredi (0902)")*((Aramburu_Mensal!$N$6:$N$1098="saldo inicial")+(Aramburu_Mensal!$N$6:$N$1098="pago")+(Aramburu_Mensal!$N$6:$N$1098="Recebido")+(Aramburu_Mensal!$N$6:$N$1098="Aplicação")+(Aramburu_Mensal!$N$6:$N$1098="Resgate")+(Aramburu_Mensal!$N$6:$N$1098="Repassado")+(Aramburu_Mensal!$N$6:$N$1098="Provisionado")+(Aramburu_Mensal!$N$6:$N$1098="Provisionado DV")+(Aramburu_Mensal!$N$6:$N$1098="A pagar")+(Aramburu_Mensal!$N$6:$N$1098="Provisionado DL")+(Aramburu_Mensal!$N$6:$N$1098="A repassar")+(Aramburu_Mensal!$N$6:$N$1098="A aplicar")+(Aramburu_Mensal!$N$6:$N$1098="A receber")+(Aramburu_Mensal!$N$6:$N$1098="A resgatar")+(Aramburu_Mensal!$N$6:$N$1098="Aplicado")+(Aramburu_Mensal!$N$6:$N$1098="Resgatado")),Aramburu_Mensal!$O$6:$O$1098),2) -> 0 | R34: =ROUND(P34+SUMPRODUCT((Aramburu_Mensal!$C$6:$C$1098="julho")*(Aramburu_Mensal!$M$6:$M$1098="Cooperativa Sicredi (0902)")*((Aramburu_Mensal!$N$6:$N$1098="saldo inicial")+(Aramburu_Mensal!$N$6:$N$1098="pago")+(Aramburu_Mensal!$N$6:$N$1098="Recebido")+(Aramburu_Mensal!$N$6:$N$1098="Aplicação")+(Aramburu_Mensal!$N$6:$N$1098="Resgate")+(Aramburu_Mensal!$N$6:$N$1098="Repassado")+(Aramburu_Mensal!$N$6:$N$1098="Provisionado")+(Aramburu_Mensal!$N$6:$N$1098="Provisionado DV")+(Aramburu_Mensal!$N$6:$N$1098="A pagar")+(Aramburu_Mensal!$N$6:$N$1098="Provisionado DL")+(Aramburu_Mensal!$N$6:$N$1098="A repassar")+(Aramburu_Mensal!$N$6:$N$1098="A aplicar")+(Aramburu_Mensal!$N$6:$N$1098="A receber")+(Aramburu_Mensal!$N$6:$N$1098="A resgatar")+(Aramburu_Mensal!$N$6:$N$1098="Aplicado")+(Aramburu_Mensal!$N$6:$N$1098="Resgatado")),Aramburu_Mensal!$O$6:$O$1098),2) -> 0 | T34: =ROUND(R34+SUMPRODUCT((Aramburu_Mensal!$C$6:$C$1098="agosto")*(Aramburu_Mensal!$M$6:$M$1098="Cooperativa Sicredi (0902)")*((Aramburu_Mensal!$N$6:$N$1098="saldo inicial")+(Aramburu_Mensal!$N$6:$N$1098="pago")+(Aramburu_Mensal!$N$6:$N$1098="Recebido")+(Aramburu_Mensal!$N$6:$N$1098="Aplicação")+(Aramburu_Mensal!$N$6:$N$1098="Resgate")+(Aramburu_Mensal!$N$6:$N$1098="Repassado")+(Aramburu_Mensal!$N$6:$N$1098="Provisionado")+(Aramburu_Mensal!$N$6:$N$1098="Provisionado DV")+(Aramburu_Mensal!$N$6:$N$1098="A pagar")+(Aramburu_Mensal!$N$6:$N$1098="Provisionado DL")+(Aramburu_Mensal!$N$6:$N$1098="A repassar")+(Aramburu_Mensal!$N$6:$N$1098="A aplicar")+(Aramburu_Mensal!$N$6:$N$1098="A receber")+(Aramburu_Mensal!$N$6:$N$1098="A resgatar")+(Aramburu_Mensal!$N$6:$N$1098="Aplicado")+(Aramburu_Mensal!$N$6:$N$1098="Resgatado")),Aramburu_Mensal!$O$6:$O$1098),2) -> 0 | V34: =ROUND(T34+SUMPRODUCT((Aramburu_Mensal!$C$6:$C$1098="setembro")*(Aramburu_Mensal!$M$6:$M$1098="Cooperativa Sicredi (0902)")*((Aramburu_Mensal!$N$6:$N$1098="saldo inicial")+(Aramburu_Mensal!$N$6:$N$1098="pago")+(Aramburu_Mensal!$N$6:$N$1098="Recebido")+(Aramburu_Mensal!$N$6:$N$1098="Aplicação")+(Aramburu_Mensal!$N$6:$N$1098="Resgate")+(Aramburu_Mensal!$N$6:$N$1098="Repassado")+(Aramburu_Mensal!$N$6:$N$1098="Provisionado")+(Aramburu_Mensal!$N$6:$N$1098="Provisionado DV")+(Aramburu_Mensal!$N$6:$N$1098="A pagar")+(Aramburu_Mensal!$N$6:$N$1098="Provisionado DL")+(Aramburu_Mensal!$N$6:$N$1098="A repassar")+(Aramburu_Mensal!$N$6:$N$1098="A aplicar")+(Aramburu_Mensal!$N$6:$N$1098="A receber")+(Aramburu_Mensal!$N$6:$N$1098="A resgatar")+(Aramburu_Mensal!$N$6:$N$1098="Aplicado")+(Aramburu_Mensal!$N$6:$N$1098="Resgatado")),Aramburu_Mensal!$O$6:$O$1098),2) -> 0 | X34: =ROUND(V34+SUMPRODUCT((Aramburu_Mensal!$C$6:$C$1098="outubro")*(Aramburu_Mensal!$M$6:$M$1098="Cooperativa Sicredi (0902)")*((Aramburu_Mensal!$N$6:$N$1098="saldo inicial")+(Aramburu_Mensal!$N$6:$N$1098="pago")+(Aramburu_Mensal!$N$6:$N$1098="Recebido")+(Aramburu_Mensal!$N$6:$N$1098="Aplicação")+(Aramburu_Mensal!$N$6:$N$1098="Resgate")+(Aramburu_Mensal!$N$6:$N$1098="Repassado")+(Aramburu_Mensal!$N$6:$N$1098="Provisionado")+(Aramburu_Mensal!$N$6:$N$1098="Provisionado DV")+(Aramburu_Mensal!$N$6:$N$1098="A pagar")+(Aramburu_Mensal!$N$6:$N$1098="Provisionado DL")+(Aramburu_Mensal!$N$6:$N$1098="A repassar")+(Aramburu_Mensal!$N$6:$N$1098="A aplicar")+(Aramburu_Mensal!$N$6:$N$1098="A receber")+(Aramburu_Mensal!$N$6:$N$1098="A resgatar")+(Aramburu_Mensal!$N$6:$N$1098="Aplicado")+(Aramburu_Mensal!$N$6:$N$1098="Resgatado")),Aramburu_Mensal!$O$6:$O$1098),2) -> 0 | Z34: =ROUND(X34+SUMPRODUCT((Aramburu_Mensal!$C$6:$C$1098="novembro")*(Aramburu_Mensal!$M$6:$M$1098="Cooperativa Sicredi (0902)")*((Aramburu_Mensal!$N$6:$N$1098="saldo inicial")+(Aramburu_Mensal!$N$6:$N$1098="pago")+(Aramburu_Mensal!$N$6:$N$1098="Recebido")+(Aramburu_Mensal!$N$6:$N$1098="Aplicação")+(Aramburu_Mensal!$N$6:$N$1098="Resgate")+(Aramburu_Mensal!$N$6:$N$1098="Repassado")+(Aramburu_Mensal!$N$6:$N$1098="Provisionado")+(Aramburu_Mensal!$N$6:$N$1098="Provisionado DV")+(Aramburu_Mensal!$N$6:$N$1098="A pagar")+(Aramburu_Mensal!$N$6:$N$1098="Provisionado DL")+(Aramburu_Mensal!$N$6:$N$1098="A repassar")+(Aramburu_Mensal!$N$6:$N$1098="A aplicar")+(Aramburu_Mensal!$N$6:$N$1098="A receber")+(Aramburu_Mensal!$N$6:$N$1098="A resgatar")+(Aramburu_Mensal!$N$6:$N$1098="Aplicado")+(Aramburu_Mensal!$N$6:$N$1098="Resgatado")),Aramburu_Mensal!$O$6:$O$1098),2) -> 0 | AB34: =ROUND(Z34+SUMPRODUCT((Aramburu_Mensal!$C$6:$C$1098="dezembro")*(Aramburu_Mensal!$M$6:$M$1098="Cooperativa Sicredi (0902)")*((Aramburu_Mensal!$N$6:$N$1098="saldo inicial")+(Aramburu_Mensal!$N$6:$N$1098="pago")+(Aramburu_Mensal!$N$6:$N$1098="Recebido")+(Aramburu_Mensal!$N$6:$N$1098="Aplicação")+(Aramburu_Mensal!$N$6:$N$1098="Resgate")+(Aramburu_Mensal!$N$6:$N$1098="Repassado")+(Aramburu_Mensal!$N$6:$N$1098="Provisionado")+(Aramburu_Mensal!$N$6:$N$1098="Provisionado DV")+(Aramburu_Mensal!$N$6:$N$1098="A pagar")+(Aramburu_Mensal!$N$6:$N$1098="Provisionado DL")+(Aramburu_Mensal!$N$6:$N$1098="A repassar")+(Aramburu_Mensal!$N$6:$N$1098="A aplicar")+(Aramburu_Mensal!$N$6:$N$1098="A receber")+(Aramburu_Mensal!$N$6:$N$1098="A resgatar")+(Aramburu_Mensal!$N$6:$N$1098="Aplicado")+(Aramburu_Mensal!$N$6:$N$1098="Resgatado")),Aramburu_Mensal!$O$6:$O$1098),2) -> 0
D35: Saldo Final SICREDI (0913): | F35: =ROUND(SUMPRODUCT((Aramburu_Mensal!$C$6:$C$1098="janeiro")*(Aramburu_Mensal!$M$6:$M$1098="Cooperativa Sicredi (0913)")*((Aramburu_Mensal!$N$6:$N$1098="saldo inicial")+(Aramburu_Mensal!$N$6:$N$1098="pago")+(Aramburu_Mensal!$N$6:$N$1098="Recebido")+(Aramburu_Mensal!$N$6:$N$1098="Aplicação")+(Aramburu_Mensal!$N$6:$N$1098="Resgate")+(Aramburu_Mensal!$N$6:$N$1098="Repassado")+(Aramburu_Mensal!$N$6:$N$1098="Provisionado")+(Aramburu_Mensal!$N$6:$N$1098="Provisionado DV")+(Aramburu_Mensal!$N$6:$N$1098="A pagar")+(Aramburu_Mensal!$N$6:$N$1098="Provisionado DL")+(Aramburu_Mensal!$N$6:$N$1098="A repassar")+(Aramburu_Mensal!$N$6:$N$1098="A aplicar")+(Aramburu_Mensal!$N$6:$N$1098="A receber")+(Aramburu_Mensal!$N$6:$N$1098="A resgatar")+(Aramburu_Mensal!$N$6:$N$1098="Aplicado")+(Aramburu_Mensal!$N$6:$N$1098="Resgatado")),Aramburu_Mensal!$O$6:$O$1098),2) -> 1819.56 | H35: =ROUND(F35+SUMPRODUCT((Aramburu_Mensal!$C$6:$C$1098="fevereiro")*(Aramburu_Mensal!$M$6:$M$1098="Cooperativa Sicredi (0913)")*((Aramburu_Mensal!$N$6:$N$1098="saldo inicial")+(Aramburu_Mensal!$N$6:$N$1098="pago")+(Aramburu_Mensal!$N$6:$N$1098="Recebido")+(Aramburu_Mensal!$N$6:$N$1098="Aplicação")+(Aramburu_Mensal!$N$6:$N$1098="Resgate")+(Aramburu_Mensal!$N$6:$N$1098="Repassado")+(Aramburu_Mensal!$N$6:$N$1098="Provisionado")+(Aramburu_Mensal!$N$6:$N$1098="Provisionado DV")+(Aramburu_Mensal!$N$6:$N$1098="A pagar")+(Aramburu_Mensal!$N$6:$N$1098="Provisionado DL")+(Aramburu_Mensal!$N$6:$N$1098="A repassar")+(Aramburu_Mensal!$N$6:$N$1098="A aplicar")+(Aramburu_Mensal!$N$6:$N$1098="A receber")+(Aramburu_Mensal!$N$6:$N$1098="A resgatar")+(Aramburu_Mensal!$N$6:$N$1098="Aplicado")+(Aramburu_Mensal!$N$6:$N$1098="Resgatado")),Aramburu_Mensal!$O$6:$O$1098),2) -> 1663.06 | J35: =ROUND(H35+SUMPRODUCT((Aramburu_Mensal!$C$6:$C$1098="março")*(Aramburu_Mensal!$M$6:$M$1098="Cooperativa Sicredi (0913)")*((Aramburu_Mensal!$N$6:$N$1098="saldo inicial")+(Aramburu_Mensal!$N$6:$N$1098="pago")+(Aramburu_Mensal!$N$6:$N$1098="Recebido")+(Aramburu_Mensal!$N$6:$N$1098="Aplicação")+(Aramburu_Mensal!$N$6:$N$1098="Resgate")+(Aramburu_Mensal!$N$6:$N$1098="Repassado")+(Aramburu_Mensal!$N$6:$N$1098="Provisionado")+(Aramburu_Mensal!$N$6:$N$1098="Provisionado DV")+(Aramburu_Mensal!$N$6:$N$1098="A pagar")+(Aramburu_Mensal!$N$6:$N$1098="Provisionado DL")+(Aramburu_Mensal!$N$6:$N$1098="A repassar")+(Aramburu_Mensal!$N$6:$N$1098="A aplicar")+(Aramburu_Mensal!$N$6:$N$1098="A receber")+(Aramburu_Mensal!$N$6:$N$1098="A resgatar")+(Aramburu_Mensal!$N$6:$N$1098="Aplicado")+(Aramburu_Mensal!$N$6:$N$1098="Resgatado")),Aramburu_Mensal!$O$6:$O$1098),2) -> 1506.56 | L35: =ROUND(J35+SUMPRODUCT((Aramburu_Mensal!$C$6:$C$1098="abril")*(Aramburu_Mensal!$M$6:$M$1098="Cooperativa Sicredi (0913)")*((Aramburu_Mensal!$N$6:$N$1098="saldo inicial")+(Aramburu_Mensal!$N$6:$N$1098="pago")+(Aramburu_Mensal!$N$6:$N$1098="Recebido")+(Aramburu_Mensal!$N$6:$N$1098="Aplicação")+(Aramburu_Mensal!$N$6:$N$1098="Resgate")+(Aramburu_Mensal!$N$6:$N$1098="Repassado")+(Aramburu_Mensal!$N$6:$N$1098="Provisionado")+(Aramburu_Mensal!$N$6:$N$1098="Provisionado DV")+(Aramburu_Mensal!$N$6:$N$1098="A pagar")+(Aramburu_Mensal!$N$6:$N$1098="Provisionado DL")+(Aramburu_Mensal!$N$6:$N$1098="A repassar")+(Aramburu_Mensal!$N$6:$N$1098="A aplicar")+(Aramburu_Mensal!$N$6:$N$1098="A receber")+(Aramburu_Mensal!$N$6:$N$1098="A resgatar")+(Aramburu_Mensal!$N$6:$N$1098="Aplicado")+(Aramburu_Mensal!$N$6:$N$1098="Resgatado")),Aramburu_Mensal!$O$6:$O$1098),2) -> 1350.06 | N35: =ROUND(L35+SUMPRODUCT((Aramburu_Mensal!$C$6:$C$1098="maio")*(Aramburu_Mensal!$M$6:$M$1098="Cooperativa Sicredi (0913)")*((Aramburu_Mensal!$N$6:$N$1098="saldo inicial")+(Aramburu_Mensal!$N$6:$N$1098="pago")+(Aramburu_Mensal!$N$6:$N$1098="Recebido")+(Aramburu_Mensal!$N$6:$N$1098="Aplicação")+(Aramburu_Mensal!$N$6:$N$1098="Resgate")+(Aramburu_Mensal!$N$6:$N$1098="Repassado")+(Aramburu_Mensal!$N$6:$N$1098="Provisionado")+(Aramburu_Mensal!$N$6:$N$1098="Provisionado DV")+(Aramburu_Mensal!$N$6:$N$1098="A pagar")+(Aramburu_Mensal!$N$6:$N$1098="Provisionado DL")+(Aramburu_Mensal!$N$6:$N$1098="A repassar")+(Aramburu_Mensal!$N$6:$N$1098="A aplicar")+(Aramburu_Mensal!$N$6:$N$1098="A receber")+(Aramburu_Mensal!$N$6:$N$1098="A resgatar")+(Aramburu_Mensal!$N$6:$N$1098="Aplicado")+(Aramburu_Mensal!$N$6:$N$1098="Resgatado")),Aramburu_Mensal!$O$6:$O$1098),2) -> 1181.06 | P35: =ROUND(N35++SUMPRODUCT((Aramburu_Mensal!$C$6:$C$1098="junho")*(Aramburu_Mensal!$M$6:$M$1098="Cooperativa Sicredi (0913)")*((Aramburu_Mensal!$N$6:$N$1098="saldo inicial")+(Aramburu_Mensal!$N$6:$N$1098="pago")+(Aramburu_Mensal!$N$6:$N$1098="Recebido")+(Aramburu_Mensal!$N$6:$N$1098="Aplicação")+(Aramburu_Mensal!$N$6:$N$1098="Resgate")+(Aramburu_Mensal!$N$6:$N$1098="Repassado")+(Aramburu_Mensal!$N$6:$N$1098="Provisionado")+(Aramburu_Mensal!$N$6:$N$1098="Provisionado DV")+(Aramburu_Mensal!$N$6:$N$1098="A pagar")+(Aramburu_Mensal!$N$6:$N$1098="Provisionado DL")+(Aramburu_Mensal!$N$6:$N$1098="A repassar")+(Aramburu_Mensal!$N$6:$N$1098="A aplicar")+(Aramburu_Mensal!$N$6:$N$1098="A receber")+(Aramburu_Mensal!$N$6:$N$1098="A resgatar")+(Aramburu_Mensal!$N$6:$N$1098="Aplicado")+(Aramburu_Mensal!$N$6:$N$1098="Resgatado")),Aramburu_Mensal!$O$6:$O$1098),2) -> 1012.07 | R35: =ROUND(P35+SUMPRODUCT((Aramburu_Mensal!$C$6:$C$1098="julho")*(Aramburu_Mensal!$M$6:$M$1098="Cooperativa Sicredi (0913)")*((Aramburu_Mensal!$N$6:$N$1098="saldo inicial")+(Aramburu_Mensal!$N$6:$N$1098="pago")+(Aramburu_Mensal!$N$6:$N$1098="Recebido")+(Aramburu_Mensal!$N$6:$N$1098="Aplicação")+(Aramburu_Mensal!$N$6:$N$1098="Resgate")+(Aramburu_Mensal!$N$6:$N$1098="Repassado")+(Aramburu_Mensal!$N$6:$N$1098="Provisionado")+(Aramburu_Mensal!$N$6:$N$1098="Provisionado DV")+(Aramburu_Mensal!$N$6:$N$1098="A pagar")+(Aramburu_Mensal!$N$6:$N$1098="Provisionado DL")+(Aramburu_Mensal!$N$6:$N$1098="A repassar")+(Aramburu_Mensal!$N$6:$N$1098="A aplicar")+(Aramburu_Mensal!$N$6:$N$1098="A receber")+(Aramburu_Mensal!$N$6:$N$1098="A resgatar")+(Aramburu_Mensal!$N$6:$N$1098="Aplicado")+(Aramburu_Mensal!$N$6:$N$1098="Resgatado")),Aramburu_Mensal!$O$6:$O$1098),2) -> 843.07 | T35: =ROUND(R35+SUMPRODUCT((Aramburu_Mensal!$C$6:$C$1098="agosto")*(Aramburu_Mensal!$M$6:$M$1098="Cooperativa Sicredi (0913)")*((Aramburu_Mensal!$N$6:$N$1098="saldo inicial")+(Aramburu_Mensal!$N$6:$N$1098="pago")+(Aramburu_Mensal!$N$6:$N$1098="Recebido")+(Aramburu_Mensal!$N$6:$N$1098="Aplicação")+(Aramburu_Mensal!$N$6:$N$1098="Resgate")+(Aramburu_Mensal!$N$6:$N$1098="Repassado")+(Aramburu_Mensal!$N$6:$N$1098="Provisionado")+(Aramburu_Mensal!$N$6:$N$1098="Provisionado DV")+(Aramburu_Mensal!$N$6:$N$1098="A pagar")+(Aramburu_Mensal!$N$6:$N$1098="Provisionado DL")+(Aramburu_Mensal!$N$6:$N$1098="A repassar")+(Aramburu_Mensal!$N$6:$N$1098="A aplicar")+(Aramburu_Mensal!$N$6:$N$1098="A receber")+(Aramburu_Mensal!$N$6:$N$1098="A resgatar")+(Aramburu_Mensal!$N$6:$N$1098="Aplicado")+(Aramburu_Mensal!$N$6:$N$1098="Resgatado")),Aramburu_Mensal!$O$6:$O$1098),2) -> 674.07 | V35: =ROUND(T35+SUMPRODUCT((Aramburu_Mensal!$C$6:$C$1098="setembro")*(Aramburu_Mensal!$M$6:$M$1098="Cooperativa Sicredi (0913)")*((Aramburu_Mensal!$N$6:$N$1098="saldo inicial")+(Aramburu_Mensal!$N$6:$N$1098="pago")+(Aramburu_Mensal!$N$6:$N$1098="Recebido")+(Aramburu_Mensal!$N$6:$N$1098="Aplicação")+(Aramburu_Mensal!$N$6:$N$1098="Resgate")+(Aramburu_Mensal!$N$6:$N$1098="Repassado")+(Aramburu_Mensal!$N$6:$N$1098="Provisionado")+(Aramburu_Mensal!$N$6:$N$1098="Provisionado DV")+(Aramburu_Mensal!$N$6:$N$1098="A pagar")+(Aramburu_Mensal!$N$6:$N$1098="Provisionado DL")+(Aramburu_Mensal!$N$6:$N$1098="A repassar")+(Aramburu_Mensal!$N$6:$N$1098="A aplicar")+(Aramburu_Mensal!$N$6:$N$1098="A receber")+(Aramburu_Mensal!$N$6:$N$1098="A resgatar")+(Aramburu_Mensal!$N$6:$N$1098="Aplicado")+(Aramburu_Mensal!$N$6:$N$1098="Resgatado")),Aramburu_Mensal!$O$6:$O$1098),2) -> 505.07 | X35: =ROUND(V35+SUMPRODUCT((Aramburu_Mensal!$C$6:$C$1098="outubro")*(Aramburu_Mensal!$M$6:$M$1098="Cooperativa Sicredi (0913)")*((Aramburu_Mensal!$N$6:$N$1098="saldo inicial")+(Aramburu_Mensal!$N$6:$N$1098="pago")+(Aramburu_Mensal!$N$6:$N$1098="Recebido")+(Aramburu_Mensal!$N$6:$N$1098="Aplicação")+(Aramburu_Mensal!$N$6:$N$1098="Resgate")+(Aramburu_Mensal!$N$6:$N$1098="Repassado")+(Aramburu_Mensal!$N$6:$N$1098="Provisionado")+(Aramburu_Mensal!$N$6:$N$1098="Provisionado DV")+(Aramburu_Mensal!$N$6:$N$1098="A pagar")+(Aramburu_Mensal!$N$6:$N$1098="Provisionado DL")+(Aramburu_Mensal!$N$6:$N$1098="A repassar")+(Aramburu_Mensal!$N$6:$N$1098="A aplicar")+(Aramburu_Mensal!$N$6:$N$1098="A receber")+(Aramburu_Mensal!$N$6:$N$1098="A resgatar")+(Aramburu_Mensal!$N$6:$N$1098="Aplicado")+(Aramburu_Mensal!$N$6:$N$1098="Resgatado")),Aramburu_Mensal!$O$6:$O$1098),2) -> 336.07 | Z35: =ROUND(X35+SUMPRODUCT((Aramburu_Mensal!$C$6:$C$1098="novembro")*(Aramburu_Mensal!$M$6:$M$1098="Cooperativa Sicredi (0913)")*((Aramburu_Mensal!$N$6:$N$1098="saldo inicial")+(Aramburu_Mensal!$N$6:$N$1098="pago")+(Aramburu_Mensal!$N$6:$N$1098="Recebido")+(Aramburu_Mensal!$N$6:$N$1098="Aplicação")+(Aramburu_Mensal!$N$6:$N$1098="Resgate")+(Aramburu_Mensal!$N$6:$N$1098="Repassado")+(Aramburu_Mensal!$N$6:$N$1098="Provisionado")+(Aramburu_Mensal!$N$6:$N$1098="Provisionado DV")+(Aramburu_Mensal!$N$6:$N$1098="A pagar")+(Aramburu_Mensal!$N$6:$N$1098="Provisionado DL")+(Aramburu_Mensal!$N$6:$N$1098="A repassar")+(Aramburu_Mensal!$N$6:$N$1098="A aplicar")+(Aramburu_Mensal!$N$6:$N$1098="A receber")+(Aramburu_Mensal!$N$6:$N$1098="A resgatar")+(Aramburu_Mensal!$N$6:$N$1098="Aplicado")+(Aramburu_Mensal!$N$6:$N$1098="Resgatado")),Aramburu_Mensal!$O$6:$O$1098),2) -> 167.07 | AB35: =ROUND(Z35+SUMPRODUCT((Aramburu_Mensal!$C$6:$C$1098="dezembro")*(Aramburu_Mensal!$M$6:$M$1098="Cooperativa Sicredi (0913)")*((Aramburu_Mensal!$N$6:$N$1098="saldo inicial")+(Aramburu_Mensal!$N$6:$N$1098="pago")+(Aramburu_Mensal!$N$6:$N$1098="Recebido")+(Aramburu_Mensal!$N$6:$N$1098="Aplicação")+(Aramburu_Mensal!$N$6:$N$1098="Resgate")+(Aramburu_Mensal!$N$6:$N$1098="Repassado")+(Aramburu_Mensal!$N$6:$N$1098="Provisionado")+(Aramburu_Mensal!$N$6:$N$1098="Provisionado DV")+(Aramburu_Mensal!$N$6:$N$1098="A pagar")+(Aramburu_Mensal!$N$6:$N$1098="Provisionado DL")+(Aramburu_Mensal!$N$6:$N$1098="A repassar")+(Aramburu_Mensal!$N$6:$N$1098="A aplicar")+(Aramburu_Mensal!$N$6:$N$1098="A receber")+(Aramburu_Mensal!$N$6:$N$1098="A resgatar")+(Aramburu_Mensal!$N$6:$N$1098="Aplicado")+(Aramburu_Mensal!$N$6:$N$1098="Resgatado")),Aramburu_Mensal!$O$6:$O$1098),2) -> -1.93 | AD35: =AB37-AD31 -> -2.0372681e-09
AH36: PROVISIONAMENTO 2027
D37: SALDO (-) CONTAS DO PRÓXIMO MÊS: | F37: =SUM(F33:F35)+H26+H25+H24 -> 967387.49 | H37: =SUM(H33:H35)+J26+J25+J24 -> 483179.15 | J37: =SUM(J33:J35)+L26+L25+L24 -> 1326193.4 | L37: =SUM(L33:L35)+N26+N25+N24 -> 1053576.9 | N37: =SUM(N33:N35)+P26+P25+P24 -> 918316.23 | P37: =SUM(P33:P35)+R26+R25+R24 -> 758402.78 | R37: =SUM(R33:R35)+T26+T25+T24 -> 997724.43 | T37: =SUM(T33:T35)+V26+V25+V24 -> 708776.37 | V37: =SUM(V33:V35)+X26+X25+X24 -> 479363.17 | X37: =SUM(X33:X35)+Z26+Z25+Z24 -> 309040.74 | Z37: =SUM(Z33:Z35)+AB26+AB25+AB24 -> 124705.34 | AB37: =SUM(AB33:AB35) -> 124705.34
AH38: 0 | AI38: Movimentações de Saídas | Janeiro
AH39: =AH20+AH38 -> 124705.34 | AI39: Saldo Final de Janeiro | 2027
D41: DESPESA VARIÁVEL
D42: LIMITE MÊS: | F42: 20000 | H42: =20000 -> 20000 | J42: 20000 | L42: 20000 | N42: 20000 | P42: 20000 | R42: 20000 | T42: 20000 | V42: 20000 | X42: 20000 | Z42: 20000 | AB42: 20000 | AD42: 840000 | AH42: 0 | AI42: Movimentações de Despesas | 2027
D43: UTILIZADO: | F43: =-1*(SUMPRODUCT((Aramburu_Mensal!$C$6:$C$1100="janeiro")*(Aramburu_Mensal!$F$6:$F$1100="Despesas Variáveis")*((Aramburu_Mensal!$N$6:$N$1100="A pagar")+(Aramburu_Mensal!$N$6:$N$1100="Pago"))*(Aramburu_Mensal!$O$6:$O$1100))) -> 8697.01 | H43: =-1*(SUMPRODUCT((Aramburu_Mensal!$C$6:$C$1100="fevereiro")*(Aramburu_Mensal!$F$6:$F$1100="Despesas Variáveis")*((Aramburu_Mensal!$N$6:$N$1100="A pagar")+(Aramburu_Mensal!$N$6:$N$1100="Pago"))*(Aramburu_Mensal!$O$6:$O$1100))) -> 11916.92 | J43: =-1*(SUMPRODUCT((Aramburu_Mensal!$C$6:$C$1100="março")*(Aramburu_Mensal!$F$6:$F$1100="Despesas Variáveis")*((Aramburu_Mensal!$N$6:$N$1100="A pagar")+(Aramburu_Mensal!$N$6:$N$1100="Pago"))*(Aramburu_Mensal!$O$6:$O$1100))) -> 25511.19 | L43: =-1*(SUMPRODUCT((Aramburu_Mensal!$C$6:$C$1100="abril")*(Aramburu_Mensal!$F$6:$F$1100="Despesas Variáveis")*((Aramburu_Mensal!$N$6:$N$1100="A pagar")+(Aramburu_Mensal!$N$6:$N$1100="Pago"))*(Aramburu_Mensal!$O$6:$O$1100))) -> 30614.41 | N43: =-1*(SUMPRODUCT((Aramburu_Mensal!$C$6:$C$1100="maio")*(Aramburu_Mensal!$F$6:$F$1100="Despesas Variáveis")*((Aramburu_Mensal!$N$6:$N$1100="A pagar")+(Aramburu_Mensal!$N$6:$N$1100="Pago"))*(Aramburu_Mensal!$O$6:$O$1100))) -> 1980.35 | P43: =-1*(SUMPRODUCT((Aramburu_Mensal!$C$6:$C$1100="junho")*(Aramburu_Mensal!$F$6:$F$1100="Despesas Variáveis")*((Aramburu_Mensal!$N$6:$N$1100="A pagar")+(Aramburu_Mensal!$N$6:$N$1100="Pago"))*(Aramburu_Mensal!$O$6:$O$1100))) -> 0 | R43: =-1*(SUMPRODUCT((Aramburu_Mensal!$C$6:$C$1100="julho")*(Aramburu_Mensal!$F$6:$F$1100="Despesas Variáveis")*((Aramburu_Mensal!$N$6:$N$1100="A pagar")+(Aramburu_Mensal!$N$6:$N$1100="Pago"))*(Aramburu_Mensal!$O$6:$O$1100))) -> 0 | T43: =-1*(SUMPRODUCT((Aramburu_Mensal!$C$6:$C$1100="agosto")*(Aramburu_Mensal!$F$6:$F$1100="Despesas Variáveis")*((Aramburu_Mensal!$N$6:$N$1100="A pagar")+(Aramburu_Mensal!$N$6:$N$1100="Pago"))*(Aramburu_Mensal!$O$6:$O$1100))) -> 0 | V43: =-1*(SUMPRODUCT((Aramburu_Mensal!$C$6:$C$1100="setembro")*(Aramburu_Mensal!$F$6:$F$1100="Despesas Variáveis")*((Aramburu_Mensal!$N$6:$N$1100="A pagar")+(Aramburu_Mensal!$N$6:$N$1100="Pago"))*(Aramburu_Mensal!$O$6:$O$1100))) -> 0 | X43: =-1*(SUMPRODUCT((Aramburu_Mensal!$C$6:$C$1100="outubro")*(Aramburu_Mensal!$F$6:$F$1100="Despesas Variáveis")*((Aramburu_Mensal!$N$6:$N$1100="A pagar")+(Aramburu_Mensal!$N$6:$N$1100="Pago"))*(Aramburu_Mensal!$O$6:$O$1100))) -> 0 | Z43: =-1*(SUMPRODUCT((Aramburu_Mensal!$C$6:$C$1100="novembro")*(Aramburu_Mensal!$F$6:$F$1100="Despesas Variáveis")*((Aramburu_Mensal!$N$6:$N$1100="A pagar")+(Aramburu_Mensal!$N$6:$N$1100="Pago"))*(Aramburu_Mensal!$O$6:$O$1100))) -> 0 | AB43: =-1*(SUMPRODUCT((Aramburu_Mensal!$C$6:$C$1100="dezembro")*(Aramburu_Mensal!$F$6:$F$1100="Despesas Variáveis")*((Aramburu_Mensal!$N$6:$N$1100="A pagar")+(Aramburu_Mensal!$N$6:$N$1100="Pago"))*(Aramburu_Mensal!$O$6:$O$1100))) -> 0 | AD43: =SUM(F43:AB43) -> 78719.88 | AH43: 0 | AI43: Movimentações de Vendas | 2027
D44: PROVISIONADO: | F44: =-1*(SUMPRODUCT((Aramburu_Mensal!$C$6:$C$1100="janeiro")*(Aramburu_Mensal!$F$6:$F$1100="Despesas Variáveis")*(Aramburu_Mensal!$N$6:$N$1100="Provisionado")*(Aramburu_Mensal!$O$6:$O$1100))) -> 0 | H44: =-1*(SUMPRODUCT((Aramburu_Mensal!$C$6:$C$1100="fevereiro")*(Aramburu_Mensal!$F$6:$F$1100="Despesas Variáveis")*(Aramburu_Mensal!$N$6:$N$1100="Provisionado")*(Aramburu_Mensal!$O$6:$O$1100))) -> 0 | J44: =-1*(SUMPRODUCT((Aramburu_Mensal!$C$6:$C$1100="março")*(Aramburu_Mensal!$F$6:$F$1100="Despesas Variáveis")*(Aramburu_Mensal!$N$6:$N$1100="Provisionado")*(Aramburu_Mensal!$O$6:$O$1100))) -> 0 | L44: =-1*(SUMPRODUCT((Aramburu_Mensal!$C$6:$C$1100="abril")*(Aramburu_Mensal!$F$6:$F$1100="Despesas Variáveis")*(Aramburu_Mensal!$N$6:$N$1100="Provisionado")*(Aramburu_Mensal!$O$6:$O$1100))) -> 0 | N44: =-1*(SUMPRODUCT((Aramburu_Mensal!$C$6:$C$1100="maio")*(Aramburu_Mensal!$F$6:$F$1100="Despesas Variáveis")*(Aramburu_Mensal!$N$6:$N$1100="Provisionado")*(Aramburu_Mensal!$O$6:$O$1100))) -> 14351.15 | P44: =-1*(SUMPRODUCT((Aramburu_Mensal!$C$6:$C$1100="junho")*(Aramburu_Mensal!$F$6:$F$1100="Despesas Variáveis")*(Aramburu_Mensal!$N$6:$N$1100="Provisionado")*(Aramburu_Mensal!$O$6:$O$1100))) -> 3071.15 | R44: =-1*(SUMPRODUCT((Aramburu_Mensal!$C$6:$C$1100="julho")*(Aramburu_Mensal!$F$6:$F$1100="Despesas Variáveis")*(Aramburu_Mensal!$N$6:$N$1100="Provisionado")*(Aramburu_Mensal!$O$6:$O$1100))) -> 3685.35 | T44: =-1*(SUMPRODUCT((Aramburu_Mensal!$C$6:$C$1100="agosto")*(Aramburu_Mensal!$F$6:$F$1100="Despesas Variáveis")*(Aramburu_Mensal!$N$6:$N$1100="Provisionado")*(Aramburu_Mensal!$O$6:$O$1100))) -> 3839.15 | V44: =-1*(SUMPRODUCT((Aramburu_Mensal!$C$6:$C$1100="agosto")*(Aramburu_Mensal!$F$6:$F$1100="Despesas Variáveis")*(Aramburu_Mensal!$N$6:$N$1100="Provisionado")*(Aramburu_Mensal!$O$6:$O$1100))) -> 3839.15 | X44: =-1*(SUMPRODUCT((Aramburu_Mensal!$C$6:$C$1100="outubro")*(Aramburu_Mensal!$F$6:$F$1100="Despesas Variáveis")*(Aramburu_Mensal!$N$6:$N$1100="Provisionado")*(Aramburu_Mensal!$O$6:$O$1100))) -> 13561.15 | Z44: =-1*(SUMPRODUCT((Aramburu_Mensal!$C$6:$C$1100="novembro")*(Aramburu_Mensal!$F$6:$F$1100="Despesas Variáveis")*(Aramburu_Mensal!$N$6:$N$1100="Provisionado")*(Aramburu_Mensal!$O$6:$O$1100))) -> 3561.15 | AB44: =-1*(SUMPRODUCT((Aramburu_Mensal!$C$6:$C$1100="dezembro")*(Aramburu_Mensal!$F$6:$F$1100="Despesas Variáveis")*(Aramburu_Mensal!$N$6:$N$1100="Provisionado")*(Aramburu_Mensal!$O$6:$O$1100))) -> 7561.15 | AH44: =SUM(AH42:AH43) -> 0 | AI44: Saldo Final em Conta | 2027
D45: SALDO: | F45: =F42-F43 -> 11302.99 | H45: =H42-H43-H44 -> 8083.08 | J45: =J42-J43-J44 -> -5511.19 | L45: =L42-L43-L44 -> -10614.41 | N45: =N42-N43-N44 -> 3668.5 | P45: =P42-P43-P44 -> 16928.85 | R45: =R42-R43-R44 -> 16314.65 | T45: =T42-T43-T44 -> 16160.85 | V45: =V42-V43-V44 -> 16160.85 | X45: =X42-X43-X44 -> 6438.85 | Z45: =Z42-Z43-Z44 -> 16438.85 | AB45: =AB42-AB43-AB44 -> 12438.85 | AD45: =AD42-AD43 -> 761280.12

Sheet __
B10: Conta Bancária | C10: (Vários itens)
B11: Status | C11: (Tudo)
B12: Tipo de Despesa | C12: (Tudo)
B13: Forma de Pgto | C13: (Tudo)
B14: Obs. Obra | C14: (Tudo)
B15: Ref. | C15: (Tudo)
B17: Soma de Valor | C17: Rótulos de Coluna
B18: Rótulos de Linha | C18: Abril | D18: Maio | E18: Junho | F18: Julho | G18: Agosto | H18: Setembro | I18: Outubro | J18: Novembro | K18: Dezembro | L18: Total Geral
B19: 1.8.1 – Cooperativa Sicredi | C19: 86068.75 | D19: 129266.79 | E19: 20446.87 | F19: 15098.94 | G19: 6060.12 | H19: 6060.12 | I19: 5913.37 | J19: 2288.37 | K19: 0 | L19: 271203.33
B20: Banco Cooperativa Sicredi | C20: 86068.75 | D20: 129266.79 | E20: 20446.87 | F20: 15098.94 | G20: 6060.12 | H20: 6060.12 | I20: 5913.37 | J20: 2288.37 | K20: 0 | L20: 271203.33
B21: 2.7.2 – Obras e Melhorias (infraestrutura) | C21: -86056.25 | D21: -129266.79 | E21: -20446.86 | F21: -15098.94 | G21: -6060.12 | H21: -6060.12 | I21: -5913.37 | J21: -2288.37 | L21: -271190.82
B22: Apoio Refrigeração - Nei Gochs | D22: -2000 | L22: -2000
B23: Bica D'agua Mat De Const Ltda | C23: -66.33 | D23: -4194.99 | L23: -4261.32
B24: Chama Azul Com. Utilidades Domésticas | D24: -2695 | L24: -2695
B25: Comercial Elétrica Dourados Ltda | C25: -3740 | D25: -4450.89 | L25: -8190.89
B26: Edson dos Santos Ortega | D26: -1400 | L26: -1400
B27: Enan Comércio de Gás Ltda - Copagaz Mju | C27: -258 | D27: -270 | L27: -528
B28: F. Carlos da Silva - Madeireira Maracaju | C28: -2725 | D28: -6350 | E28: -6350 | F28: -3625 | G28: -3625 | H28: -3625 | I28: -3625 | L28: -29925
B29: Ferragem Alvorada Ltda | C29: -3242 | L29: -3242
B30: Ferragens Alvorada Ltda | D30: -905 | E30: -600.99 | F30: -600.99 | L30: -2106.98
B31: Gabriel Fernandes Zarate - Renato Pintor | C31: -12000 | D31: -33000 | L31: -45000 | M31: 23797.51
B32: Gilson Freitas de Souza ME | C32: -481.5 | D32: -481.5 | L32: -963
B33: Graciele Gonçalves Tolentino - Marmoaria Fênix | C33: -2288.41 | D33: -2288.37 | E33: -2288.37 | F33: -2288.37 | G33: -2288.37 | H33: -2288.37 | I33: -2288.37 | J33: -2288.37 | L33: -18307
B34: J & E Vidrobox Alumínios Ltda | C34: -4900 | D34: -29500 | L34: -34400
B35: Jchagas Alimentos Ltda - Fogo Atacadista | C35: -1545.65 | D35: -1209.46 | L35: -2755.11
B36: JV Tubos e Acabamentos Ltda | D36: -3495.16 | E36: -3187.33 | F36: -3187.33 | L36: -9869.82
B37: LTS Engenharia Sistemas Construtivos Ltda | D37: -8622.43 | L37: -8622.43
B38: Magazine Luiza S/A | D38: -1050.5 | E38: -1050.5 | F38: -1050.5 | L38: -3151.5
B39: MPS Distr. Mercantil - Apoio Refrigeração | C39: -2511.41 | D39: -2511.41 | E39: -2511.41 | L39: -7534.23
B40: Odílio Duarte Fretes | C40: -24822.2 | L40: -24822.2
B41: Ping Tecnologia e Segurança Ltda | C41: -1059.22 | D41: -1059.22 | E41: -1059.21 | L41: -3177.65
B42: Pracasa Utilidades e Aceessórios Ltda | C42: -47.6 | L42: -47.6
B43: R. B. Ramalho Serviços em Gesso Ltda | C43: -1301.37 | D43: -1301.37 | L43: -2602.74
B44: Receita Federal | C44: -1900.1 | D44: -7364.44 | E44: -2400 | F44: -4200 | L44: -15864.54
B45: Refrigeração Amaral | C45: -1918 | D45: -1918 | L45: -3836
B46: Restaurante Santa Brasa Ltda | C46: -78 | L46: -78
B47: RRX Com. De Carnes Eireli | C47: -1040.79 | L47: -1040.79 | P47: =SUMPRODUCT((Aramburu_Mensal!$C$6:$C$1098="novembro")*((Aramburu_Mensal!$N$6:$N$1098="provisionado")+(Aramburu_Mensal!$N$6:$N$1098="a pagar")+(Aramburu_Mensal!$N$6:$N$1098="Pago")+(Aramburu_Mensal!$N$6:$N$1098="Provisionado DV"))*(Aramburu_Mensal!$O$6:$O$1098))-P50 -> -50609.3 | R47: =SUMPRODUCT((Aramburu_Mensal!$C$6:$C$1098="dezembro")*((Aramburu_Mensal!$N$6:$N$1098="provisionado")+(Aramburu_Mensal!$N$6:$N$1098="a pagar")+(Aramburu_Mensal!$N$6:$N$1098="Pago")+(Aramburu_Mensal!$N$6:$N$1098="Provisionado DV"))*(Aramburu_Mensal!$O$6:$O$1098))-R50 -> -49648.47 | S47: =SUMPRODUCT((Aramburu_Mensal!$C$6:$C$1098="setembro")*((Aramburu_Mensal!$N$6:$N$1098="provisionado")+(Aramburu_Mensal!$N$6:$N$1098="a pagar")+(Aramburu_Mensal!$N$6:$N$1098="Pago")+(Aramburu_Mensal!$N$6:$N$1098="Provisionado DV"))*(Aramburu_Mensal!$O$6:$O$1098))-S50 -> -173937.05
B48: Smart Center Comércio de Materiais de Construção Ltda | C48: -5194.1 | L48: -5194.1
B49: Todimo Construção e Acabamento | C49: -146.77 | D49: -146.75 | E49: -146.75 | F49: -146.75 | G49: -146.75 | H49: -146.75 | L49: -880.52
B50: Tom Mudas Ltda | C50: -1737.5 | L50: -1737.5
B51: Total Tintas Comércio de Tintas e Materiais | C51: -12200 | D51: -12200 | L51: -24400
B52: VACV Tecnologia Ltda - Ping Tecnologia | C52: -852.3 | D52: -852.3 | E52: -852.3 | L52: -2556.9
B53: Total Geral | C53: 12.5 | D53: 4.7748472e-12 | E53: 0.01 | F53: 1.8189894e-12 | G53: 0 | H53: 0 | I53: 0 | J53: 0 | K53: 0 | L53: 12.51

Sheet Aramburu_Mensal
B3: AGROPECUÁRIA ARAMBURU
B5: Dia | C5: Mês | D5: Conta Contábil | E5: Centro de Custo | F5: Tipo de Despesa | G5: Fornecedor | H5: Descrição | I5: Obs. Obra | J5: Ref. | K5: Parcelas | L5: Forma de Pgto | M5: Conta Bancária | N5: Status | O5: Valor
B6: 46024 | C6: =PROPER(TEXT(B6,"MMMM")) -> Janeiro | D6: 1.1 – Saldo Inicial | E6: 1.1.1 – Banco Cora | F6: - | G6: Banco Cora | H6: Saldo Inical do Resultado do Exercício de 2025 | I6: - | J6: - | K6: - | L6: - | M6: Banco Cora (0001) | N6: Saldo inicial | O6: 383184.43
B7: 46024 | C7: =PROPER(TEXT(B7,"MMMM")) -> Janeiro | D7: 2.2 – Despesas com Pessoal | E7: 2.2.3 – Benefícios (vale, alimentação, etc.) | F7: Despesas Fixas | G7: Pluxee Benefícios Brasil S.A. | H7: Pluxee Multibenefícios - Administrativo | I7: - | J7: NF 211497 | K7: - | L7: Boleto | M7: Banco Cora (0001) | N7: Pago | O7: -700
B8: 46024 | C8: =PROPER(TEXT(B8,"MMMM")) -> Janeiro | D8: 2.3 – Operação da Propriedade | E8: 2.3.6 – Produtos e Peças | F8: Despesas Variáveis | G8: Agro Amizade Com. De Produtos Veterinário Ltda | H8: Diversos | I8: - | J8: NF 716 | K8: - | L8: Pix | M8: Banco Cora (0001) | N8: Pago | O8: -150
B9: 46024 | C9: =PROPER(TEXT(B9,"MMMM")) -> Janeiro | D9: 2.8 – Distribuição de Lucro / Saídas Pessoais | E9: 2.8.1 – Distribuição de Lucros | F9: - | G9: Aramburu Participações Ltda | H9: Banco Inter - Distribuição de Lucro | I9: - | J9: Jan/2026 | K9: - | L9: Pix | M9: Banco Cora (0001) | N9: Repassado | O9: -62680.13
B10: 46024 | C10: =PROPER(TEXT(B10,"MMMM")) -> Janeiro | D10: 2.6 – Investimentos em Capital | E10: 2.6.1 – Aplicações Financeiras | F10: - | G10: Agropecuária Aramburu Ltda | H10: Reserva p/ Conta XP (Taxa armazenagem_Safrinha Milho 25/25) | I10: - | J10: - | K10: - | L10: Pix | M10: Banco Cora (0001) | N10: Aplicado | O10: -100000
B11: 46024 | C11: =PROPER(TEXT(B11,"MMMM")) -> Janeiro | D11: 2.9 – Outras Saídas | E11: 2.9.3 – Outras Despesas Não Classificadas | F11: - | G11: Agropecuária Aramburu Ltda | H11: Transferência Entre Contas - Pgto das Tarifas Bancárias | I11: - | J11: 2026 | K11: - | L11: Transferência | M11: Banco Cora (0001) | N11: Pago | O11: -1878
B12: 46024 | C12: =PROPER(TEXT(B12,"MMMM")) -> Janeiro | D12: 1.8 – Resgate de Aplicações | E12: 1.8.1 – Cooperativa Sicredi | F12: - | G12: Banco Cooperativa Sicredi | H12: Resgate da Conta Investimento Invest - Pgto das Tarifas Bancárias | I12: - | J12: 2026 | K12: - | L12: - | M12: Cooperativa Sicredi (0902) | N12: Resgatado | O12: 900
B13: 46024 | C13: =PROPER(TEXT(B13,"MMMM")) -> Janeiro | D13: 1.8 – Resgate de Aplicações | E13: 1.8.1 – Cooperativa Sicredi | F13: - | G13: Banco Cooperativa Sicredi | H13: Resgate da Conta Investimento Invest Evolutivo - Reserva p/ Construção da Sede | I13: - | J13: - | K13: - | L13: - | M13: Cooperativa Sicredi (0902) | N13: Resgatado | O13: 3700
B14: 46024 | C14: =PROPER(TEXT(B14,"MMMM")) -> Janeiro | D14: 1.1 – Saldo Inicial | E14: 1.1.2 – Cooperativa Sicredi | F14: - | G14: Banco Cooperativa Sicredi | H14: Saldo Inical do Resultado do Exercício de 2025 | I14: - | J14: - | K14: - | L14: - | M14: Cooperativa Sicredi (0902) | N14: Saldo inicial | O14: 51.15
B15: 46024 | C15: =PROPER(TEXT(B15,"MMMM")) -> Janeiro | D15: 1.1 – Saldo Inicial | E15: 1.1.2 – Cooperativa Sicredi | F15: - | G15: Banco Cooperativa Sicredi | H15: Saldo Inical do Resultado do Exercício de 2025 | I15: - | J15: - | K15: - | L15: - | M15: Cooperativa Sicredi (0913) | N15: Saldo inicial | O15: 100
B16: 46024 | C16: =PROPER(TEXT(B16,"MMMM")) -> Janeiro | D16: 1.8 – Resgate de Aplicações | E16: 1.8.1 – Cooperativa Sicredi | F16: - | G16: Banco Cooperativa Sicredi | H16: Resgate da Conta Investimento Invest - Reserva p/ Construção da Sede | I16: - | J16: - | K16: - | L16: - | M16: Cooperativa Sicredi (0913) | N16: Resgatado | O16: 12732.35
B17: 46024 | C17: =PROPER(TEXT(B17,"MMMM")) -> Janeiro | D17: 2.5 – Financeiras e Bancárias | E17: 2.5.1 – Juros Bancários | F17: Despesas Variáveis | G17: Banco Cooperativa Sicredi | H17: IOF Basico CH PJ | I17: - | J17: - | K17: - | L17: Débito Automático | M17: Cooperativa Sicredi (0913) | N17: Pago | O17: -0.03
B18: 46024 | C18: =PROPER(TEXT(B18,"MMMM")) -> Janeiro | D18: 2.5 – Financeiras e Bancárias | E18: 2.5.1 – Juros Bancários | F18: Despesas Variáveis | G18: Banco Cooperativa Sicredi | H18: IOF Adicional PJ CH Especial | I18: - | J18: - | K18: - | L18: Débito Automático | M18: Cooperativa Sicredi (0913) | N18: Pago | O18: -0.21
B19: 46024 | C19: =PROPER(TEXT(B19,"MMMM")) -> Janeiro | D19: 2.5 – Financeiras e Bancárias | E19: 2.5.1 – Juros Bancários | F19: Despesas Variáveis | G19: Banco Cooperativa Sicredi | H19: Juros Utiliz. CH Especial | I19: - | J19: - | K19: - | L19: Débito Automático | M19: Cooperativa Sicredi (0913) | N19: Pago | O19: -1.68
B20: 46024 | C20: =PROPER(TEXT(B20,"MMMM")) -> Janeiro | D20: 2.5 – Financeiras e Bancárias | E20: 2.5.2 – Tarifas Bancárias | F20: Despesas Fixas | G20: Banco Cooperativa Sicredi | H20: Integralização de Capital Subscrito | I20: - | J20: Jan/2026 | K20: - | L20: Débito Automático | M20: Cooperativa Sicredi (0913) | N20: Pago | O20: -100
B21: 46024 | C21: =PROPER(TEXT(B21,"MMMM")) -> Janeiro | D21: 1.9 – Outros Recebimentos | E21: 1.9.1 – Diversos | F21: - | G21: Agropecuária Aramburu Ltda | H21: Transferência Entre Contas - Pgto das Tarifas Bancárias | I21: - | J21: - | K21: - | L21: Transferência | M21: Cooperativa Sicredi (0913) | N21: Recebido | O21: 1878
B22: 46027 | C22: =PROPER(TEXT(B22,"MMMM")) -> Janeiro | D22: 2.1 – Despesas Administrativas | E22: 2.1.1 – Honorários Contábeis | F22: Despesas Fixas | G22: Oeste Paulista Contabilidade | H22: Contabilidade | I22: - | J22: NF 27980 | K22: - | L22: Boleto | M22: Banco Cora (0001) | N22: Pago | O22: -4574
B23: 46027 | C23: =PROPER(TEXT(B23,"MMMM")) -> Janeiro | D23: 2.4 – Serviços Terceirizados | E23: 2.4.7 – Serviços Diversos | F23: Despesas Variáveis | G23: Rasat Soluções Inteligentes Ltda | H23: Rastreamento Veicular - Caminhonete L200 | I23: - | J23: NF 32 | K23: - | L23: Boleto | M23: Banco Cora (0001) | N23: Pago | O23: -70
B24: 46027 | C24: =PROPER(TEXT(B24,"MMMM")) -> Janeiro | D24: 2.3 – Operação da Propriedade | E24: 2.3.6 – Produtos e Peças | F24: Despesas Variáveis | G24: Soldamaq Comércio de Ferramentas Ltda - CG | H24: Pá Coração + Cadeados + Regador de Jardim | I24: - | J24: NF 175894 | K24: - | L24: Boleto | M24: Banco Cora (0001) | N24: Pago | O24: -258.29
... B42: 46030 | C42: =PROPER(TEXT(B42,"MMMM")) -> Janeiro | D42: 2.5 – Financeiras e Bancárias | E42: 2.5.2 – Tarifas Bancárias | F42: Despesas Fixas | G42: Banco Cooperativa Sicredi | H42: Deb.Cta. Fatura | I42: - | J42: Jan/2026 | K42: - | L42: Débito Automático | M42: Cooperativa Sicredi (0902) | N42: Pago | O42: -10
B43: 46030 | C43: =PROPER(TEXT(B43,"MMMM")) -> Janeiro | D43: 1.8 – Resgate de Aplicações | E43: 1.8.1 – Cooperativa Sicredi | F43: - | G43: Banco Cooperativa Sicredi | H43: Resgate da Conta Investimento Invest - Reserva p/ Construção da Sede | I43: - | J43: - | K43: - | L43: - | M43: Cooperativa Sicredi (0913) | N43: Resgatado | O43: =7593.33+1166.77 -> 8760.1
B44: 46030 | C44: =PROPER(TEXT(B44,"MMMM")) -> Janeiro | D44: 2.7 – Investimentos em Imobilizado Operacional | E44: 2.7.2 – Obras e Melhorias (infraestrutura) | F44: Despesas Eventuais | G44: RRX Com. De Carnes Eireli | H44: Construção da Sede - Produtos alimentícios refeição funcionários LTS | I44: OUTRAS | J44: NF 12873 | K44: - | L44: Pix | M44: Cooperativa Sicredi (0913) | N44: Pago | O44: -1166.77
B45: 46031 | C45: =PROPER(TEXT(B45,"MMMM")) -> Janeiro | D45: 2.3 – Operação da Propriedade | E45: 2.3.6 – Produtos e Peças | F45: Despesas Variáveis | G45: Bica D'agua Mat De Const Ltda | H45: Tampa da Caixa D'Agua Fortlev 10 mil litros | I45: - | J45: NF 277091 | K45: 2/2 | L45: Boleto | M45: Banco Cora (0001) | N45: Pago | O45: -1695
B46: 46031 | C46: =PROPER(TEXT(B46,"MMMM")) -> Janeiro | D46: 2.7 – Investimentos em Imobilizado Operacional | E46: 2.7.2 – Obras e Melhorias (infraestrutura) | F46: Despesas Eventuais | G46: Prefeitura Municipal de Maracaju | H46: Construção da Sede_Projeto_Contrato - Execução (ISS) | I46: MEDIÇÃO 04 | J46: NF 258 | K46: - | L46: Guia | M46: Banco Cora (0001) | N46: Pago | O46: -5952.38
B47: 46031 | C47: =PROPER(TEXT(B47,"MMMM")) -> Janeiro | D47: 2.7 – Investimentos em Imobilizado Operacional | E47: 2.7.2 – Obras e Melhorias (infraestrutura) | F47: Despesas Eventuais | G47: Prefeitura Municipal de Maracaju | H47: Construção da Sede_Projeto_Contrato - Execução (ISS) | I47: OUTRAS | J47: NF 1000991 | K47: - | L47: Guia | M47: Banco Cora (0001) | N47: Pago | O47: =-85.63-7.57 -> -93.2
B48: 46031 | C48: =PROPER(TEXT(B48,"MMMM")) -> Janeiro | D48: 2.7 – Investimentos em Imobilizado Operacional | E48: 2.7.2 – Obras e Melhorias (infraestrutura) | F48: Despesas Eventuais | G48: Prefeitura Municipal de Maracaju | H48: Construção da Sede_Projeto_Contrato - Execução (ISS) | I48: MEDIÇÃO 05 | J48: NF 262 | K48: - | L48: Guia | M48: Banco Cora (0001) | N48: Pago | O48: -1555.32
B49: 46031 | C49: =PROPER(TEXT(B49,"MMMM")) -> Janeiro | D49: 1.8 – Resgate de Aplicações | E49: 1.8.1 – Cooperativa Sicredi | F49: - | G49: Banco Cooperativa Sicredi | H49: Resgate da Conta Investimento Invest Evolutivo - Reserva p/ Construção da Sede | I49: - | J49: - | K49: - | L49: - | M49: Cooperativa Sicredi (0902) | N49: Resgatado | O49: 9800
B50: 46031 | C50: =PROPER(TEXT(B50,"MMMM")) -> Janeiro | D50: 1.8 – Resgate de Aplicações | E50: 1.8.1 – Cooperativa Sicredi | F50: - | G50: Banco Cooperativa Sicredi | H50: Resgate da Conta Investimento Invest - Reserva p/ Construção da Sede | I50: - | J50: - | K50: - | L50: - | M50: Cooperativa Sicredi (0913) | N50: Resgatado | O50: 129
B51: 46031 | C51: =PROPER(TEXT(B51,"MMMM")) -> Janeiro | D51: 2.7 – Investimentos em Imobilizado Operacional | E51: 2.7.2 – Obras e Melhorias (infraestrutura) | F51: Despesas Eventuais | G51: Douratubos Acessórios Industriais Ltda | H51: Construção da Sede - Instalações hidrossanitárias | I51: OUTRAS | J51: NF 358792 | K51: 1/3 | L51: Boleto | M51: Cooperativa Sicredi (0913) | N51: Pago | O51: -391.66
B52: 46031 | C52: =PROPER(TEXT(B52,"MMMM")) -> Janeiro | D52: 1.9 – Outros Recebimentos | E52: 1.9.1 – Diversos | F52: - | G52: Agropecuária Aramburu Ltda | H52: Transf. Entre Contas_Resgate Investimento XP - Extra Emergencial p/ Construção da Sede | I52: - | J52: - | K52: - | L52: Transferência | M52: Cooperativa Sicredi (0913) | N52: Recebido | O52: 100488.96
B53: 46031 | C53: =PROPER(TEXT(B53,"MMMM")) -> Janeiro | D53: 2.6 – Investimentos em Capital | E53: 2.6.1 – Aplicações Financeiras | F53: - | G53: Agropecuária Aramburu Ltda | H53: Aplicação Financeira - Extra Emergencial p/ Construção da Sede | I53: - | J53: - | K53: - | L53: Transferência | M53: Cooperativa Sicredi (0913) | N53: Aplicado | O53: -100488.96
B54: 46032 | C54: =PROPER(TEXT(B54,"MMMM")) -> Janeiro | D54: 2.1 – Despesas Administrativas | E54: 2.1.3 – Despesas com Aluguel | F54: Despesas Fixas | G54: Atmosphera Saúde Esportes e R. Ltda | H54: Aluguel de Sala Atmosphera | I54: - | J54: Recibo 020/2026 | K54: - | L54: Pix | M54: Banco Cora (0001) | N54: Pago | O54: -1974
B55: 46033 | C55: =PROPER(TEXT(B55,"MMMM")) -> Janeiro | D55: 2.7 – Investimentos em Imobilizado Operacional | E55: 2.7.2 – Obras e Melhorias (infraestrutura) | F55: Despesas Eventuais | G55: Bica D'agua Mat De Const Ltda | H55: Construção da Sede - Instalações hidrossanitárias | I55: OUTRAS | J55: NF 280640 | K55: - | L55: Pix | M55: Cooperativa Sicredi (0913) | N55: Pago | O55: -55.7
B56: 46034 | C56: =PROPER(TEXT(B56,"MMMM")) -> Janeiro | D56: 2.7 – Investimentos em Imobilizado Operacional | E56: 2.7.2 – Obras e Melhorias (infraestrutura) | F56: Despesas Eventuais | G56: Eliete Duarte Taglialenha - Montana Móveis | H56: Construção da Sede - Móveis Planejados | I56: OUTRAS | J56: NF 6 | K56: 3/5 | L56: Pix | M56: Cooperativa Sicredi (0902) | N56: Pago | O56: -9800
B57: 46034 | C57: =PROPER(TEXT(B57,"MMMM")) -> Janeiro | D57: 1.8 – Resgate de Aplicações | E57: 1.8.1 – Cooperativa Sicredi | F57: - | G57: Banco Cooperativa Sicredi | H57: Resgate da Conta Investimento Invest - Reserva p/ Construção da Sede | I57: - | J57: - | K57: - | L57: - | M57: Cooperativa Sicredi (0913) | N57: Resgatado | O57: 2109
B58: 46034 | C58: =PROPER(TEXT(B58,"MMMM")) -> Janeiro | D58: 2.7 – Investimentos em Imobilizado Operacional | E58: 2.7.2 – Obras e Melhorias (infraestrutura) | F58: Despesas Eventuais | G58: Enan Comércio de Gás Ltda - Copagaz Mju | H58: Construção da Sede - GLP Botijão 13 kg | I58: OUTRAS | J58: NF 2467 | K58: - | L58: Boleto | M58: Cooperativa Sicredi (0913) | N58: Pago | O58: -129
B59: 46034 | C59: =PROPER(TEXT(B59,"MMMM")) -> Janeiro | D59: 2.5 – Financeiras e Bancárias | E59: 2.5.2 – Tarifas Bancárias | F59: Despesas Fixas | G59: Banco Cooperativa Sicredi | H59: Cesta Relacionamento | I59: - | J59: Jan/2026 | K59: - | L59: Débito Automático | M59: Cooperativa Sicredi (0913) | N59: Pago | O59: -56.5
... B63: 46035 | C63: =PROPER(TEXT(B63,"MMMM")) -> Janeiro | D63: 1.8 – Resgate de Aplicações | E63: 1.8.1 – Cooperativa Sicredi | F63: - | G63: Banco Cooperativa Sicredi | H63: Resgate da Conta Investimento Invest - Reserva p/ Construção da Sede | I63: - | J63: - | K63: - | L63: - | M63: Cooperativa Sicredi (0913) | N63: Resgatado | O63: 442
B64: 46035 | C64: =PROPER(TEXT(B64,"MMMM")) -> Janeiro | D64: 1.8 – Resgate de Aplicações | E64: 1.8.1 – Cooperativa Sicredi | F64: - | G64: Banco Cooperativa Sicredi | H64: Resgate da Conta Investimento Invest - Reserva p/ Construção da Sede | I64: - | J64: - | K64: - | L64: - | M64: Cooperativa Sicredi (0913) | N64: Resgatado | O64: =7037.5+7.57 -> 7045.07
B65: 46035 | C65: =PROPER(TEXT(B65,"MMMM")) -> Janeiro | D65: 2.7 – Investimentos em Imobilizado Operacional | E65: 2.7.2 – Obras e Melhorias (infraestrutura) | F65: Despesas Eventuais | G65: Comercial Elétrica Dourados Ltda | H65: Construção da Sede - Instalações elétricas | I65: OUTRAS | J65: NF 314917 | K65: - | L65: Boleto | M65: Cooperativa Sicredi (0913) | N65: Pago | O65: -382.4
B66: 46035 | C66: =PROPER(TEXT(B66,"MMMM")) -> Janeiro | D66: 2.7 – Investimentos em Imobilizado Operacional | E66: 2.7.2 – Obras e Melhorias (infraestrutura) | F66: Despesas Eventuais | G66: Restaurante Santa Brasa Ltda | H66: Construção da Sede - Refeições aos colaboradores da LTS (9 almoços + 8 jantares) | I66: OUTRAS | J66: NF 69 | K66: - | L66: Pix | M66: Cooperativa Sicredi (0913) | N66: Pago | O66: -442
B67: 46035 | C67: =PROPER(TEXT(B67,"MMMM")) -> Janeiro | D67: 2.7 – Investimentos em Imobilizado Operacional | E67: 2.7.2 – Obras e Melhorias (infraestrutura) | F67: Despesas Eventuais | G67: R. B. Ramalho Serviços em Gesso Ltda | H67: Construção da Sede - Materiais_Molduras de gessoa (portas e janelas) | I67: OUTRAS | J67: NF 180 | K67: 1/5 | L67: Pix | M67: Cooperativa Sicredi (0913) | N67: Pago | O67: -3760
B68: 46035 | C68: =PROPER(TEXT(B68,"MMMM")) -> Janeiro | D68: 2.7 – Investimentos em Imobilizado Operacional | E68: 2.7.2 – Obras e Melhorias (infraestrutura) | F68: Despesas Eventuais | G68: R. B. Ramalho Serviços em Gesso Ltda | H68: Construção da Sede - Mão de Obra_Molduras de gessoa (portas e janelas) | I68: OUTRAS | J68: NF 373 | K68: 1/5 | L68: Pix | M68: Cooperativa Sicredi (0913) | N68: Pago | O68: -1540
B69: 46035 | C69: =PROPER(TEXT(B69,"MMMM")) -> Janeiro | D69: 2.9 – Outras Saídas | E69: 2.9.3 – Outras Despesas Não Classificadas | F69: - | G69: Agropecuária Aramburu Ltda | H69: Transferência Entre Contas | I69: - | J69: - | K69: - | L69: Pix | M69: Cooperativa Sicredi (0913) | N69: Pago | O69: -7600.92
B70: 46036 | C70: =PROPER(TEXT(B70,"MMMM")) -> Janeiro | D70: 1.8 – Resgate de Aplicações | E70: 1.8.1 – Cooperativa Sicredi | F70: - | G70: Banco Cooperativa Sicredi | H70: Resgate da Conta Investimento Invest - Reserva p/ Construção da Sede | I70: - | J70: - | K70: - | L70: - | M70: Cooperativa Sicredi (0913) | N70: Resgatado | O70: 442
B71: 46036 | C71: =PROPER(TEXT(B71,"MMMM")) -> Janeiro | D71: 2.7 – Investimentos em Imobilizado Operacional | E71: 2.7.2 – Obras e Melhorias (infraestrutura) | F71: Despesas Eventuais | G71: Tom Mudas Ltda | H71: Construção da Sede - Mudas p/ paisagismo | I71: OUTRAS | J71: NF 2184 | K71: 1/4 | L71: Boleto | M71: Cooperativa Sicredi (0913) | N71: Pago | O71: -1737.5
B72: 46036 | C72: =PROPER(TEXT(B72,"MMMM")) -> Janeiro | D72: 2.7 – Investimentos em Imobilizado Operacional | E72: 2.7.2 – Obras e Melhorias (infraestrutura) | F72: Despesas Eventuais | G72: Jchagas Alimentos Ltda - Fogo Atacadista | H72: Construção da Sede - Produtos alimentícios refeição funcionários LTS | I72: OUTRAS | J72: NF 17660 | K72: - | L72: Boleto | M72: Cooperativa Sicredi (0913) | N72: Pago | O72: -1642.2
B73: 46036 | C73: =PROPER(TEXT(B73,"MMMM")) -> Janeiro | D73: 2.7 – Investimentos em Imobilizado Operacional | E73: 2.7.2 – Obras e Melhorias (infraestrutura) | F73: Despesas Eventuais | G73: Restaurante Santa Brasa Ltda | H73: Construção da Sede - Refeições aos colaboradores da LTS (9 almoços + 8 jantares) | I73: OUTRAS | J73: NF 72 | K73: - | L73: Pix | M73: Cooperativa Sicredi (0913) | N73: Pago | O73: -442
B74: 46037 | C74: =PROPER(TEXT(B74,"MMMM")) -> Janeiro | D74: 2.3 – Operação da Propriedade | E74: 2.3.6 – Produtos e Peças | F74: Despesas Variáveis | G74: Soldamaq Comércio de Ferramentas Ltda - Mju | H74: Kijacto Policampo 5L + Solupan 5L + Óleo 2T Stihl 500ml | I74: - | J74: NF 16436 | K74: - | L74: Boleto | M74: Banco Cora (0001) | N74: Pago | O74: -248.06
B75: 46037 | C75: =PROPER(TEXT(B75,"MMMM")) -> Janeiro | D75: 2.1 – Despesas Administrativas | E75: 2.1.8 – Despesas Gerais | F75: Despesas Variáveis | G75: Canva Pty Ltda | H75: Assinatura Anual do Canva | I75: - | J75: - | K75: 1/12 | L75: Cartão de Crédito | M75: Banco Cora (0001) | N75: Pago | O75: -24.16
B76: 46037 | C76: =PROPER(TEXT(B76,"MMMM")) -> Janeiro | D76: 2.1 – Despesas Administrativas | E76: 2.1.8 – Despesas Gerais | F76: Despesas Variáveis | G76: Dejneka & Menezes Serviços e Consultoria Ltda | H76: Assinatura Anual do MD Commodities | I76: - | J76: NF 6477 | K76: 10/12 | L76: Cartão de Crédito | M76: Banco Cora (0001) | N76: Pago | O76: -398.91
... B82: 46038 | C82: =PROPER(TEXT(B82,"MMMM")) -> Janeiro | D82: 1.9 – Outros Recebimentos | E82: 1.9.1 – Diversos | F82: - | G82: Agropecuária Aramburu Ltda | H82: Transf. Entre Contas_Resgate Investimento XP - Extra Emergencial p/ Construção da Sede | I82: - | J82: - | K82: - | L82: Transferência | M82: Banco Cora (0001) | N82: Recebido | O82: 200084.84
B83: 46038 | C83: =PROPER(TEXT(B83,"MMMM")) -> Janeiro | D83: 1.8 – Resgate de Aplicações | E83: 1.8.1 – Cooperativa Sicredi | F83: - | G83: Banco Cooperativa Sicredi | H83: Resgate da Conta Investimento Invest - Reserva p/ Construção da Sede | I83: - | J83: - | K83: - | L83: - | M83: Cooperativa Sicredi (0913) | N83: Resgatado | O83: =16516.94+804 -> 17320.94
B84: 46038 | C84: =PROPER(TEXT(B84,"MMMM")) -> Janeiro | D84: 2.7 – Investimentos em Imobilizado Operacional | E84: 2.7.2 – Obras e Melhorias (infraestrutura) | F84: Despesas Eventuais | G84: Bica D'agua Mat De Const Ltda | H84: Construção da Sede - Instalações hidrossanitárias | I84: OUTRAS | J84: NF 281269 | K84: - | L84: Pix | M84: Cooperativa Sicredi (0913) | N84: Pago | O84: -84.4
B85: 46039 | C85: =PROPER(TEXT(B85,"MMMM")) -> Janeiro | D85: 2.7 – Investimentos em Imobilizado Operacional | E85: 2.7.2 – Obras e Melhorias (infraestrutura) | F85: Despesas Eventuais | G85: Douratubos Acessórios Industriais Ltda | H85: Construção da Sede - Instalações hidrossanitárias | I85: OUTRAS | J85: NF 356916 | K85: 2/3 | L85: Boleto | M85: Cooperativa Sicredi (0902) | N85: Pago | O85: -1348.67
B86: 46039 | C86: =PROPER(TEXT(B86,"MMMM")) -> Janeiro | D86: 2.7 – Investimentos em Imobilizado Operacional | E86: 2.7.2 – Obras e Melhorias (infraestrutura) | F86: Despesas Eventuais | G86: Smart Center Comércio de Materiais de Construção Ltda | H86: Construção da Sede_Obra_Contrato - Material de Construção | I86: ORDEM DE COMPRA | J86: NF 10010 | K86: 2/3 | L86: Boleto | M86: Cooperativa Sicredi (0902) | N86: Pago | O86: -2583.19
B87: 46039 | C87: =PROPER(TEXT(B87,"MMMM")) -> Janeiro | D87: 2.7 – Investimentos em Imobilizado Operacional | E87: 2.7.2 – Obras e Melhorias (infraestrutura) | F87: Despesas Eventuais | G87: Smart Center Comércio de Materiais de Construção Ltda | H87: Construção da Sede_Obra_Contrato - Material de Construção | I87: ORDEM DE COMPRA | J87: NF 4915 | K87: 2/3 | L87: Boleto | M87: Cooperativa Sicredi (0902) | N87: Pago | O87: -6027.45
B88: 46040 | C88: =PROPER(TEXT(B88,"MMMM")) -> Janeiro | D88: 2.7 – Investimentos em Imobilizado Operacional | E88: 2.7.3 – Benfeitorias Temporárias / Construções Leves | F88: Despesas Variáveis | G88: Bica D'agua Mat De Const Ltda | H88: Cimento + Tijolos | Manutenção nos Cochos do Chiqueiro | I88: - | J88: NF 281464 | K88: - | L88: Pix | M88: Banco Cora (0001) | N88: Pago | O88: -65.45
B89: 46041 | C89: =PROPER(TEXT(B89,"MMMM")) -> Janeiro | D89: 1.9 – Outros Recebimentos | E89: 1.9.1 – Diversos | F89: - | G89: Agropecuária Aramburu Ltda | H89: Transferência Entre Contas | I89: - | J89: - | K89: - | L89: Pix | M89: Banco Cora (0001) | N89: Recebido | O89: 16516.94
B90: 46041 | C90: =PROPER(TEXT(B90,"MMMM")) -> Janeiro | D90: 2.9 – Outras Saídas | E90: 2.9.3 – Outras Despesas Não Classificadas | F90: - | G90: Agropecuária Aramburu Ltda | H90: Transf. Entre Contas_Resgate Investimento XP - Extra Emergencial p/ Construção da Sede | I90: - | J90: - | K90: - | L90: Transferência | M90: Banco Cora (0001) | N90: Pago | O90: -200084.84
B91: 46041 | C91: =PROPER(TEXT(B91,"MMMM")) -> Janeiro | D91: 1.8 – Resgate de Aplicações | E91: 1.8.1 – Cooperativa Sicredi | F91: - | G91: Banco Cooperativa Sicredi | H91: Resgate da Conta Investimento Invest Evolutivo - Reserva p/ Construção da Sede | I91: - | J91: - | K91: - | L91: - | M91: Cooperativa Sicredi (0902) | N91: Resgatado | O91: 26325.57
B92: 46041 | C92: =PROPER(TEXT(B92,"MMMM")) -> Janeiro | D92: 2.7 – Investimentos em Imobilizado Operacional | E92: 2.7.2 – Obras e Melhorias (infraestrutura) | F92: Despesas Eventuais | G92: WS Locações de Máquinas Ltda | H92: Construção da Sede_Obra_Contrato - Locação de Equipamentos (Andaimes) | I92: ORDEM DE COMPRA | J92: ND-020548 | K92: - | L92: Boleto | M92: Cooperativa Sicredi (0913) | N92: Pago | O92: -804
B93: 46041 | C93: =PROPER(TEXT(B93,"MMMM")) -> Janeiro | D93: 2.9 – Outras Saídas | E93: 2.9.3 – Outras Despesas Não Classificadas | F93: - | G93: Agropecuária Aramburu Ltda | H93: Transferência Entre Contas | I93: - | J93: - | K93: - | L93: Pix | M93: Cooperativa Sicredi (0913) | N93: Pago | O93: -16516.94
B94: 46041 | C94: =PROPER(TEXT(B94,"MMMM")) -> Janeiro | D94: 1.9 – Outros Recebimentos | E94: 1.9.1 – Diversos | F94: - | G94: Agropecuária Aramburu Ltda | H94: Transf. Entre Contas_Resgate Investimento XP - Extra Emergencial p/ Construção da Sede | I94: - | J94: - | K94: - | L94: Transferência | M94: Cooperativa Sicredi (0913) | N94: Recebido | O94: 200084.84
B95: 46041 | C95: =PROPER(TEXT(B95,"MMMM")) -> Janeiro | D95: 2.6 – Investimentos em Capital | E95: 2.6.1 – Aplicações Financeiras | F95: - | G95: Agropecuária Aramburu Ltda | H95: Aplicação Financeira - Extra Emergencial p/ Construção da Sede | I95: - | J95: - | K95: - | L95: Transferência | M95: Cooperativa Sicredi (0913) | N95: Aplicado | O95: -200084.84
B96: 46042 | C96: =PROPER(TEXT(B96,"MMMM")) -> Janeiro | D96: 2.3 – Operação da Propriedade | E96: 2.3.5 – Combustíveis e Lubrificantes | F96: Despesas Variáveis | G96: Copasul Comercio Varejistas - Posto Carreteiro | H96: Abastecimentos Posto Carreteiro | I96: - | J96: NF 17850 | K96: - | L96: Boleto | M96: Banco Cora (0001) | N96: Pago | O96: =-304-312.5-145.19 -> -761.69
B97: 46042 | C97: =PROPER(TEXT(B97,"MMMM")) -> Janeiro | D97: 2.7 – Investimentos em Imobilizado Operacional | E97: 2.7.2 – Obras e Melhorias (infraestrutura) | F97: Despesas Eventuais | G97: Receita Federal | H97: Construção da Sede_Projeto_Contrato - Execução (INSS) | I97: MEDIÇÃO 04 | J97: NF 258 | K97: - | L97: Guia | M97: Banco Cora (0001) | N97: Pago | O97: -13095.24
B98: 46042 | C98: =PROPER(TEXT(B98,"MMMM")) -> Janeiro | D98: 2.7 – Investimentos em Imobilizado Operacional | E98: 2.7.2 – Obras e Melhorias (infraestrutura) | F98: Despesas Eventuais | G98: Receita Federal | H98: Construção da Sede_Projeto_Contrato - Execução (INSS) | I98: MEDIÇÃO 05 | J98: NF 262 | K98: - | L98: Guia | M98: Banco Cora (0001) | N98: Pago | O98: -3421.7
B99: 46042 | C99: =PROPER(TEXT(B99,"MMMM")) -> Janeiro | D99: 2.2 – Despesas com Pessoal | E99: 2.2.2 – Encargos Sociais (INSS, FGTS) | F99: Despesas Fixas | G99: Receita Federal | H99: INSS Folha de Pgto | I99: - | J99: Dez/2025 | K99: - | L99: Guia | M99: Banco Cora (0001) | N99: Pago | O99: -2428.98
B100: 46042 | C100: =PROPER(TEXT(B100,"MMMM")) -> Janeiro | D100: 2.2 – Despesas com Pessoal | E100: 2.2.2 – Encargos Sociais (INSS, FGTS) | F100: Despesas Fixas | G100: Ministério Do Trabalho E Emprego | H100: FGTS 13/2025 | I100: - | J100: 13º/2025 | K100: - | L100: Guia | M100: Banco Cora (0001) | N100: Pago | O100: -200
B101: 46042 | C101: =PROPER(TEXT(B101,"MMMM")) -> Janeiro | D101: 2.2 – Despesas com Pessoal | E101: 2.2.2 – Encargos Sociais (INSS, FGTS) | F101: Despesas Fixas | G101: Ministério Do Trabalho E Emprego | H101: FGTS Folha de Pgto | I101: - | J101: Dez/2025 | K101: - | L101: Guia | M101: Banco Cora (0001) | N101: Pago | O101: -400
B102: 46042 | C102: =PROPER(TEXT(B102,"MMMM")) -> Janeiro | D102: 2.8 – Distribuição de Lucro / Saídas Pessoais | E102: 2.8.1 – Distribuição de Lucros | F102: - | G102: Aramburu Participações Ltda | H102: Banco Inter - Distribuição de Lucro | I102: - | J102: Jan/2026 | K102: - | L102: Pix | M102: Banco Cora (0001) | N102: Repassado | O102: -915.86
B103: 46042 | C103: =PROPER(TEXT(B103,"MMMM")) -> Janeiro | D103: 2.7 – Investimentos em Imobilizado Operacional | E103: 2.7.2 – Obras e Melhorias (infraestrutura) | F103: Despesas Eventuais | G103: Kingspan Isoeste Construtivo Isotérmicos S/A | H103: Construção da Sede_Obra_Contrato - Telhas, acessórios de fixação e acessórios de acabamento | I103: ORDEM DE COMPRA | J103: NF 73519 | K103: 4/4 | L103: Boleto | M103: Cooperativa Sicredi (0902) | N103: Pago | O103: -26325.57
B104: 46043 | C104: =PROPER(TEXT(B104,"MMMM")) -> Janeiro | D104: 2.7 – Investimentos em Imobilizado Operacional | E104: 2.7.2 – Obras e Melhorias (infraestrutura) | F104: Despesas Eventuais | G104: Comercial Elétrica Dourados Ltda | H104: Construção da Sede - Instalações elétricas | I104: OUTRAS | J104: NF 314450 | K104: 2/3 | L104: Boleto | M104: Cooperativa Sicredi (0902) | N104: Pago | O104: -657
B105: 46043 | C105: =PROPER(TEXT(B105,"MMMM")) -> Janeiro | D105: 2.5 – Financeiras e Bancárias | E105: 2.5.2 – Tarifas Bancárias | F105: Despesas Fixas | G105: Banco Cooperativa Sicredi | H105: Integralização de Capital Subscrito | I105: - | J105: Jan/2026 | K105: - | L105: Débito Automático | M105: Cooperativa Sicredi (0902) | N105: Pago | O105: -50
B106: 46044 | C106: =PROPER(TEXT(B106,"MMMM")) -> Janeiro | D106: 2.8 – Distribuição de Lucro / Saídas Pessoais | E106: 2.8.1 – Distribuição de Lucros | F106: - | G106: Aramburu Participações Ltda | H106: Banco Inter - Distribuição de Lucro | I106: - | J106: Jan/2026 | K106: - | L106: Pix | M106: Banco Cora (0001) | N106: Repassado | O106: -100
B107: 46044 | C107: =PROPER(TEXT(B107,"MMMM")) -> Janeiro | D107: 1.8 – Resgate de Aplicações | E107: 1.8.1 – Cooperativa Sicredi | F107: - | G107: Banco Cooperativa Sicredi | H107: Resgate da Conta Investimento Invest - Reserva p/ Construção da Sede | I107: - | J107: - | K107: - | L107: - | M107: Cooperativa Sicredi (0913) | N107: Resgatado | O107: =380.13+400 -> 780.13
B108: 46044 | C108: =PROPER(TEXT(B108,"MMMM")) -> Janeiro | D108: 1.8 – Resgate de Aplicações | E108: 1.8.1 – Cooperativa Sicredi | F108: - | G108: Banco Cooperativa Sicredi | H108: Resgate da Conta Investimento Invest - Reserva p/ Construção da Sede | I108: - | J108: - | K108: - | L108: - | M108: Cooperativa Sicredi (0913) | N108: Resgatado | O108: 2850
B109: 46045 | C109: =PROPER(TEXT(B109,"MMMM")) -> Janeiro | D109: 2.7 – Investimentos em Imobilizado Operacional | E109: 2.7.2 – Obras e Melhorias (infraestrutura) | F109: Despesas Eventuais | G109: Gabriel e Cia Ltda - Conquista | H109: Construção da Sede - Materiais Elétricos | I109: OUTRAS | J109: NF 23626 | K109: - | L109: Boleto | M109: Cooperativa Sicredi (0913) | N109: Pago | O109: -380.13
B110: 46045 | C110: =PROPER(TEXT(B110,"MMMM")) -> Janeiro | D110: 2.7 – Investimentos em Imobilizado Operacional | E110: 2.7.2 – Obras e Melhorias (infraestrutura) | F110: Despesas Eventuais | G110: Comercial Elétrica Dourados Ltda | H110: Construção da Sede - Instalações elétricas | I110: OUTRAS | J110: NF 314524 | K110: 2/6 | L110: Boleto | M110: Cooperativa Sicredi (0913) | N110: Pago | O110: -2850
B111: 46046 | C111: =PROPER(TEXT(B111,"MMMM")) -> Janeiro | D111: 2.8 – Distribuição de Lucro / Saídas Pessoais | E111: 2.8.3 – Pagamentos Pessoais (não operacionais) | F111: Despesas Fixas | G111: Bradesco Saúde | H111: Plano de Saúde Bradesco | I111: - | J111: Jan/2026 | K111: - | L111: Pix | M111: Banco Cora (0001) | N111: Pago | O111: -8489.33
B112: 46047 | C112: =PROPER(TEXT(B112,"MMMM")) -> Janeiro | D112: 2.2 – Despesas com Pessoal | E112: 2.2.3 – Benefícios (vale, alimentação, etc.) | F112: Despesas Variáveis | G112: Tavares e Soares C. G. A. Ltda - Farturão | H112: 01 Kit Cesta Básica Economia (1 pessoa) | I112: - | J112: NF 40606 | K112: - | L112: Boleto | M112: Banco Cora (0001) | N112: Pago | O112: -180
B113: 46047 | C113: =PROPER(TEXT(B113,"MMMM")) -> Janeiro | D113: 2.2 – Despesas com Pessoal | E113: 2.2.3 – Benefícios (vale, alimentação, etc.) | F113: Despesas Variáveis | G113: Tavares e Soares C. G. A. Ltda - Farturão | H113: 01 Kit Cesta Básica Solidária (Casal) | I113: - | J113: NF 40518 | K113: - | L113: Boleto | M113: Banco Cora (0001) | N113: Pago | O113: -310
B114: 46048 | C114: =PROPER(TEXT(B114,"MMMM")) -> Janeiro | D114: 1.8 – Resgate de Aplicações | E114: 1.8.1 – Cooperativa Sicredi | F114: - | G114: Banco Cooperativa Sicredi | H114: Resgate da Conta Investimento Invest Evolutivo - Reserva p/ Construção da Sede | I114: - | J114: - | K114: - | L114: - | M114: Cooperativa Sicredi (0902) | N114: Resgatado | O114: 12200
B115: 46048 | C115: =PROPER(TEXT(B115,"MMMM")) -> Janeiro | D115: 2.7 – Investimentos em Imobilizado Operacional | E115: 2.7.2 – Obras e Melhorias (infraestrutura) | F115: Despesas Eventuais | G115: Rafael Crippa ME - Fênix Containers | H115: Construção da Sede_Obra_Contrato - Locação de Equipamento (Container) | I115: ORDEM DE COMPRA | J115: ND 3538 | K115: - | L115: Boleto | M115: Cooperativa Sicredi (0913) | N115: Pago | O115: -400
B116: 46049 | C116: =PROPER(TEXT(B116,"MMMM")) -> Janeiro | D116: 2.1 – Despesas Administrativas | E116: 2.1.6 – Taxas e Impostos (ITR, INCRA, etc.) | F116: Despesas Periódicas | G116: OFC Certificação Digital Ltda | H116: Renovação OFC PJ Agropecuária Aramburu Ltda | I116: - | J116: 2026 | K116: - | L116: Pix | M116: Banco Cora (0001) | N116: Pago | O116: -200
B117: 46049 | C117: =PROPER(TEXT(B117,"MMMM")) -> Janeiro | D117: 2.7 – Investimentos em Imobilizado Operacional | E117: 2.7.2 – Obras e Melhorias (infraestrutura) | F117: Despesas Eventuais | G117: JV Tubos e Acabamentos Ltda | H117: Construção da Sede - Pisos | I117: OUTRAS | J117: NF 360329 | K117: 4/5 | L117: Boleto | M117: Cooperativa Sicredi (0902) | N117: Pago | O117: -12200
B118: 46051 | C118: =PROPER(TEXT(B118,"MMMM")) -> Janeiro | D118: 2.1 – Despesas Administrativas | E118: 2.1.6 – Taxas e Impostos (ITR, INCRA, etc.) | F118: Despesas Fixas | G118: Ministério Da Fazenda | H118: CSLL 4º Trimestre/2025 | I118: - | J118: 2025 | K118: - | L118: Guia | M118: Banco Cora (0001) | N118: Pago | O118: -18524.6
B119: 46051 | C119: =PROPER(TEXT(B119,"MMMM")) -> Janeiro | D119: 2.1 – Despesas Administrativas | E119: 2.1.6 – Taxas e Impostos (ITR, INCRA, etc.) | F119: Despesas Fixas | G119: Receita Federal | H119: IRPJ-LP 4º Trimestre/2025 | I119: - | J119: 2025 | K119: - | L119: Guia | M119: Banco Cora (0001) | N119: Pago | O119: -10179.9
B120: 46051 | C120: =PROPER(TEXT(B120,"MMMM")) -> Janeiro | D120: 2.8 – Distribuição de Lucro / Saídas Pessoais | E120: 2.8.1 – Distribuição de Lucros | F120: - | G120: Aramburu Participações Ltda | H120: Banco Inter - Distribuição de Lucro | I120: - | J120: Jan/2026 | K120: - | L120: Pix | M120: Banco Cora (0001) | N120: Repassado | O120: -444
B121: 46051 | C121: =PROPER(TEXT(B121,"MMMM")) -> Janeiro | D121: 2.1 – Despesas Administrativas | E121: 2.1.8 – Despesas Gerais | F121: Despesas Variáveis | G121: Silvana Silva Lima - Dr. Note Informática | H121: 01 bateria original do notebook Dell Inspiron 5448 + instalação + troca do conector USB | I121: - | J121: NF 79 | K121: 1/2 | L121: Pix | M121: Banco Cora (0001) | N121: Pago | O121: -207.5
B122: 46051 | C122: =PROPER(TEXT(B122,"MMMM")) -> Janeiro | D122: 1.8 – Resgate de Aplicações | E122: 1.8.1 – Cooperativa Sicredi | F122: - | G122: Banco Cooperativa Sicredi | H122: Resgate da Conta Investimento Invest - Reserva p/ Construção da Sede | I122: - | J122: - | K122: - | L122: - | M122: Cooperativa Sicredi (0913) | N122: Resgatado | O122: 900
B123: 46051 | C123: =PROPER(TEXT(B123,"MMMM")) -> Janeiro | D123: 2.7 – Investimentos em Imobilizado Operacional | E123: 2.7.2 – Obras e Melhorias (infraestrutura) | F123: Despesas Eventuais | G123: Prebase Artefato de Concreto | H123: Construção da Sede - Elemento vazado (cobogó flor natural 39x39x7) | I123: OUTRAS | J123: NF 6308 | K123: - | L123: Pix | M123: Cooperativa Sicredi (0913) | N123: Pago | O123: -900
B124: 46052 | C124: =PROPER(TEXT(B124,"MMMM")) -> Janeiro | D124: 2.8 – Distribuição de Lucro / Saídas Pessoais | E124: 2.8.1 – Distribuição de Lucros | F124: - | G124: Aramburu Participações Ltda | H124: Banco Inter - Distribuição de Lucro | I124: - | J124: Jan/2026 | K124: - | L124: Pix | M124: Banco Cora (0001) | N124: Repassado | O124: -9355.72
B125: 46052 | C125: =PROPER(TEXT(B125,"MMMM")) -> Janeiro | D125: 1.2 – Receita de Arrendamento de Terras | E125: 1.2.1 – Venda de Soja | F125: - | G125: Copasul Cooperativa | H125: Venda Soja Safra 24/25 | I125: - | J125: NF 8066969 | K125: - | L125: Pix | M125: Banco Cora (0001) | N125: Recebido | O125: 960000
B126: 46054 | C126: =PROPER(TEXT(B126,"MMMM")) -> Fevereiro | D126: 2.8 – Distribuição de Lucro / Saídas Pessoais | E126: 2.8.1 – Distribuição de Lucros | F126: - | G126: Aramburu Participações Ltda | H126: Banco Inter - Distribuição de Lucro | I126: - | J126: Fev/2026 | K126: - | L126: Pix | M126: Banco Cora (0001) | N126: Repassado | O126: -79702.92
B127: 46055 | C127: =PROPER(TEXT(B127,"MMMM")) -> Fevereiro | D127: 2.5 – Financeiras e Bancárias | E127: 2.5.2 – Tarifas Bancárias | F127: Despesas Fixas | G127: Banco Cooperativa Sicredi | H127: Integralização de Capital Subscrito | I127: - | J127: Fev/2026 | K127: - | L127: Débito Automático | M127: Cooperativa Sicredi (0913) | N127: Pago | O127: -100
B128: 46055 | C128: =PROPER(TEXT(B128,"MMMM")) -> Fevereiro | D128: 2.3 – Operação da Propriedade | E128: 2.3.6 – Produtos e Peças | F128: Despesas Variáveis | G128: Agro Amizade Com. De Produtos Veterinário Ltda | H128: Diversos | I128: - | J128: NF 768 | K128: - | L128: Pix | M128: Banco Cora (0001) | N128: Pago | O128: -1010
...

Sheet _
B12: Status | C12: (Tudo)
B14: Soma de Valor | C14: Rótulos de Coluna
B15: Rótulos de Linha | C15: Janeiro | D15: Fevereiro | E15: Março | F15: Abril | G15: Maio | H15: Junho | I15: Julho | J15: Agosto | K15: Setembro | L15: Outubro | M15: Novembro | N15: Dezembro | O15: Total Geral
B16: 1.1 - Imóvel | C16: 28593.56 | D16: 29781.4 | E16: 33242.19 | F16: 54266.64 | G16: 2200 | H16: 28205.72 | I16: 26876.23 | J16: 26876.23 | K16: 26876.23 | L16: 26876.23 | M16: 26876.23 | N16: 26876.23 | O16: 337546.89
B17: 1.2 - Família | C17: 3504.84 | D17: 10445.88 | E17: 757.8 | F17: 6804.32 | H17: 3944 | I17: 3944 | J17: 3944 | K17: 3944 | L17: 3944 | M17: 5944 | N17: 4944 | O17: 52120.84
B18: 1.3 - Renda Mensal/Qualidade de Vida | C18: 22415.99 | D18: 40468.25 | E18: 111423.25 | F18: 59936.5 | H18: 48568.25 | I18: 21968.25 | J18: 131223.25 | K18: 74168.25 | L18: 101168.25 | M18: 67968.25 | N18: 84168.25 | O18: 763476.74
B19: 1.4 - Despesas Pessoais | C19: 16836.03 | D19: 1177.76 | E19: 2190.07 | F19: 9989.44 | G19: 20903.84 | H19: 3454.77 | I19: 3254.77 | J19: 2493.13 | K19: 2554.77 | L19: 2254.77 | M19: 8960.77 | N19: 6206.2 | O19: 80276.32
B20: 1.5 - Fazenda Aramburu | C20: 13250.88 | D20: 12456.41 | E20: 9622.21 | F20: 19958.13 | G20: 4610.91 | H20: 8992.25 | I20: 15354.49 | J20: 12997.53 | K20: 13527.88 | L20: 11290.02 | M20: 12252.25 | N20: 12492.25 | O20: 146805.21
B21: 1.6 - Contratos de Venda | E21: 278995.54 | F21: 278995.53 | O21: 557991.07
B22: Total Geral | C22: 84601.3 | D22: 94329.7 | E22: 436231.06 | F22: 429950.56 | G22: 27714.75 | H22: 93164.99 | I22: 71397.74 | J22: 177534.14 | K22: 121071.13 | L22: 145533.27 | M22: 122001.5 | N22: 134686.93 | O22: 1938217.1

Sheet Distribuição de Lucro_Mensal
C3: DISTRIBUIÇÃO DE LUCRO
C5: Dia | D5: Mês | E5: Sócio | F5: Classificação | G5: Descrição | H5: Banco | I5: Valor | J5: Data Vencimento | K5: Status
C6: 46024 | D6: =PROPER(TEXT(C6,"MMMM")) -> Janeiro | E6: Claudio Luiz Resta Fragelli | F6: 1.1 - Imóvel | G6: Parcelamento (Residência SC) | H6: Bradesco 3489 C/C 3154-2 | I6: 13616.54 | J6: 46024 | K6: Realizado | L6: 10476.95 | M6: Sócio | O6: Classificação
C7: 46024 | D7: =PROPER(TEXT(C7,"MMMM")) -> Janeiro | E7: Claudio Luiz Resta Fragelli | F7: 1.1 - Imóvel | G7: Reforma Programada | H7: Bradesco 3489 C/C 3154-2 | I7: 2000 | J7: 46024 | K7: Realizado | M7: Ana Beatriz Ponte Fragelli | O7: 1.1 - Imóvel
C8: 46024 | D8: =PROPER(TEXT(C8,"MMMM")) -> Janeiro | E8: Claudio Luiz Resta Fragelli | F8: 1.3 - Renda Mensal/Qualidade de Vida | G8: Custos Emergenciais | H8: Bradesco 1375 C/C 242867-9 | I8: 300 | J8: 46024 | K8: Realizado | M8: Claudio Luiz Resta Fragelli | O8: 1.2 - Família
C9: 46024 | D9: =PROPER(TEXT(C9,"MMMM")) -> Janeiro | E9: Claudio Luiz Resta Fragelli | F9: 1.3 - Renda Mensal/Qualidade de Vida | G9: Distribuição Fixa | H9: Bradesco 1375 C/C 242867-9 | I9: 3105 | J9: 46024 | K9: Realizado | M9: Isamelia Ponte Fragelli | O9: 1.3 - Renda Mensal/Qualidade de Vida
C10: 46024 | D10: =PROPER(TEXT(C10,"MMMM")) -> Janeiro | E10: Claudio Luiz Resta Fragelli | F10: 1.3 - Renda Mensal/Qualidade de Vida | G10: Medicamentos | H10: Bradesco 1375 C/C 242867-9 | I10: 713.25 | J10: 46024 | K10: Realizado | M10: Pedro Henrique Ponte Fragelli | O10: 1.4 - Despesas Pessoais
C11: 46024 | D11: =PROPER(TEXT(C11,"MMMM")) -> Janeiro | E11: Claudio Luiz Resta Fragelli | F11: 1.3 - Renda Mensal/Qualidade de Vida | G11: Troca de Celular | H11: B. Brasil cfragelli7@gmail.com | I11: 447.74 | J11: 46024 | K11: Realizado | O11: 1.5 - Fazenda Aramburu
C12: 46024 | D12: =PROPER(TEXT(C12,"MMMM")) -> Janeiro | E12: Claudio Luiz Resta Fragelli | F12: 1.4 - Despesas Pessoais | G12: Manutenção Conta Bradesco | H12: Bradesco 1375 C/C 242867-9 | I12: 150 | J12: 46024 | K12: Realizado | O12: 1.6 - Contratos de Venda
C13: 46024 | D13: =PROPER(TEXT(C13,"MMMM")) -> Janeiro | E13: Claudio Luiz Resta Fragelli | F13: 1.4 - Despesas Pessoais | G13: Troca de Pneus | H13: Bradesco 3489 C/C 3154-2 | I13: 3200 | J13: 46024 | K13: Realizado
C14: 46024 | D14: =PROPER(TEXT(C14,"MMMM")) -> Janeiro | E14: Claudio Luiz Resta Fragelli | F14: 1.5 - Fazenda Aramburu | G14: FGTS 12/2025 e 13º Folha de Pgto | H14: Bradesco 3489 C/C 3154-2 | I14: 626.8 | J14: 46042 | K14: Realizado
C15: 46024 | D15: =PROPER(TEXT(C15,"MMMM")) -> Janeiro | E15: Claudio Luiz Resta Fragelli | F15: 1.5 - Fazenda Aramburu | G15: Folha de Pgto - Amadeu Fava Junior | H15: Bradesco 3489 C/C 3154-2 | I15: 2297.77 | J15: 46027 | K15: Realizado
C16: 46024 | D16: =PROPER(TEXT(C16,"MMMM")) -> Janeiro | E16: Claudio Luiz Resta Fragelli | F16: 1.5 - Fazenda Aramburu | G16: Folha de Pgto - Cristiane da Silva Freire | H16: Bradesco 3489 C/C 3154-2 | I16: 1469.15 | J16: 46027 | K16: Realizado
C17: 46024 | D17: =PROPER(TEXT(C17,"MMMM")) -> Janeiro | E17: Claudio Luiz Resta Fragelli | F17: 1.5 - Fazenda Aramburu | G17: Folha de Pgto - Peres Siqueira | H17: Bradesco 3489 C/C 3154-2 | I17: 2297.77 | J17: 46027 | K17: Realizado
C18: 46024 | D18: =PROPER(TEXT(C18,"MMMM")) -> Janeiro | E18: Claudio Luiz Resta Fragelli | F18: 1.5 - Fazenda Aramburu | G18: INSS Folha de Pgto | H18: Bradesco 3489 C/C 3154-2 | I18: 466.34 | J18: 46042 | K18: Realizado
C19: 46024 | D19: =PROPER(TEXT(C19,"MMMM")) -> Janeiro | E19: Claudio Luiz Resta Fragelli | F19: 1.5 - Fazenda Aramburu | G19: Pluxee Multibenefícios - Amadeu Fava Junior | H19: Bradesco 3489 C/C 3154-2 | I19: 450 | J19: 46024 | K19: Realizado
C20: 46024 | D20: =PROPER(TEXT(C20,"MMMM")) -> Janeiro | E20: Claudio Luiz Resta Fragelli | F20: 1.5 - Fazenda Aramburu | G20: Pluxee Multibenefícios - Cristiane da Silva Freire | H20: Bradesco 3489 C/C 3154-2 | I20: 350 | J20: 46024 | K20: Realizado
C21: 46024 | D21: =PROPER(TEXT(C21,"MMMM")) -> Janeiro | E21: Claudio Luiz Resta Fragelli | F21: 1.5 - Fazenda Aramburu | G21: Pluxee Multibenefícios - Gabriel Costa | H21: Bradesco 3489 C/C 3154-2 | I21: 450 | J21: 46024 | K21: Realizado
C22: 46024 | D22: =PROPER(TEXT(C22,"MMMM")) -> Janeiro | E22: Isamelia Ponte Fragelli | F22: 1.1 - Imóvel | G22: Condomínio (Forest House CG) | H22: Bradesco 3489 C/C 35858-4 | I22: 1100 | J22: 46032 | K22: Realizado
C23: 46024 | D23: =PROPER(TEXT(C23,"MMMM")) -> Janeiro | E23: Isamelia Ponte Fragelli | F23: 1.1 - Imóvel | G23: Energisa (Forest House CG) | H23: Bradesco 3489 C/C 35858-4 | I23: 633.93 | J23: 46032 | K23: Realizado
C24: 46024 | D24: =PROPER(TEXT(C24,"MMMM")) -> Janeiro | E24: Isamelia Ponte Fragelli | F24: 1.1 - Imóvel | G24: Jardineiro (Forest House CG) | H24: Bradesco 3489 C/C 35858-4 | I24: 400 | J24: 46024 | K24: Realizado
... C58: 46054 | D58: =PROPER(TEXT(C58,"MMMM")) -> Fevereiro | E58: Claudio Luiz Resta Fragelli | F58: 1.4 - Despesas Pessoais | G58: Vivo Família Móvel | H58: Bradesco 3489 C/C 3154-2 | I58: 552.86 | J58: 46059 | K58: Realizado
C59: 46054 | D59: =PROPER(TEXT(C59,"MMMM")) -> Fevereiro | E59: Claudio Luiz Resta Fragelli | F59: 1.5 - Fazenda Aramburu | G59: FGTS Folha de Pgto | H59: Bradesco 3489 C/C 3154-2 | I59: 529.68 | J59: 202/02 | K59: Realizado
C60: 46054 | D60: =PROPER(TEXT(C60,"MMMM")) -> Fevereiro | E60: Claudio Luiz Resta Fragelli | F60: 1.5 - Fazenda Aramburu | G60: Folha de Pgto - Amadeu Fava Junior | H60: Bradesco 3489 C/C 3154-2 | I60: 2299.32 | J60: 46058 | K60: Realizado
C61: 46054 | D61: =PROPER(TEXT(C61,"MMMM")) -> Fevereiro | E61: Claudio Luiz Resta Fragelli | F61: 1.5 - Fazenda Aramburu | G61: Folha de Pgto - Cristiane da Silva Freire | H61: Bradesco 3489 C/C 3154-2 | I61: 1566.97 | J61: 46058 | K61: Realizado
C62: 46054 | D62: =PROPER(TEXT(C62,"MMMM")) -> Fevereiro | E62: Claudio Luiz Resta Fragelli | F62: 1.5 - Fazenda Aramburu | G62: Folha de Pgto - Peres Siqueira | H62: Bradesco 3489 C/C 3154-2 | I62: 2299.32 | J62: 46058 | K62: Realizado
C63: 46054 | D63: =PROPER(TEXT(C63,"MMMM")) -> Fevereiro | E63: Claudio Luiz Resta Fragelli | F63: 1.5 - Fazenda Aramburu | G63: INSS Folha de Pgto | H63: Bradesco 3489 C/C 3154-2 | I63: 468.63 | J63: 46073 | K63: Realizado
C64: 46054 | D64: =PROPER(TEXT(C64,"MMMM")) -> Fevereiro | E64: Claudio Luiz Resta Fragelli | F64: 1.5 - Fazenda Aramburu | G64: Pluxee Multibenefícios - Amadeu Fava Junior | H64: Bradesco 3489 C/C 3154-2 | I64: 450 | J64: 46055 | K64: Realizado
C65: 46054 | D65: =PROPER(TEXT(C65,"MMMM")) -> Fevereiro | E65: Claudio Luiz Resta Fragelli | F65: 1.5 - Fazenda Aramburu | G65: Pluxee Multibenefícios - Cristiane da Silva Freire | H65: Bradesco 3489 C/C 3154-2 | I65: 350 | J65: 46055 | K65: Realizado
C66: 46054 | D66: =PROPER(TEXT(C66,"MMMM")) -> Fevereiro | E66: Claudio Luiz Resta Fragelli | F66: 1.5 - Fazenda Aramburu | G66: Pluxee Multibenefícios - Gabriel Costa | H66: Bradesco 3489 C/C 3154-2 | I66: 321.43 | J66: 46055 | K66: Realizado
C67: 46055 | D67: =PROPER(TEXT(C67,"MMMM")) -> Fevereiro | E67: Claudio Luiz Resta Fragelli | F67: 1.1 - Imóvel | G67: IPTU (Atmosphera) parc. 2/6 | H67: Bradesco 3489 C/C 3154-2 | I67: 1329.49 | J67: 46065 | K67: Realizado
C68: 46055 | D68: =PROPER(TEXT(C68,"MMMM")) -> Fevereiro | E68: Claudio Luiz Resta Fragelli | F68: 1.1 - Imóvel | G68: IPTU (Casa Vila Inventário) parc. 2/12 | H68: Bradesco 3489 C/C 3154-2 | I68: 204.78 | J68: 46065 | K68: Realizado
C69: 46055 | D69: =PROPER(TEXT(C69,"MMMM")) -> Fevereiro | E69: Claudio Luiz Resta Fragelli | F69: 1.1 - Imóvel | G69: IPTU (Forest House) parc. 2/12 | H69: Bradesco 3489 C/C 3154-2 | I69: 503.91 | J69: 46065 | K69: Realizado
C70: 46055 | D70: =PROPER(TEXT(C70,"MMMM")) -> Fevereiro | E70: Claudio Luiz Resta Fragelli | F70: 1.1 - Imóvel | G70: IPTU (R. Appa 201) | H70: Bradesco 3489 C/C 3154-2 | I70: 2287.21 | J70: 46065 | K70: Realizado
C71: 46055 | D71: =PROPER(TEXT(C71,"MMMM")) -> Fevereiro | E71: Claudio Luiz Resta Fragelli | F71: 1.1 - Imóvel | G71: Parcelamento (Residência SC) | H71: Bradesco 3489 C/C 3154-2 | I71: 13616.54 | J71: 46055 | K71: Realizado
... C144: 46104 | D144: =PROPER(TEXT(C144,"MMMM")) -> Março | E144: Claudio Luiz Resta Fragelli | F144: 1.5 - Fazenda Aramburu | G144: Exames Clínica CMT - Peres (Demissional) e Gabriel (Admissional) | H144: Bradesco 3489 C/C 3154-2 | I144: 276 | J144: 46108 | K144: Realizado
C145: 46111 | D145: =PROPER(TEXT(C145,"MMMM")) -> Março | E145: Ana Beatriz Ponte Fragelli | F145: 1.6 - Contratos de Venda | G145: Repasse Venda Soja 24/25 | H145: Inter 0001 C/C 12284789-0 | I145: =278995.536/2 -> 139497.77 | J145: 46111 | K145: Realizado
C146: 46111 | D146: =PROPER(TEXT(C146,"MMMM")) -> Março | E146: Ana Beatriz Ponte Fragelli | F146: 1.6 - Contratos de Venda | G146: Repasse Venda Soja 24/25 | H146: Inter 0001 C/C 12284789-0 | I146: =278995.536/2 -> 139497.77 | J146: 46111 | K146: Realizado
C147: 46113 | D147: =PROPER(TEXT(C147,"MMMM")) -> Abril | E147: Ana Beatriz Ponte Fragelli | F147: 1.6 - Contratos de Venda | G147: Repasse Venda Soja 24/25 | H147: Inter 0001 C/C 12284789-0 | I147: 139497.77 | J147: 46113 | K147: Realizado
C148: 46113 | D148: =PROPER(TEXT(C148,"MMMM")) -> Abril | E148: Ana Beatriz Ponte Fragelli | F148: 1.6 - Contratos de Venda | G148: Repasse Venda Soja 24/25 | H148: Inter 0001 C/C 12284789-0 | I148: 139497.76 | J148: 46114 | K148: Realizado
C149: 46113 | D149: =PROPER(TEXT(C149,"MMMM")) -> Abril | E149: Claudio Luiz Resta Fragelli | F149: 1.1 - Imóvel | G149: IPTU (Atmosphera) parc. 4/6 | H149: Bradesco 3489 C/C 3154-2 | I149: 1329.49 | J149: 46124 | K149: Realizado
C150: 46113 | D150: =PROPER(TEXT(C150,"MMMM")) -> Abril | E150: Claudio Luiz Resta Fragelli | F150: 1.1 - Imóvel | G150: IPTU (Casa Vila Inventário) parc. 4/12 | H150: Bradesco 3489 C/C 3154-2 | I150: 204.78 | J150: 46124 | K150: Realizado
C151: 46113 | D151: =PROPER(TEXT(C151,"MMMM")) -> Abril | E151: Claudio Luiz Resta Fragelli | F151: 1.1 - Imóvel | G151: IPTU (Forest House) parc. 4/12 | H151: Bradesco 3489 C/C 3154-2 | I151: 503.91 | J151: 46124 | K151: Realizado
C152: 46113 | D152: =PROPER(TEXT(C152,"MMMM")) -> Abril | E152: Claudio Luiz Resta Fragelli | F152: 1.1 - Imóvel | G152: Parcelamento (Residência SC) | H152: Bradesco 3489 C/C 3154-2 | I152: 13616.54 | J152: 46113 | K152: Realizado
C153: 46113 | D153: =PROPER(TEXT(C153,"MMMM")) -> Abril | E153: Claudio Luiz Resta Fragelli | F153: 1.1 - Imóvel | G153: Reforma Programada | H153: Bradesco 3489 C/C 3154-2 | I153: 2000 | J153: 46113 | K153: Realizado
C154: 46113 | D154: =PROPER(TEXT(C154,"MMMM")) -> Abril | E154: Claudio Luiz Resta Fragelli | F154: 1.3 - Renda Mensal/Qualidade de Vida | G154: Custos Emergenciais | H154: Bradesco 1375 C/C 242867-9 | I154: 300 | J154: 46113 | K154: Realizado
C155: 46113 | D155: =PROPER(TEXT(C155,"MMMM")) -> Abril | E155: Claudio Luiz Resta Fragelli | F155: 1.3 - Renda Mensal/Qualidade de Vida | G155: Distribuição Fixa | H155: Bradesco 1375 C/C 242867-9 | I155: 3105 | J155: 46113 | K155: Realizado
C156: 46113 | D156: =PROPER(TEXT(C156,"MMMM")) -> Abril | E156: Claudio Luiz Resta Fragelli | F156: 1.3 - Renda Mensal/Qualidade de Vida | G156: Medicamentos | H156: Bradesco 1375 C/C 242867-9 | I156: 713.25 | J156: 46113 | K156: Realizado
C157: 46113 | D157: =PROPER(TEXT(C157,"MMMM")) -> Abril | E157: Claudio Luiz Resta Fragelli | F157: 1.4 - Despesas Pessoais | G157: Custos Cartório Habit-se Casa Barão | H157: Bradesco 3489 C/C 3154-2 | I157: 464.84 | J157: 46113 | K157: Realizado
C158: 46113 | D158: =PROPER(TEXT(C158,"MMMM")) -> Abril | E158: Claudio Luiz Resta Fragelli | F158: 1.4 - Despesas Pessoais | G158: Manutenção Conta Bradesco | H158: Bradesco 1375 C/C 242867-9 | I158: 150 | J158: 46113 | K158: Realizado
... C234: 46152 | D234: =PROPER(TEXT(C234,"MMMM")) -> Maio | E234: Claudio Luiz Resta Fragelli | F234: 1.5 - Fazenda Aramburu | G234: Energisa (Fazenda Aramburu) | H234: Bradesco 3489 C/C 3154-2 | I234: 860.91 | J234: 46158 | K234: Provisionado
C235: 46172 | D235: =PROPER(TEXT(C235,"MMMM")) -> Maio | E235: Claudio Luiz Resta Fragelli | F235: 1.4 - Despesas Pessoais | G235: IRPF 2026 | H235: Bradesco 3489 C/C 3154-2 | I235: 6847.64 | J235: - | K235: Provisionado
C236: 46172 | D236: =PROPER(TEXT(C236,"MMMM")) -> Maio | E236: Claudio Luiz Resta Fragelli | F236: 1.5 - Fazenda Aramburu | G236: Serviços Advocatícios Ação Civil Pública nº 0900021-98.2020.8.12.0014 | H236: Bradesco 3489 C/C 3154-2 | I236: 3750 | J236: - | K236: Provisionado
C237: 46172 | D237: =PROPER(TEXT(C237,"MMMM")) -> Maio | E237: Isamelia Ponte Fragelli | F237: 1.4 - Despesas Pessoais | G237: Seguro Veículo | H237: Bradesco 3489 C/C 35858-4 | I237: 6000 | J237: - | K237: Provisionado
C238: 46172 | D238: =PROPER(TEXT(C238,"MMMM")) -> Maio | E238: Isamelia Ponte Fragelli | F238: 1.4 - Despesas Pessoais | G238: Revisão Veículo | H238: Bradesco 3489 C/C 35858-4 | I238: 7000 | J238: - | K238: Provisionado
C239: 46174 | D239: =PROPER(TEXT(C239,"MMMM")) -> Junho | E239: Claudio Luiz Resta Fragelli | F239: 1.1 - Imóvel | G239: IPTU (Atmosphera) parc. 6/6 | H239: Bradesco 3489 C/C 3154-2 | I239: 1329.49 | J239: 46185 | K239: Provisionado
C240: 46174 | D240: =PROPER(TEXT(C240,"MMMM")) -> Junho | E240: Claudio Luiz Resta Fragelli | F240: 1.1 - Imóvel | G240: IPTU (Casa Vila Inventário) parc. 6/12 | H240: Bradesco 3489 C/C 3154-2 | I240: 204.78 | J240: 46185 | K240: Provisionado
C241: 46174 | D241: =PROPER(TEXT(C241,"MMMM")) -> Junho | E241: Claudio Luiz Resta Fragelli | F241: 1.1 - Imóvel | G241: IPTU (Forest House) parc. 6/12 | H241: Bradesco 3489 C/C 3154-2 | I241: 503.91 | J241: 46185 | K241: Provisionado
C242: 46174 | D242: =PROPER(TEXT(C242,"MMMM")) -> Junho | E242: Claudio Luiz Resta Fragelli | F242: 1.1 - Imóvel | G242: Parcelamento (Residência SC) | H242: Bradesco 3489 C/C 3154-2 | I242: 13616.54 | K242: Provisionado
C243: 46174 | D243: =PROPER(TEXT(C243,"MMMM")) -> Junho | E243: Claudio Luiz Resta Fragelli | F243: 1.1 - Imóvel | G243: Reforma Programada | H243: Bradesco 3489 C/C 3154-2 | I243: 2000 | K243: Provisionado
C244: 46174 | D244: =PROPER(TEXT(C244,"MMMM")) -> Junho | E244: Claudio Luiz Resta Fragelli | F244: 1.3 - Renda Mensal/Qualidade de Vida | G244: Custos Emergenciais | H244: Bradesco 1375 C/C 242867-9 | I244: 300 | K244: Provisionado
C245: 46174 | D245: =PROPER(TEXT(C245,"MMMM")) -> Junho | E245: Claudio Luiz Resta Fragelli | F245: 1.3 - Renda Mensal/Qualidade de Vida | G245: Distribuição Fixa | H245: Bradesco 1375 C/C 242867-9 | I245: 3105 | K245: Provisionado
C246: 46174 | D246: =PROPER(TEXT(C246,"MMMM")) -> Junho | E246: Claudio Luiz Resta Fragelli | F246: 1.3 - Renda Mensal/Qualidade de Vida | G246: Medicamentos | H246: Bradesco 1375 C/C 242867-9 | I246: 713.25 | K246: Provisionado
C247: 46174 | D247: =PROPER(TEXT(C247,"MMMM")) -> Junho | E247: Claudio Luiz Resta Fragelli | F247: 1.3 - Renda Mensal/Qualidade de Vida | G247: Tratamento Dentário | H247: Bradesco 1375 C/C 242867-9 | I247: 2500 | K247: Provisionado
C248: 46174 | D248: =PROPER(TEXT(C248,"MMMM")) -> Junho | E248: Claudio Luiz Resta Fragelli | F248: 1.3 - Renda Mensal/Qualidade de Vida | G248: Viagem Trimestral | H248: B. Brasil cfragelli7@gmail.com | I248: 7600 | K248: Provisionado
C249: 46174 | D249: =PROPER(TEXT(C249,"MMMM")) -> Junho | E249: Claudio Luiz Resta Fragelli | F249: 1.4 - Despesas Pessoais | G249: Seguro Veículo parc. 3/8 | H249: Bradesco 3489 C/C 3154-2 | I249: 1048.57 | J249: 46188 | K249: Provisionado
C250: 46174 | D250: =PROPER(TEXT(C250,"MMMM")) -> Junho | E250: Claudio Luiz Resta Fragelli | F250: 1.4 - Despesas Pessoais | G250: Manutenção Conta Bradesco | H250: Bradesco 1375 C/C 242867-9 | I250: 150 | K250: Provisionado
C251: 46174 | D251: =PROPER(TEXT(C251,"MMMM")) -> Junho | E251: Claudio Luiz Resta Fragelli | F251: 1.4 - Despesas Pessoais | G251: Renovação OFC Certificado Digital | H251: Bradesco 3489 C/C 3154-2 | I251: 200 | K251: Provisionado
C252: 46174 | D252: =PROPER(TEXT(C252,"MMMM")) -> Junho | E252: Claudio Luiz Resta Fragelli | F252: 1.4 - Despesas Pessoais | G252: Vivo Família Móvel | H252: Bradesco 3489 C/C 3154-2 | I252: 552.86 | K252: Provisionado
C253: 46174 | D253: =PROPER(TEXT(C253,"MMMM")) -> Junho | E253: Claudio Luiz Resta Fragelli | F253: 1.5 - Fazenda Aramburu | G253: Energisa (Fazenda Aramburu) | H253: Bradesco 3489 C/C 3154-2 | I253: 860.91 | K253: Provisionado
C254: 46174 | D254: =PROPER(TEXT(C254,"MMMM")) -> Junho | E254: Claudio Luiz Resta Fragelli | F254: 1.5 - Fazenda Aramburu | G254: FGTS Folha de Pgto | H254: Bradesco 3489 C/C 3154-2 | I254: 410 | K254: Provisionado
C255: 46174 | D255: =PROPER(TEXT(C255,"MMMM")) -> Junho | E255: Claudio Luiz Resta Fragelli | F255: 1.5 - Fazenda Aramburu | G255: Folha de Pgto - Amadeu Fava Junior | H255: Bradesco 3489 C/C 3154-2 | I255: 2300 | K255: Provisionado
C256: 46174 | D256: =PROPER(TEXT(C256,"MMMM")) -> Junho | E256: Claudio Luiz Resta Fragelli | F256: 1.5 - Fazenda Aramburu | G256: Folha de Pgto - Cristiane da Silva Freire | H256: Bradesco 3489 C/C 3154-2 | I256: 1405 | K256: Provisionado
C257: 46174 | D257: =PROPER(TEXT(C257,"MMMM")) -> Junho | E257: Claudio Luiz Resta Fragelli | F257: 1.5 - Fazenda Aramburu | G257: Folha de Pgto - Gabriel Costa | H257: Bradesco 3489 C/C 3154-2 | I257: 2300 | K257: Provisionado
C258: 46174 | D258: =PROPER(TEXT(C258,"MMMM")) -> Junho | E258: Claudio Luiz Resta Fragelli | F258: 1.5 - Fazenda Aramburu | G258: INSS Folha de Pgto | H258: Bradesco 3489 C/C 3154-2 | I258: 466.34 | K258: Provisionado
C259: 46174 | D259: =PROPER(TEXT(C259,"MMMM")) -> Junho | E259: Claudio Luiz Resta Fragelli | F259: 1.5 - Fazenda Aramburu | G259: Pluxee Multibenefícios - Amadeu Fava Junior | H259: Bradesco 3489 C/C 3154-2 | I259: 450 | K259: Provisionado
C260: 46174 | D260: =PROPER(TEXT(C260,"MMMM")) -> Junho | E260: Claudio Luiz Resta Fragelli | F260: 1.5 - Fazenda Aramburu | G260: Pluxee Multibenefícios - Cristiane da Silva Freire | H260: Bradesco 3489 C/C 3154-2 | I260: 350 | K260: Provisionado
C261: 46174 | D261: =PROPER(TEXT(C261,"MMMM")) -> Junho | E261: Claudio Luiz Resta Fragelli | F261: 1.5 - Fazenda Aramburu | G261: Pluxee Multibenefícios - Gabriel Costa | H261: Bradesco 3489 C/C 3154-2 | I261: 450 | K261: Provisionado
... C283: 46174 | D283: =PROPER(TEXT(C283,"MMMM")) -> Junho | E283: Pedro Henrique Ponte Fragelli | F283: 1.4 - Despesas Pessoais | G283: Curso | H283: XP 0001 C/C 817380-1 | I283: 1000 | K283: Provisionado
C284: 46204 | D284: =PROPER(TEXT(C284,"MMMM")) -> Julho | E284: Claudio Luiz Resta Fragelli | F284: 1.1 - Imóvel | G284: IPTU (Casa Vila Inventário) parc. 7/12 | H284: Bradesco 3489 C/C 3154-2 | I284: 204.78 | J284: 46215 | K284: Provisionado
C285: 46204 | D285: =PROPER(TEXT(C285,"MMMM")) -> Julho | E285: Claudio Luiz Resta Fragelli | F285: 1.1 - Imóvel | G285: IPTU (Forest House) parc. 7/12 | H285: Bradesco 3489 C/C 3154-2 | I285: 503.91 | J285: 46215 | K285: Provisionado
C286: 46204 | D286: =PROPER(TEXT(C286,"MMMM")) -> Julho | E286: Claudio Luiz Resta Fragelli | F286: 1.1 - Imóvel | G286: Parcelamento (Residência SC) | H286: Bradesco 3489 C/C 3154-2 | I286: 13616.54 | K286: Provisionado
C287: 46204 | D287: =PROPER(TEXT(C287,"MMMM")) -> Julho | E287: Claudio Luiz Resta Fragelli | F287: 1.1 - Imóvel | G287: Reforma Programada | H287: Bradesco 3489 C/C 3154-2 | I287: 2000 | K287: Provisionado
C288: 46204 | D288: =PROPER(TEXT(C288,"MMMM")) -> Julho | E288: Claudio Luiz Resta Fragelli | F288: 1.3 - Renda Mensal/Qualidade de Vida | G288: Custos Emergenciais | H288: Bradesco 1375 C/C 242867-9 | I288: 300 | K288: Provisionado
C289: 46204 | D289: =PROPER(TEXT(C289,"MMMM")) -> Julho | E289: Claudio Luiz Resta Fragelli | F289: 1.3 - Renda Mensal/Qualidade de Vida | G289: Distribuição Fixa | H289: Bradesco 1375 C/C 242867-9 | I289: 3105 | K289: Provisionado
C290: 46204 | D290: =PROPER(TEXT(C290,"MMMM")) -> Julho | E290: Claudio Luiz Resta Fragelli | F290: 1.3 - Renda Mensal/Qualidade de Vida | G290: Medicamentos | H290: Bradesco 1375 C/C 242867-9 | I290: 713.25 | K290: Provisionado
C291: 46204 | D291: =PROPER(TEXT(C291,"MMMM")) -> Julho | E291: Claudio Luiz Resta Fragelli | F291: 1.4 - Despesas Pessoais | G291: Seguro Veículo parc. 4/8 | H291: Bradesco 3489 C/C 3154-2 | I291: 1048.57 | J291: 46218 | K291: Provisionado
C292: 46204 | D292: =PROPER(TEXT(C292,"MMMM")) -> Julho | E292: Claudio Luiz Resta Fragelli | F292: 1.4 - Despesas Pessoais | G292: Manutenção Conta Bradesco | H292: Bradesco 1375 C/C 242867-9 | I292: 150 | K292: Provisionado
C293: 46204 | D293: =PROPER(TEXT(C293,"MMMM")) -> Julho | E293: Claudio Luiz Resta Fragelli | F293: 1.4 - Despesas Pessoais | G293: Vivo Família Móvel | H293: Bradesco 3489 C/C 3154-2 | I293: 552.86 | K293: Provisionado
C294: 46204 | D294: =PROPER(TEXT(C294,"MMMM")) -> Julho | E294: Claudio Luiz Resta Fragelli | F294: 1.5 - Fazenda Aramburu | G294: Energisa (Fazenda Aramburu) | H294: Bradesco 3489 C/C 3154-2 | I294: 860.91 | K294: Provisionado
C295: 46204 | D295: =PROPER(TEXT(C295,"MMMM")) -> Julho | E295: Claudio Luiz Resta Fragelli | F295: 1.5 - Fazenda Aramburu | G295: Férias - Amadeu Fava Junior | H295: Bradesco 3489 C/C 3154-2 | I295: 3017.63 | K295: Provisionado
C296: 46204 | D296: =PROPER(TEXT(C296,"MMMM")) -> Julho | E296: Claudio Luiz Resta Fragelli | F296: 1.5 - Fazenda Aramburu | G296: Férias - Cristiane da Silva Freire | H296: Bradesco 3489 C/C 3154-2 | I296: 1864.61 | K296: Provisionado
C297: 46204 | D297: =PROPER(TEXT(C297,"MMMM")) -> Julho | E297: Claudio Luiz Resta Fragelli | F297: 1.5 - Fazenda Aramburu | G297: FGTS Folha de Pgto | H297: Bradesco 3489 C/C 3154-2 | I297: 410 | K297: Provisionado
C298: 46204 | D298: =PROPER(TEXT(C298,"MMMM")) -> Julho | E298: Claudio Luiz Resta Fragelli | F298: 1.5 - Fazenda Aramburu | G298: Folha de Pgto - Amadeu Fava Junior | H298: Bradesco 3489 C/C 3154-2 | I298: 2300 | K298: Provisionado
C299: 46204 | D299: =PROPER(TEXT(C299,"MMMM")) -> Julho | E299: Claudio Luiz Resta Fragelli | F299: 1.5 - Fazenda Aramburu | G299: Folha de Pgto - Cristiane da Silva Freire | H299: Bradesco 3489 C/C 3154-2 | I299: 1405 | K299: Provisionado
C300: 46204 | D300: =PROPER(TEXT(C300,"MMMM")) -> Julho | E300: Claudio Luiz Resta Fragelli | F300: 1.5 - Fazenda Aramburu | G300: Folha de Pgto - Gabriel Costa | H300: Bradesco 3489 C/C 3154-2 | I300: 2300 | K300: Provisionado
C301: 46204 | D301: =PROPER(TEXT(C301,"MMMM")) -> Julho | E301: Claudio Luiz Resta Fragelli | F301: 1.5 - Fazenda Aramburu | G301: INSS Folha de Pgto | H301: Bradesco 3489 C/C 3154-2 | I301: 466.34 | K301: Provisionado
C302: 46204 | D302: =PROPER(TEXT(C302,"MMMM")) -> Julho | E302: Claudio Luiz Resta Fragelli | F302: 1.5 - Fazenda Aramburu | G302: Pluxee Multibenefícios - Amadeu Fava Junior | H302: Bradesco 3489 C/C 3154-2 | I302: 450 | K302: Provisionado
C303: 46204 | D303: =PROPER(TEXT(C303,"MMMM")) -> Julho | E303: Claudio Luiz Resta Fragelli | F303: 1.5 - Fazenda Aramburu | G303: Pluxee Multibenefícios - Cristiane da Silva Freire | H303: Bradesco 3489 C/C 3154-2 | I303: 350 | K303: Provisionado
... C324: 46204 | D324: =PROPER(TEXT(C324,"MMMM")) -> Julho | E324: Pedro Henrique Ponte Fragelli | F324: 1.4 - Despesas Pessoais | G324: Curso | H324: XP 0001 C/C 817380-1 | I324: 1000 | K324: Provisionado
...

Sheet Ana Beatriz
K3: ANA BEATRIZ
C11: Sócio | D11: Ana Beatriz Ponte Fragelli
C12: Status | D12: (Tudo)
C14: Soma de Valor | D14: Rótulos de Coluna
C15: Rótulos de Linha | D15: Abril | E15: Total Geral
C16: 1.5 - Fazenda Aramburu | D16: 600 | E16: 600
C17: Pgto Celso José Bazana (Transporte de 01 animal bovino macho_touro) | D17: 600 | E17: 600
C18: 1.6 - Contratos de Venda | D18: 278995.53 | E18: 278995.53
C19: Repasse Venda Soja 24/25 | D19: 278995.53 | E19: 278995.53
C20: Total Geral | D20: 279595.53 | E20: 279595.53

Sheet Cláudio Luiz
M3: CLÁUDIO LUIZ
C10: Sócio | D10: Claudio Luiz Resta Fragelli
C11: Status | D11: (Tudo)
C12: Banco | D12: (Tudo)
C14: Soma de Valor | D14: Rótulos de Coluna
C15: Rótulos de Linha | D15: Maio | E15: Total Geral
C16: 1.4 - Despesas Pessoais | D16: 7400.5 | E16: 7400.5
C17: IRPF 2026 | D17: 6847.64 | E17: 6847.64
C18: Vivo Família Móvel | D18: 552.86 | E18: 552.86
C19: 1.5 - Fazenda Aramburu | D19: 4610.91 | E19: 4610.91
C20: Energisa (Fazenda Aramburu) | D20: 860.91 | E20: 860.91
C21: Serviços Advocatícios Ação Civil Pública nº 0900021-98.2020.8.12.0014 | D21: 3750 | E21: 3750
C22: Total Geral | D22: 12011.41 | E22: 12011.41

Sheet Isamélia
L3: ISAMÉLIA FRAGELLI
C10: Sócio | D10: Isamelia Ponte Fragelli
C11: Status | D11: Realizado
C12: Banco | D12: (Tudo)
C14: Soma de Valor | D14: Rótulos de Coluna
C15: Rótulos de Linha | D15: Abril | E15: Total Geral
C16: 1.1 - Imóvel | D16: 2232.2 | E16: 2232.2
C17: Piscineiro (Forest House CG) | D17: 220 | E17: 220
C18: Jardineiro (Forest House CG) | D18: 400 | E18: 400
C19: Energisa (Forest House CG) | D19: 579.72 | E19: 579.72
C20: Condomínio (Forest House CG) | D20: 900 | E20: 900
C21: Águas Guariroba (Forest House CG) | D21: 132.48 | E21: 132.48
C22: 1.2 - Família | D22: 2905.32 | E22: 2905.32
C23: Folha de Pgto - Zilmar Umbelino de Oliveira | D23: 2200 | E23: 2200
C24: FGTS - Zilmar Umbelino de Oliveira | D24: 507.32 | E24: 507.32
C25: Auxílio Combustível - Zilmar Umbelino de Oliveira | D25: 198 | E25: 198
C26: 1.3 - Renda Mensal/Qualidade de Vida | D26: 11550 | E26: 11550
C27: Medicamentos | D27: 220 | E27: 220
... C32: Total Geral | D32: 17175.83 | E32: 17175.83

Sheet Pedro Henrique
L3: PEDRO HENRIQUE
C11: Sócio | D11: Pedro Henrique Ponte Fragelli
C12: Status | D12: Realizado
C14: Soma de Valor | D14: Rótulos de Coluna
C15: Rótulos de Linha | D15: Abril | E15: Total Geral
C16: 1.1 - Imóvel | D16: 7031 | E16: 7031
C17: Aluguel | D17: 4900 | E17: 4900
C18: Gastos Imóvel | D18: 2131 | E18: 2131
C19: 1.3 - Renda Mensal/Qualidade de Vida | D19: 16300 | E19: 16300
C20: Distribuição Fixa | D20: 5000 | E20: 5000
C21: Custos Emergenciais | D21: 200 | E21: 200
C22: Medicamentos | D22: 100 | E22: 100
C23: Caixa Investimento | D23: 1000 | E23: 1000
C24: Fluxo de Aceleração | D24: 10000 | E24: 10000
C25: 1.4 - Despesas Pessoais | D25: 1990 | E25: 1990
C26: Curso | D26: 1000 | E26: 1000
C27: Troca de bateria veicular | D27: 990 | E27: 990
C28: Total Geral | D28: 25321 | E28: 25321

Sheet LTS
E1: =TODAY() -> 46146 | F1: VENCIDO
F2: VENCE HOJE
F3: EM ABERTO
C6: OC | D6: DATA COMPRA | E6: LOJA | F6: NF | G6: FORMA DE PAGAMENTO | H6: VALOR | I6: VENCIMENTOS | J6: STATUS | K6: TOTAL
C7: 000 | D7: 45818 | E7: ESPAÇO SMART | F7: 2299/8675 | G7: ENTRADA 50% + 4X BOLETOS | H7: 18694.06 | I7: 45819 | J7: PAGO | K7: =SUM(H7:H12) -> 186940.56
H8: 74776.22 | I8: 45820 | J8: PAGO
H9: 23367.57 | I9: 45846 | J9: PAGO
H10: 23367.57 | I10: 45874 | J10: PAGO
H11: 23367.57 | I11: 45902 | J11: PAGO
H12: 23367.57 | I12: 45930 | J12: PAGO
C13: ENTRADA | D13: 45799 | E13: LTS ENGENHARIA | F13: 211 | G13: PIX | H13: 97734.37 | I13: 45800 | J13: PAGO | K13: 97734.37
C14: 001 | D14: 45884 | E14: MADEGRAN | F14: 9963 | G14: 1X BOLETO | H14: 1020 | I14: 45915 | J14: PAGO | K14: =H14 -> 1020
C15: 002/1 | D15: 45902 | E15: TOLDOS MIRASSOL | F15: LOCAÇÃO | G15: 1X BOLETO | H15: 1200 | I15: 45930 | J15: PAGO | K15: =H15 -> 1200
C16: 003/1 | D16: NF CANCELADA | E16: FÊNIX CONTAINERS | F16: LOCAÇÃO | G16: 1X BOLETO | H16: 1300 | I16: 45925 | J16: PAGO | K16: =H16 -> 1300
C17: 004 | D17: 45888 | E17: BICA D'ÁGUA | F17: 267742 | G17: 1X BOLETO | H17: 470.2 | I17: 45918 | J17: PAGO | K17: =H17 -> 470.2
C18: 005 | D18: 45908 | E18: MAGUI MUNCK | F18: 1434 | G18: 1X BOLETO | H18: 1150 | I18: 45912 | J18: PAGO | K18: =H18 -> 1150
C19: 006 | D19: 45891 | E19: MADEGRAN | F19: 9972 | G19: PIX | H19: 2351 | I19: 45922 | J19: PAGO | K19: =H19 -> 2351
C20: 007 | D20: 45897 | E20: DOURATUBOS | F20: 349750 | G20: 2X BOLETO | H20: 2562 | I20: 45926 | J20: PAGO | K20: =SUM(H20:H21) -> 5124
H21: 2562 | I21: 45954 | J21: PAGO
C22: 008 | D22: 45903 | E22: ESTEIO | F22: 108141 | G22: PIX | H22: 4200 | I22: 45903 | J22: PAGO | K22: =H22 -> 4200
C23: 009 | D23: 45904 | E23: LOPES | F23: 900630 | G23: 1X BOLETO | H23: 1416.39 | I23: 45925 | J23: PAGO | K23: =H23 -> 1416.39
C24: 010 | D24: 45781 | E24: AÇOTELHA | F24: 428270 | G24: 1X BOLETO | H24: 28654.93 | I24: 45936 | J24: PAGO | K24: =H24 -> 28654.93
C25: 011 | D25: 45909 | E25: DOURATUBOS | F25: 350907 | G25: 1X BOLETO | H25: 338 | I25: 45939 | J25: PAGO | K25: =H25 -> 338
C26: 012 | D26: 45909 | E26: ALUGA MÁQUINAS | F26: LOCAÇÃO | G26: 1X BOLETO | H26: 120 | I26: 45923 | J26: PAGO | K26: =H26 -> 120
C27: 013 | D27: 45912 | E27: AÇOTELHA | F27: 428584 | G27: 1X BOLETO | H27: 180 | I27: 45933 | J27: PAGO | K27: =H27 -> 180
C28: 014 | D28: 45911 | E28: ESPAÇO SMART | F28: 3636 | G28: 1X BOLETO | H28: 997.5 | I28: 45939 | J28: PAGO | K28: =H28 -> 997.5
C29: 015 | D29: 45915 | E29: MADEGRAN | F29: 9992 | G29: 1X BOLETO | H29: 305 | I29: 45933 | J29: PAGO | K29: =H29 -> 305
C30: MED 001 | D30: 45917 | E30: LTS ENGENHARIA | F30: 238 | G30: PIX | H30: 138885.56 | I30: 45923 | J30: PAGO | K30: =H30 -> 138885.56
C31: 016 | D31: 45918 | E31: WM CONCRETO | F31: 2590 | G31: 2X BOLETO | H31: 15230 | I31: 45932 | J31: PAGO | K31: =SUM(H31:H32) -> 30460
H32: 15230 | I32: 45947 | J32: PAGO
C33: 017 | D33: 45916 | E33: ALUGA MÁQUINAS | F33: LOCAÇÃO | G33: 1X BOLETO | H33: 80 | I33: 45930 | J33: PAGO | K33: =H33 -> 80
C34: 018 | D34: 45922 | E34: DOURATUBOS | F34: 352099 | G34: 1X BOLETO | H34: 561.5 | I34: 45952 | J34: PAGO | K34: =H34 -> 561.5
C35: 019 | D35: 45930 | E35: SOLDAMAQ | F35: 14585 | G35: 1X BOLETO | H35: 310.92 | I35: 45960 | J35: PAGO | K35: =H35 -> 310.92
C36: 020 | D36: 45929 | E36: WM CONCRETO | F36: 2606 | G36: 2X BOLETO | H36: 7677.5 | I36: 45946 | J36: PAGO | K36: =SUM(H36:H37) -> 15355
H37: 7677.5 | I37: 45964 | J37: PAGO
C38: 021 | D38: 45929 | E38: ALUGA MÁQUINAS | F38: ND-019515 | G38: 1X BOLETO | H38: 80 | I38: 45945 | J38: PAGO | K38: 80
C39: 022.1 | D39: 45929 | E39: ALUGA MÁQUINAS | F39: ND-019514 | G39: 1X BOLETO | H39: 1098.4 | I39: 45943 | J39: PAGO | K39: 1098.4
C40: 023 | D40: 45931 | E40: KINGSPAN | F40: 73519 | G40: 20% ENTRADA | H40: 19749.12 | I40: 45932 | J40: PAGO | K40: =SUM(H40:H44) -> 112894.06
G41: 3X BOLETO | H41: 26335.45 | I41: 45986 | J41: PAGO
H42: 26335.45 | I42: 46014 | J42: PAGO
H43: 26325.57 | I43: 46042 | J43: PAGO
G44: DIFAL | H44: 14148.47 | I44: 45986 | J44: PAGO
C45: 003/2 | D45: 45933 | E45: FÊNIX CONTAINERS | F45: ND 3382 | G45: 1X BOLETO | H45: 400 | I45: 45955 | J45: PAGO | K45: =H45 -> 400
C46: 024 | D46: 45939 | E46: ESPAÇO SMART | F46: NF 4084 | G46: 1X BOLETO | H46: 14443.86 | I46: 45967 | J46: PAGO | K46: 14443.86
C47: MED 002 | D47: 45917 | E47: LTS ENGENHARIA | F47: 250 | G47: PIX | H47: 175442.63 | I47: 45923 | J47: PAGO | K47: =H47 -> 175442.63
C48: 025 | D48: 45954 | E48: ESPAÇO SMART | F48: 4386 | G48: 2X BOLETO | H48: 8353.96 | I48: 45982 | J48: PAGO | K48: 4176.98
I49: 46010 | J49: PAGO | K49: 4176.98
C50: 026 | D50: 45961 | E50: PARAÍSO DAS TINTAS | F50: 10964 | G50: 1X BOLETO | H50: 190 | I50: 45992 | J50: PAGO | K50: 190
C51: 027 | D51: 45964 | E51: DOURATUBOS | G51: 1X BOLETO | H51: 127 | I51: 45994 | J51: PAGO | K51: =H51 -> 127
C52: 003/3 | D52: 45961 | E52: FÊNIX CONTAINERS | F52: ND 3435 | G52: 1X BOLETO | H52: 400 | I52: 45986 | J52: PAGO | K52: =H52 -> 400
C53: 022.2 | D53: 45961 | E53: ALUGA MÁQUINAS | F53: ND-019855 | G53: 1X BOLETO | H53: 804 | I53: 45974 | J53: PAGO | K53: =H53 -> 804
C54: MED 003 | D54: 45979 | E54: LTS ENGENHARIA | F54: 256 | G54: PIX | H54: 84116.67 | I54: 45980 | J54: PAGO | K54: =H54 -> 84116.67
C55: 028 | D55: 45982 | E55: SMART CENTER | F55: 10010 | G55: 3X BOLETO | H55: 2583.19 | I55: 46011 | J55: PAGO | K55: =SUM(H55:H57) -> 7749.58
F56: 10010 | G56: 3X BOLETO | H56: 2583.19 | I56: 46039 | J56: PAGO
F57: 10010 | G57: 3X BOLETO | H57: 2583.2 | I57: 46067 | J57: PAGO
F58: 4915 | G58: 3X BOLETO | H58: 6027.45 | I58: 46011 | J58: PAGO | K58: =SUM(H58:H60) -> 18082.34
F59: 4915 | G59: 3X BOLETO | H59: 6027.45 | I59: 46039 | J59: PAGO
F60: 4915 | G60: 3X BOLETO | H60: 6027.44 | I60: 46067 | J60: PAGO
C61: 029 | D61: 45988 | E61: PETEL | F61: - | G61: 1X BOLETO | H61: 117.5 | I61: 46017 | J61: PAGO | K61: =H61 -> 117.5
C62: 030 | D62: 45988 | E62: SMART CENTER | F62: - | G62: 1X BOLETO | H62: 8797.94 | I62: 46027 | J62: PAGO | K62: =H62 -> 8797.94
C63: MED 004 | D63: 45996 | E63: LTS ENGENHARIA | F63: 258 | G63: PIX | H63: 100000.02 | I63: 46000 | J63: PAGO | K63: 119047.64
C64: 022.3 | D64: 45999 | E64: ALUGA MÁQUINAS | F64: ND-020221 | G64: 1X BOLETO | H64: 804 | I64: 46006 | J64: PAGO | K64: =H64 -> 804
C65: 003/4 | D65: 45999 | E65: FÊNIX CONTAINERS | F65: ND 3482 | G65: 1X BOLETO | H65: 400 | I65: 46017 | J65: PAGO | K65: =H65 -> 400
C66: MED 005 | D66: 46008 | E66: LTS ENGENHARIA | F66: 262 | G66: PIX | H66: 31106.38 | I66: 46008 | J66: PAGO | K66: 31106.39
C67: 003/4 | D67: 45999 | E67: FÊNIX CONTAINERS | F67: ND 3538 | G67: 1X BOLETO | H67: 400 | I67: 46048 | J67: PAGO | K67: =H67 -> 400
C68: 022.4 | D68: 45999 | E68: ALUGA MÁQUINAS | F68: ND-020548 | G68: 1X BOLETO | H68: 804 | I68: 46041 | J68: PAGO | K68: =H68 -> 804
C69: 031 | D69: 46031 | E69: SMART CENTER | F69: 5841 | G69: 3X BOLETO | H69: 5194.1 | I69: 46065 | J69: PAGO | K69: =SUM(H69:H71) -> 15582.3
H70: 5194.1 | I70: 46093 | J70: =_xlfn.IFS(I70<$E$1,$F$1,I70>$E$1,$F$3,I70=$E$1,$F$2) -> VENCIDO
H71: 5194.1 | I71: 46124 | J71: =_xlfn.IFS(I71<$E$1,$F$1,I71>$E$1,$F$3,I71=$E$1,$F$2) -> VENCIDO
C72: 022.5 | D72: 46050 | E72: ALUGA MÁQUINAS | F72: ND-020780 | G72: 1X BOLETO | H72: 804 | I72: 46065 | J72: PAGO | K72: =H72 -> 804
C73: 032 | D73: 46052 | E73: BRX | F73: 0.3 | G73: ENTRADA 50% + 1X BOLETO | H73: 1400 | I73: 46056 | J73: PAGO | K73: =H73 -> 1400
H74: 1400 | I74: 46078 | J74: =_xlfn.IFS(I74<$E$1,$F$1,I74>$E$1,$F$3,I74=$E$1,$F$2) -> VENCIDO | K74: =H74 -> 1400
C75: 033 | D75: 46052 | E75: MAZZUCATO | F75: - | G75: PIX 10 DIAS APÓS FINALIZAÇÃO | H75: 500 | I75: 46072 | J75: =_xlfn.IFS(I75<$E$1,$F$1,I75>$E$1,$F$3,I75=$E$1,$F$2) -> VENCIDO | K75: =H75 -> 500
C76: 003/5 | D76: 46056 | E76: FÊNIX CONTAINERS | F76: ND 3597 | G76: 1X BOLETO | H76: 400 | I76: 46078 | J76: =_xlfn.IFS(I76<$E$1,$F$1,I76>$E$1,$F$3,I76=$E$1,$F$2) -> VENCIDO | K76: =H76 -> 400
C77: 034 | D77: 46058 | E77: MAZZUCATO | F77: - | G77: PIX 10 DIAS APÓS FINALIZAÇÃO | H77: 500 | I77: 46072 | J77: =_xlfn.IFS(I77<$E$1,$F$1,I77>$E$1,$F$3,I77=$E$1,$F$2) -> VENCIDO | K77: =H77 -> 500
C78: 022.6 | D78: 46083 | E78: ALUGA MÁQUINAS | F78: ND-021072 | G78: 1X BOLETO | H78: 804 | I78: 46094 | J78: =_xlfn.IFS(I78<$E$1,$F$1,I78>$E$1,$F$3,I78=$E$1,$F$2) -> VENCIDO | K78: =H78 -> 804
C79: 035 | D79: 46084 | E79: FÊNIX CONTAINERS | F79: ND 3648 | G79: 1X BOLETO | H79: 900 | I79: 46106 | J79: =_xlfn.IFS(I79<$E$1,$F$1,I79>$E$1,$F$3,I79=$E$1,$F$2) -> VENCIDO | K79: =H79 -> 900
C80: SOMATÓRIA TOTAL CONTRATO (MAT.) SALDO CONTRATO (MAT.) | K80: =SUM(K7:K79) -> 1127105.2 | L80: TOTAL
K81: 977343.79 | L81: Contrato 01
K82: 59833.34 | L82: Contrato 02
K83: 92400 | L83: Contrato 03
K84: 6150.5 | L84: Outros
K85: =(K81+K82+K83+K84)-K80 -> 8622.43 | L85: Saldo

Sheet $ obra sede
E6: CUSTOS DA OBRA | SEDE
E8: Capital Inicial (Maio/2025) | F8: 1147800
C10: PAGO | F10: =SUM(F11+F15) -> 1748357
E11: Pago 2025 | F11: =SUM(F12:F14) -> 1365471.4
E12: LTS (Medição) | F12: 524574.25
E13: LTS (Ordem de Compra) | F13: 523480.46
E14: Outras | F14: 317416.73
E15: Pago 2026 | F15: =SUM(F16:F18) -> 382885.54
E16: LTS (Medição) | F16: ='obra sede'!I22 -> 24024.64
E17: LTS (Ordem de Compra) | F17: ='obra sede'!I16 -> 75839.09
E18: Outras | F18: =SUM('obra sede'!I66) -> 283021.81
C20: A PAGAR | F20: =SUM(+F21) -> 69851.19
E21: A pagar | F21: =SUM(F22:F24) -> 69851.19
E22: LTS (Medição) | F22: ='obra sede'!I23 -> 0
E23: LTS (Ordem de Compra) | F23: ='obra sede'!I17 -> 0
E24: Outras | F24: =SUM('obra sede'!I67) -> 69851.19
C26: PROVISIONADO | F26: =SUM(F27) -> 115355.98
E27: Provisionados | F27: =SUM(F28:F30) -> 115355.98
E28: LTS (Medição) | F28: =SUM('obra sede'!I24+'obra sede'!I25+'obra sede'!I26+'obra sede'!I27) -> 8622.43
E29: LTS (Ordem de Compra) | F29: ='obra sede'!I18 -> 0
E30: Outras | F30: =SUM('obra sede'!I68) -> 106733.55
E32: Custo total até o momento | F32: =F10+F20+F26 -> 1933564.1
E34: Diferença entre custo total x capital inicial (ou seja, investimento extra necessário além do capital inicial sem considerar o rendimento da aplicação) | F34: =F8-F32 -> -785764.15
E36: Foram realizadas três operações de resgate na conta da XP e uma operação de empréstimo do Sr. Cláudio Fragelli, consideradas como investimentos extras, no valor total de 600 mil, ocorridas respectivamente nos dias 09 e 17 de dezembro de 2025 e 09 e 19 de janeiro de 2026. Do total, 180 mil foram destinados à Sicredi MJU e 419 mil à Sicredi CGR. | F36: =180000+119598.61+100488.96+200084.84 -> 600172.41 | I36: Saldo da conta investimento (conta encerrada) | J36: 0 | L36: | Sicredi Maracaju
I38: Saldo da conta investimento em 30/04/2026 | J38: 212673.87 | L38: | Sicredi Campo Grande
H40: =G40-(G41+G42) -> 0 | I40: A pagar + Provisionado | J40: =SUM(F20+F26) -> 185207.17 | K40: =J40-(J41+J42+J43) -> 0 | L40: =IF(K40=0,"Ok","Valor Incorreto") -> Ok
I41: LTS (Medição) | J41: =SUM(F22+F28) -> 8622.43
I42: LTS (Ordem de Compra) | J42: =SUM(F23+F29) -> 0
I43: Outras | J43: =SUM('obra sede'!I58+'obra sede'!I67+'obra sede'!I68) -> 176584.74
I45: Diferença entre saldo atual da conta investimento x contas a pagar e provisionadas (se negativo, é necessário investimento extra IMEDIATO) | J45: =(J36+J38)-J40 -> 27466.7 | N45: =J36+J38 -> 212673.87
N46: =N45-J40 -> 27466.7 | O46: 32168.81 | P46: =N46-O46 -> -4702.11 | Q46: DESPESAS A MAIS
I47: SICREDI MJU
I48: =-1*SUMPRODUCT((Aramburu_Mensal!$E$6:$E$1160="2.7.2 – Obras e Melhorias (infraestrutura)")*(Aramburu_Mensal!$N$6:$N$1160="A pagar")*((Aramburu_Mensal!$M$6:$M$1160="Cooperativa Sicredi (0902)")*(Aramburu_Mensal!$O$6:$O$1160))) -> 0 | J48: a pagar
I49: =J36-I48 -> 0
I50: =IF(I49>=0,"SALDO SUFICIENTE","SALDO INSUFICIENTE") -> SALDO SUFICIENTE
I53: SICREDI CGR
I54: =-1*SUMPRODUCT((Aramburu_Mensal!$E$6:$E$1160="2.7.2 – Obras e Melhorias (infraestrutura)")*(Aramburu_Mensal!$N$6:$N$1160="A pagar")*((Aramburu_Mensal!$M$6:$M$1160="Cooperativa Sicredi (0913)")+(Aramburu_Mensal!$M$6:$M$1160="Banco Cora (0001)"))*(Aramburu_Mensal!$O$6:$O$1160)) -> 69851.19 | J54: a pagar
I55: =J38-I54 -> 142822.68
I56: =IF(I55>=0,"SALDO SUFICIENTE","SALDO INSUFICIENTE") -> SALDO SUFICIENTE
I58: =SUM(F26) -> 115355.98 | J58: provisionadas
I59: =(J38-I54)-I58 -> 27466.7
I60: =IF(I59>=0,"SALDO SUFICIENTE","SALDO INSUFICIENTE") -> SALDO SUFICIENTE

Sheet day20
B5: Análise de Provisionamento
B6: Distribuição de Lucro
B7: Cláudio Luiz Resta Fragelli
B9: Subitem | C9: 1.1 - Imóvel | D9: =SUM(D10:D16) -> 37583.74
B10: 1.1.1 | C10: IPTU (Atmosphera) | D10: 10476.95 | E10: *
B11: 1.1.2 | C11: IPTU (Casa Vila Inventário) | D11: 1507.96 | E11: *
B12: 1.1.3 | C12: IPTU (Forest House) | D12: 5102.87 | E12: *
B13: 1.1.4 | C13: IPTU (R. Margina Humberlina Lima 80) | D13: 2280.61 | E13: *
B14: 1.1.5 | C14: IPTU (R. Margina Humberlina Lima 90) | D14: 2287.21 | E14: *
B15: 1.1.6 | C15: Manutenção Forest | D15: 2000
B16: 1.1.7 | C16: Parcelamento (Residência SC) | D16: 13928.14
C17: 1.3 - Renda Mensal/Qualidade de Vida | D17: =SUM(D18:D21) -> 4565.99
B18: 1.3.1 | C18: Custos Emergenciais | D18: 300
B19: 1.3.2 | C19: Distribuição Fixa | D19: 3105
B20: 1.3.3 | C20: Medicamentos | D20: 713.25
B21: 1.3.4 | C21: Troca de Celular | D21: 447.74
C22: 1.4 - Despesas Pessoais | D22: =SUM(D23:D26) -> 6724.21
B23: 1.4.1 | C23: IPVA - Triton Sport (SLZ-8B58) | D23: 3731.55 | E23: *
B24: 1.4.2 | C24: Manutenção Conta Bradesco | D24: 150
B25: 1.4.3 | C25: Troca de Pneus | D25: 2300
B26: 1.4.4 | C26: Vivo Família Móvel | D26: 542.66 | E26: *
C27: 1.5 - Fazenda Aramburu | D27: =SUM(D28:D39) -> 15089.26
B28: 1.5.1 | C28: Energisa (Fazenda Aramburu) | D28: 860.91 | E28: *
B29: 1.5.2 | C29: FGTS 13/2025 | D29: 410 | E29: *
B30: 1.5.3 | C30: FGTS Folha de Pgto | D30: 410 | E30: *
B31: 1.5.4 | C31: Folha de Pgto - Amadeu Fava Junior | D31: 2300 | E31: *
B32: 1.5.5 | C32: Folha de Pgto - Cristiane da Silva Freire | D32: 1405 | E32: *
B33: 1.5.6 | C33: Folha de Pgto - Peres Siqueira | D33: 2300 | E33: *
B34: 1.5.7 | C34: INSS Folha de Pgto | D34: 650 | E34: *
B35: 1.5.8 | C35: IPVA - Triton L200 (NRY-0578) | D35: 1753.35 | E35: *
B36: 1.5.9 | C36: Pluxee Multibenefícios - Amadeu Fava Junior | D36: 450
B37: 1.5.10 | C37: Pluxee Multibenefícios - Cristiane da Silva Freire | D37: 350
B38: 1.5.11 | C38: Pluxee Multibenefícios - Peres Siqueira | D38: 450
B39: 1.5.12 | C39: Serviços Advocatícios Ação Civil Pública nº 0900021-98.2020.8.12.0014 | D39: 3750
C40: Total Geral | D40: =SUM(D9+D17+D22+D27) -> 63963.2
B41: * Valor sujeito a alteração.
B50: Análise de Provisionamento
B51: Distribuição de Lucro
B52: Isamélia Ponte Fragelli
B54: Subitem | C54: 1.1 - Imóvel | D54: =SUM(D55:D59) -> 3854.99
B55: 1.1.1 | C55: Piscineiro (Forest House CG) | D55: 210
B56: 1.1.2 | C56: Jardineiro (Forest House CG) | D56: 400
B57: 1.1.3 | C57: Energisa (Forest House CG) | D57: 700 | E57: *
B58: 1.1.4 | C58: Condomínio (Forest House CG) | D58: 1444.99
B59: 1.1.5 | C59: Águas Guariroba (Forest House CG) | D59: 1100 | E59: *
C60: 1.2 - Família | D60: =SUM(D61:D65) -> 7218.79
B61: 1.2.1 | C61: Vale Transporte - Célia Regina de Amorim Apontes | D61: 209 | E61: *
B62: 1.2.2 | C62: Folha de Pgto - Célia Regina de Amorim Apontes | D62: 2000.43 | E62: *
B63: 1.2.3 | C63: FGTS 13/2025 - Célia Regina de Amorim Apontes | D63: 735 | E63: *
B64: 1.2.4 | C64: FGTS - Célia Regina de Amorim Apontes | D64: 735 | E64: *
B65: 1.2.5 | C65: Férias - Célia Regina de Amorim Apontes | D65: 3539.36 | E65: *
C66: 1.3 - Renda Mensal/Qualidade de Vida | D66: =SUM(D67:D69) -> 11550 | E66: *
B67: 1.3.2 | C67: Medicamentos | D67: 220 | E67: *
B68: 1.3.3 | C68: Distribuição Fixa | D68: 11000 | E68: *
B69: 1.3.4 | C69: Custos Emergenciais | D69: 330
C70: 1.4 - Despesas Pessoais | D70: =SUM(D71:D72) -> 4681.85
B71: 1.4.1 | C71: Vivo TV + Internet | D71: 503.34
B72: 1.4.1 | C72: IPVA - Jeep Commander (RWJ-9B92) | D72: 4178.51
C73: Total Geral | D73: =SUM(D54+D60+D66+D70) -> 27305.63
B74: * Valor sujeito a alteração.
B83: Análise de Provisionamento
B84: Distribuição de Lucro
B85: Pedro Henrique Ponte Fragelli
B88: Subitem | C88: 1.1 - Imóvel | D88: =SUM(D89:D90) -> 7031
B89: 1.1.1 | C89: Aluguel | D89: 4900
B90: 1.1.2 | C90: Gastos Imóvel | D90: 2131
C91: 1.3 - Renda Mensal/Qualidade de Vida | D91: =SUM(D92:D95) -> 6300
B92: 1.3.1 | C92: Distribuição Fixa | D92: 5000
B93: 1.3.2 | C93: Custos Emergenciais | D93: 200
B94: 1.3.3 | C94: Medicamentos | D94: 100
B95: 1.3.4 | C95: Caixa Investimento | D95: 1000
C96: 1.4 - Despesas Pessoais | D96: =SUM(D97) -> 3115.84
B97: 1.4.1 | C97: IPVA - Hyundai Creta (RWG-4I21) | D97: 3115.84 | E97: *
C98: Total Geral | D98: =SUM(D88+D96+D91) -> 16446.84
B99: * Valor sujeito a alteração.
B106: Análise de Provisionamento
B107: Distribuição de Lucro
B108: Ana Beatriz Ponte Fragelli
B111: Subitem | C111: 1.6 - Contratos de Venda | D111: =SUM(D112:D112) -> 0
B112: 1.6.1
C113: Total Geral | D113: =SUM(D111) -> 0

Sheet NOTAS EM GRUPO
C9: Data | E9: Referência | F9: Valor
C11: 46102 | D11: Março | E11: Orçamento 003M6G | F11: 880.52
C13: 46102 | D13: Março | E13: NF 201122 | F13: 139.9
C14: 46102 | D14: Março | E14: NF 101496 | F14: 740.62
E16: Valor de notas emitidas | F16: =SUM(F13:F14) -> 880.52
E17: Valor de notas a emitir | F17: =F11-F16 -> 0
C20: O valor total foi parcelado em 6 vezes, por meio do cartão de crédito do Sicredi (agência 0913).

Sheet pendências da obra
C6: PENDÊNCIAS DA OBRA | SEDE | H6: EMPRESA | I6: CONDIÇÃO DE PGTO | J6: VALOR | K6: OBSERVAÇÃO
C8: Pintura
C9: ↳ Material | H9: Total Tintas | I9: Entrada + 30/60d | J9: 36600 | K9: Maracaju
C10: ↳ Mão de Obra | H10: Renato | RP Pinturas | I10: 6.000 quinzenal (2-3 homens) | J10: 45000 | K10: R$ 9.000,00 de INSS Patronal
C12: Granito
C13: ↳ Filetes | H13: Marmoaria Fênix | I13: Parcelado em 8x no cartão de crédito | J13: 18307 | K13: -
C14: ↳ Pingadeiras (janelas)
C15: ↳ Soleiras (portas)
C16: ↳ Bancadas (banheiro, cozinha e área gourmet)
C17: ↳ Rodapés de armários e bancadas
C19: Piso
C20: ↳ Mão de Obra (Sr. Odílio) | H20: Odílio Duarte Fretes | I20: 1º Medição (158,3421 m²) | J20: 9500.52 | K20: R$ 1.900,10 de INSS Patronal
I21: 2º Medição (218,24 mt²) | J21: 13094.4 | K21: R$ 2.618,88 de INSS Patronal
I22: 3º Medição (111 mt² previsto) | J22: 6660 | K22: R$ 1.332,00 de INSS Patronal
C24: Elétrica
C25: ↳ Infraestrutura elétrica | H25: - | I25: - | J25: - | K25: -
C26: ↳ Fiação de ligação da casa (quadro de luz) ao padrão
C27: ↳ Iluminação | H27: DouraLuz | I27: Parcelado em 2x no cartão de crédito | J27: 963 | K27: Dourados
C28: ↳ Luminárias, interruptores e tomadas
C29: ↳ Luminárias, interruptores e tomadas | H29: - | I29: - | J29: - | K29: -
C31: Revestimento
C32: ↳ Lareira | H32: Bica D'Agua | I32: - | J32: - | K32: -
C33: ↳ Churrasqueira | H33: Bica D'Agua | I33: - | J33: - | K33: -
C35: Porta Frontal
C36: ↳ Material/Confecção | H36: Madeireira Guarantã | I36: Parcelado em 6x no boleto | J36: 21750 | K36: Maracaju
C38: Box Banheiros
C39: ↳ Material/Confecção | H39: Vidro Box | I39: 50% entrada + 50% finalização | J39: 4900 | K39: Dourados

Sheet obra sede
C6: LTS ENGENHARIA
C8: Contrato 01 - Obra | I8: 977343.79
C9: Contrato 02 - Obra | I9: 59833.34
C10: Contrato 02 - Obra | I10: 92400
C11: Outros | I11: 6150.5
C12: Total do Contrato - Projeto | I12: 20813.24
I13: =SUM(I8:I12) -> 1156540.9
C15: Ordem de Compra
C16: Pago | I16: =-1*(SUMIFS(Aramburu_Mensal!$O$6:$O$1251,Aramburu_Mensal!$E$6:$E$1251,"2.7.2 – Obras e Melhorias (infraestrutura)",Aramburu_Mensal!$I$6:$I$1251,"Ordem de Compra",Aramburu_Mensal!$N$6:$N$1251,"Pago")+SUMIFS(Aramburu_Mensal!$O$6:$O$1251,Aramburu_Mensal!$E$6:$E$1251,"2.7.2 – Obras e Melhorias (infraestrutura)",Aramburu_Mensal!$I$6:$I$1251,"Projeto",Aramburu_Mensal!$N$6:$N$1251,"Pago")) -> 75839.09
C17: A pagar | I17: =-1*(SUMIFS(Aramburu_Mensal!$O$6:$O$1251,Aramburu_Mensal!$E$6:$E$1251,"2.7.2 – Obras e Melhorias (infraestrutura)",Aramburu_Mensal!$I$6:$I$1251,"Ordem de Compra",Aramburu_Mensal!$N$6:$N$1251,"A pagar")+SUMIFS(Aramburu_Mensal!$O$6:$O$1251,Aramburu_Mensal!$E$6:$E$1251,"2.7.2 – Obras e Melhorias (infraestrutura)",Aramburu_Mensal!$I$6:$I$1251,"Projeto",Aramburu_Mensal!$N$6:$N$1251,"A pagar")) -> 0
C18: Provisionado | I18: =-1*(SUMIFS(Aramburu_Mensal!$O$6:$O$1251,Aramburu_Mensal!$E$6:$E$1251,"2.7.2 – Obras e Melhorias (infraestrutura)",Aramburu_Mensal!$I$6:$I$1251,"Ordem de Compra",Aramburu_Mensal!$N$6:$N$1251,"Provisionado")+SUMIFS(Aramburu_Mensal!$O$6:$O$1251,Aramburu_Mensal!$E$6:$E$1251,"2.7.2 – Obras e Melhorias (infraestrutura)",Aramburu_Mensal!$I$6:$I$1251,"Projeto",Aramburu_Mensal!$N$6:$N$1251,"Provisionado")) -> 0
I19: =SUM(I16:I18) -> 75839.09
C21: Medições
C22: Pago | I22: =-1*(SUMIFS(Aramburu_Mensal!$O$6:$O$1251,Aramburu_Mensal!$E$6:$E$1251,"2.7.2 – Obras e Melhorias (infraestrutura)",Aramburu_Mensal!$I$6:$I$1251,"Medição 04",Aramburu_Mensal!$N$6:$N$1251,"Pago"))+(-1*(SUMIFS(Aramburu_Mensal!$O$6:$O$1251,Aramburu_Mensal!$E$6:$E$1251,"2.7.2 – Obras e Melhorias (infraestrutura)",Aramburu_Mensal!$I$6:$I$1251,"Medição 05",Aramburu_Mensal!$N$6:$N$1251,"Pago")))+(-1*(SUMIFS(Aramburu_Mensal!$O$6:$O$1251,Aramburu_Mensal!$E$6:$E$1251,"2.7.2 – Obras e Melhorias (infraestrutura)",Aramburu_Mensal!$I$6:$I$1251,"Medição 06",Aramburu_Mensal!$N$6:$N$1251,"Pago")))+(-1*(SUMIFS(Aramburu_Mensal!$O$6:$O$1251,Aramburu_Mensal!$E$6:$E$1251,"2.7.2 – Obras e Melhorias (infraestrutura)",Aramburu_Mensal!$I$6:$I$1251,"Retenção",Aramburu_Mensal!$N$6:$N$1251,"Pago"))) -> 24024.64
C23: A pagar | I23: =-1*(SUMIFS(Aramburu_Mensal!$O$6:$O$1251,Aramburu_Mensal!$E$6:$E$1251,"2.7.2 – Obras e Melhorias (infraestrutura)",Aramburu_Mensal!$I$6:$I$1251,"Medição 04",Aramburu_Mensal!$N$6:$N$1251,"A pagar"))+(-1*(SUMIFS(Aramburu_Mensal!$O$6:$O$1251,Aramburu_Mensal!$E$6:$E$1251,"2.7.2 – Obras e Melhorias (infraestrutura)",Aramburu_Mensal!$I$6:$I$1251,"Medição 05",Aramburu_Mensal!$N$6:$N$1251,"A pagar")))+(-1*(SUMIFS(Aramburu_Mensal!$O$6:$O$1251,Aramburu_Mensal!$E$6:$E$1251,"2.7.2 – Obras e Melhorias (infraestrutura)",Aramburu_Mensal!$I$6:$I$1251,"Medição 06",Aramburu_Mensal!$N$6:$N$1251,"A pagar")))+(-1*(SUMIFS(Aramburu_Mensal!$O$6:$O$1251,Aramburu_Mensal!$E$6:$E$1251,"2.7.2 – Obras e Melhorias (infraestrutura)",Aramburu_Mensal!$I$6:$I$1251,"Retenção",Aramburu_Mensal!$N$6:$N$1251,"A pagar"))) -> 0
C24: Provisionado (Medição 04) | I24: =-1*(SUMIFS(Aramburu_Mensal!$O$6:$O$1251,Aramburu_Mensal!$E$6:$E$1251,"2.7.2 – Obras e Melhorias (infraestrutura)",Aramburu_Mensal!$I$6:$I$1251,"Medição 04",Aramburu_Mensal!$N$6:$N$1251,"Provisionado")) -> 0
C25: Provisionado (Medição 05) | I25: =-1*(SUMIFS(Aramburu_Mensal!$O$6:$O$1251,Aramburu_Mensal!$E$6:$E$1251,"2.7.2 – Obras e Melhorias (infraestrutura)",Aramburu_Mensal!$I$6:$I$1251,"Medição 05",Aramburu_Mensal!$N$6:$N$1251,"Provisionado")) -> 0
C26: Provisionado (Medição 06) | I26: =-1*(SUMIFS(Aramburu_Mensal!$O$6:$O$1251,Aramburu_Mensal!$E$6:$E$1251,"2.7.2 – Obras e Melhorias (infraestrutura)",Aramburu_Mensal!$I$6:$I$1251,"Medição 06",Aramburu_Mensal!$N$6:$N$1251,"Provisionado")) -> 8622.43
C27: Provisionado (Retenção) | I27: =-1*(SUMIFS(Aramburu_Mensal!$O$6:$O$1251,Aramburu_Mensal!$E$6:$E$1251,"2.7.2 – Obras e Melhorias (infraestrutura)",Aramburu_Mensal!$I$6:$I$1251,"Retenção",Aramburu_Mensal!$N$6:$N$1251,"Provisionado")) -> 0
I28: =SUM(I22:I27) -> 32647.07
C30: Valor Planilha LTS | I30: =LTS!K80 -> 1127105.2
C32: Validação x Planilha LTS | H32: =(I16+I17+I18+I22+I23+I24+I25+I35+I38+I41+I44+I47+I50+I53)-(I12+I30) -> 0 | I32: =IF(H32=0,"Ok","Valor Incorreto") -> Ok
I34: 2025
C35: Projeto | H35: =SUM(H36:H37) -> 20813.24 | I35: 20813.24
C36: Pago | H36: =-1*(SUMPRODUCT(([1]Aramburu_Mensal!$E$6:$E$935="2.7.2 – Obras e Melhorias (infraestrutura)")*([1]Aramburu_Mensal!$N$6:$N$935="Pago")*((([1]Aramburu_Mensal!$I$6:$I$935="Projeto")*([1]Aramburu_Mensal!$O$6:$O$935))))) -> 20813.24 | I36: 20813.24
C37: A pagar | H37: =-1*(SUMPRODUCT(([1]Aramburu_Mensal!$E$6:$E$935="2.7.2 – Obras e Melhorias (infraestrutura)")*([1]Aramburu_Mensal!$N$6:$N$935="A pagar")*((([1]Aramburu_Mensal!$I$6:$I$935="Projeto")*([1]Aramburu_Mensal!$O$6:$O$935))))) -> 0 | I37: 0
C38: Ordem de Compra | H38: =SUM(H39:H40) -> 502667.22 | I38: 502667.22
C39: Pago | H39: =-1*(SUMPRODUCT(([1]Aramburu_Mensal!$E$6:$E$935="2.7.2 – Obras e Melhorias (infraestrutura)")*([1]Aramburu_Mensal!$N$6:$N$935="Pago")*((([1]Aramburu_Mensal!$I$6:$I$935="Ordem de Compra")*([1]Aramburu_Mensal!$O$6:$O$935))))) -> 502667.22 | I39: 502667.22
C40: A pagar | H40: =-1*(SUMPRODUCT(([1]Aramburu_Mensal!$E$6:$E$935="2.7.2 – Obras e Melhorias (infraestrutura)")*([1]Aramburu_Mensal!$N$6:$N$935="A pagar")*((([1]Aramburu_Mensal!$I$6:$I$935="Ordem de Compra")*([1]Aramburu_Mensal!$O$6:$O$935))))) -> 0 | I40: 0
C41: Medição 01 | H41: =SUM(H42:H43) -> 138885.56 | I41: 138885.56
C42: Pago | H42: =-1*(SUMPRODUCT(([1]Aramburu_Mensal!$E$6:$E$935="2.7.2 – Obras e Melhorias (infraestrutura)")*([1]Aramburu_Mensal!$N$6:$N$935="Pago")*((([1]Aramburu_Mensal!$I$6:$I$935="Medição 01")*([1]Aramburu_Mensal!$O$6:$O$935))))) -> 138885.56 | I42: 138885.56
C43: A pagar | H43: =-1*(SUMPRODUCT(([1]Aramburu_Mensal!$E$6:$E$935="2.7.2 – Obras e Melhorias (infraestrutura)")*([1]Aramburu_Mensal!$N$6:$N$935="A pagar")*((([1]Aramburu_Mensal!$I$6:$I$935="Medição 01")*([1]Aramburu_Mensal!$O$6:$O$935))))) -> 0 | I43: 0
C44: Medição 02 | H44: =SUM(H45:H46) -> 175442.63 | I44: 175442.63
C45: Pago | H45: =-1*(SUMPRODUCT(([1]Aramburu_Mensal!$E$6:$E$935="2.7.2 – Obras e Melhorias (infraestrutura)")*([1]Aramburu_Mensal!$N$6:$N$935="Pago")*((([1]Aramburu_Mensal!$I$6:$I$935="Medição 02")*([1]Aramburu_Mensal!$O$6:$O$935))))) -> 175442.63 | I45: 175442.63
C46: A pagar | H46: =-1*(SUMPRODUCT(([1]Aramburu_Mensal!$E$6:$E$935="2.7.2 – Obras e Melhorias (infraestrutura)")*([1]Aramburu_Mensal!$N$6:$N$935="A pagar")*((([1]Aramburu_Mensal!$I$6:$I$935="Medição 02")*([1]Aramburu_Mensal!$O$6:$O$935))))) -> 0 | I46: 0
C47: Medição 03 | H47: =SUM(H48:H49) -> 84116.67 | I47: 84116.67
C48: Pago | H48: =-1*(SUMPRODUCT(([1]Aramburu_Mensal!$E$6:$E$935="2.7.2 – Obras e Melhorias (infraestrutura)")*([1]Aramburu_Mensal!$N$6:$N$935="Pago")*((([1]Aramburu_Mensal!$I$6:$I$935="Medição 03")*([1]Aramburu_Mensal!$O$6:$O$935))))) -> 84116.67 | I48: 84116.67
C49: A pagar | H49: =-1*(SUMPRODUCT(([1]Aramburu_Mensal!$E$6:$E$935="2.7.2 – Obras e Melhorias (infraestrutura)")*([1]Aramburu_Mensal!$N$6:$N$935="A pagar")*((([1]Aramburu_Mensal!$I$6:$I$935="Medição 03")*([1]Aramburu_Mensal!$O$6:$O$935))))) -> 0 | I49: 0
C50: Medição 04 | H50: =SUM(H51:H52) -> 100000.02 | I50: 100000.02
C51: Pago | H51: =-1*(SUMPRODUCT(([1]Aramburu_Mensal!$E$6:$E$935="2.7.2 – Obras e Melhorias (infraestrutura)")*([1]Aramburu_Mensal!$N$6:$N$935="Pago")*((([1]Aramburu_Mensal!$I$6:$I$935="Medição 04")*([1]Aramburu_Mensal!$O$6:$O$935))))) -> 100000.02 | I51: 100000.02
C52: A pagar | H52: =-1*(SUMPRODUCT(([1]Aramburu_Mensal!$E$6:$E$935="2.7.2 – Obras e Melhorias (infraestrutura)")*([1]Aramburu_Mensal!$N$6:$N$935="A pagar")*((([1]Aramburu_Mensal!$I$6:$I$935="Medição 04")*([1]Aramburu_Mensal!$O$6:$O$935))))) -> 0 | I52: 0
C53: Medição 05 | H53: =SUM(H54:H55) -> 26129.37 | I53: 26129.37
C54: Pago | H54: =-1*(SUMPRODUCT(([1]Aramburu_Mensal!$E$6:$E$935="2.7.2 – Obras e Melhorias (infraestrutura)")*([1]Aramburu_Mensal!$N$6:$N$935="Pago")*((([1]Aramburu_Mensal!$I$6:$I$935="Medição 05")*([1]Aramburu_Mensal!$O$6:$O$935))))) -> 26129.37 | I54: 26129.37
C55: A pagar | H55: =-1*(SUMPRODUCT(([1]Aramburu_Mensal!$E$6:$E$935="2.7.2 – Obras e Melhorias (infraestrutura)")*([1]Aramburu_Mensal!$N$6:$N$935="A pagar")*((([1]Aramburu_Mensal!$I$6:$I$935="Medição 05")*([1]Aramburu_Mensal!$O$6:$O$935))))) -> 0 | I55: 0
C56: Outras Despesas | H56: =SUM(H57:H58) -> 317416.73 | I56: 317416.73
C57: Pago | H57: =-1*(SUMPRODUCT(([1]Aramburu_Mensal!$E$6:$E$935="2.7.2 – Obras e Melhorias (infraestrutura)")*([1]Aramburu_Mensal!$N$6:$N$935="Pago")*((([1]Aramburu_Mensal!$I$6:$I$935="Outras")*([1]Aramburu_Mensal!$O$6:$O$935))))) -> 317416.73 | I57: 317416.73
C58: A pagar | H58: =-1*(SUMPRODUCT(([1]Aramburu_Mensal!$E$6:$E$935="2.7.2 – Obras e Melhorias (infraestrutura)")*([1]Aramburu_Mensal!$N$6:$N$935="A pagar")*((([1]Aramburu_Mensal!$I$6:$I$935="Outras")*([1]Aramburu_Mensal!$O$6:$O$935))))) -> 0 | I58: 0
H60: =SUM(H35+H38+H41+H44+H47+H50+H53+H56) -> 1365471.4 | I60: 1365471.4
C62: Validação x Contrato da LTS | H62: =(I19+I28+I35+I38+I41+I44+I47+I50+I53)-I13 -> 0 | I62: =IF(H62=0,"Ok","Valor Incorreto") -> Ok
C64: OUTRAS DESPESAS
C66: Pago | I66: =-1*(SUMIFS(Aramburu_Mensal!$O$6:$O$1242,Aramburu_Mensal!$E$6:$E$1242,"2.7.2 – Obras e Melhorias (infraestrutura)",Aramburu_Mensal!$I$6:$I$1242,"Outras",Aramburu_Mensal!$N$6:$N$1242,"Pago")) -> 283021.81
C67: A pagar | I67: =-1*(SUMIFS(Aramburu_Mensal!$O$6:$O$1242,Aramburu_Mensal!$E$6:$E$1242,"2.7.2 – Obras e Melhorias (infraestrutura)",Aramburu_Mensal!$I$6:$I$1242,"Outras",Aramburu_Mensal!$N$6:$N$1242,"A pagar")) -> 69851.19
C68: Provisionado | I68: =-1*(SUMIFS(Aramburu_Mensal!$O$6:$O$1242,Aramburu_Mensal!$E$6:$E$1242,"2.7.2 – Obras e Melhorias (infraestrutura)",Aramburu_Mensal!$I$6:$I$1242,"Outras",Aramburu_Mensal!$N$6:$N$1242,"Provisionado")) -> 106733.55
I69: =SUM(I66:I68) -> 459606.55
C72: TOTAL
C74: Pago | I74: =-1*(SUMIFS(Aramburu_Mensal!$O$6:$O$1242,Aramburu_Mensal!$E$6:$E$1242,"2.7.2 – Obras e Melhorias (infraestrutura)",Aramburu_Mensal!$F$6:$F$1242,"Despesas Eventuais",Aramburu_Mensal!$N$6:$N$1242,"Pago")) -> 382885.54
C75: A pagar | I75: =-1*(SUMIFS(Aramburu_Mensal!$O$6:$O$1242,Aramburu_Mensal!$E$6:$E$1242,"2.7.2 – Obras e Melhorias (infraestrutura)",Aramburu_Mensal!$F$6:$F$1242,"Despesas Eventuais",Aramburu_Mensal!$N$6:$N$1242,"A pagar")) -> 69851.19
C76: Provisionado | I76: =-1*(SUMIFS(Aramburu_Mensal!$O$6:$O$1242,Aramburu_Mensal!$E$6:$E$1242,"2.7.2 – Obras e Melhorias (infraestrutura)",Aramburu_Mensal!$F$6:$F$1242,"Despesas Eventuais",Aramburu_Mensal!$N$6:$N$1242,"Provisionado")) -> 115355.98
I77: =SUM(I74:I76) -> 568092.71
C79: Validação do Valor total | H79: =(I19+I28+I69)-I77 -> 0 | I79: =IF(H79=0,"Ok","Valor Incorreto") -> Ok
